Workbook

Sheet Dashboard
A1: TOTALS | I1: EARNINGS
A2: Type | B2: Total Open | C2: %Portfolio | I2: Type | J2: Total Open | K2: % Open
A3: CASH | B3: 761 | C3: =if($A3=0,"",$B3/$F$14) -> 0.098446515 | I3: CEDEAR | J3: =IFNA(CEDEARs!AF22,0) -> 1074.7897 | K3: =J3/F14 -> 0.13903982
A4: CEDEAR | B4: =IFNA(CEDEARs!AF20,0) -> 3650.6595 | C4: =if($A4=0,"",$B4/$F$14) -> 0.47226637 | I4: BOND | J4: =IFNA(Bonds!AL20,0) -> 863.47705 | K4: =J4/F14 -> 0.11170343
A5: BOND | B5: =IFNA(Bonds!AL18,0) -> 1340.4354 | C5: =if($A5=0,"",$B5/$F$14) -> 0.17340498 | I5: ON | J5: =IFNA(ONs!AH20,0) -> 283.94694 | K5: =$J5/$F$14 -> 0.036732703
A6: ON | B6: =IFNA(ONs!AH18,0) -> 1533.8601 | C6: =if($A6=0,"",$B6/$F$14) -> 0.19842731 | I6: FCI | J6: =IFNA(FCIs!AH20,0) -> 0 | K6: =$J6/$F$14 -> 0
A7: FCI | B7: =IFNA(FCIs!AH18,0) -> 0 | C7: =if($A7=0,"",$B7/$F$14) -> 0 | I7: Crypto | J7: =IFNA(Cryptos!Y22,0) -> 175.00669 | K7: =$J7/$F$14 -> 0.022639683
A8: Crypto | B8: =IFNA(Cryptos!Y20,0) -> 444.1307 | C8: =if($A8=0,"",$B8/$F$14) -> 0.057454822 | K8: =$J8/$F$14 -> 0
C9: =if($A9=0,"",$B9/$F$14) | K9: =$J9/$F$14 -> 0
C10: =if($A10=0,"",$B10/$F$14) | K10: =$J10/$F$14 -> 0
C11: =if($A11=0,"",$B11/$F$14) | K11: =$J11/$F$14 -> 0
C12: =if($A12=0,"",$B12/$F$14) | K12: =$J12/$F$14 -> 0
E14: Total U$D | F14: =SUM(B3:B12) -> 7730.0857 | I14: Total U$D | J14: =SUM(J3:J12) -> 2397.2204 | K14: =J14/F14 -> 0.31011563
K15: a

Sheet CEDEARs
A1: ID | B1: Ticker | C1: Apertura | D1: Estado | E1: Cierre | F1: Dias | G1: Moneda | H1: Unidades | I1: Valor Compra | J1: Valor Venta | K1: Valor Actual | L1: Total Compra | M1: CCL Compra | N1: TC USD | O1: Total Venta | P1: CCL Venta | Q1: TV USD | R1: GAN USD% | S1: GAN USD | T1: Ganancias (%) | U1: Ganancias Bruta | W1: CEDEAR Ticker | X1: Unidades | Y1: % Cartera | Z1: PPC | AA1: Total (Abierto) | AB1: Ganancias (%) | AC1: Ganancias Tot
A2: IOL | B2: AAPL | C2: 44939 | D2: ABIERTA | F2: =if($B2=0,"...", IF($E2=0,today()-$C2,$E2-$C2)) -> 1057 | G2: PESOS | H2: 20 | I2: 4374 | K2: =IFERROR(__xludf.DUMMYFUNCTION("if(B2=0,""..."",IF($G2=""PESOS"",GOOGLEFINANCE(""BCBA:""&$B2),GOOGLEFINANCE($B2)/20))"),21040.0) -> 21040 | L2: =if(B2=0,"...",$H2*I2) -> 87480 | M2: =VLOOKUP(C2,CCLHistory!$A$3:$B84,2,FALSE) -> 349,26 | N2: =L2/IF(G2="USD",1,M2) -> 250.47243 | O2: =if(B2=0,"...",$H2*(IF(D2="ABIERTA",K2,J2)*(1-VLOOKUP(A2,Config!$A$3:$B$5,2,FALSE)))) -> 420778.96 | P2: =IF(D2="ABIERTA",Config!$D$4,VLOOKUP(E2,CCLHistory!$A$6:$B84,2,FALSE)) -> 1269 | Q2: =O2/IF(G2="USD",1,P2) -> 331.5831 | R2: =if(B2=0,"...",Q2/N2-1) -> 0.32383076 | S2: =if(B2=0,"...",Q2-N2) -> 81.110677 | T2: =if(B2=0,"...",O2/L2-1) -> 3.8100018 | U2: =if(B2=0,"...",O2-L2) -> 333298.96 | W2: {=Unique(B2:B84)} -> AAPL | X2: =if(W2=0,"...",sumifs($H$2:$H84,$B$2:$B84,W2,$D$2:$D84,"ABIERTA")) -> 32 | Y2: =if(W2=0,"",AA2/$AF$20) -> 0.13686806 | Z2: =if(X2=0,"...",if(W2=0,"...",sumifs($N$2:$N84,$B$2:$B84,W2,$D$2:$D84,"ABIERTA")/X2)) -> 11.417888 | AA2: =if(W2=0,"...",sumifs($Q$2:$Q84,$B$2:$B84,W2,$D$2:$D84,"ABIERTA")) -> 499.6587 | AB2: =if(X2=0,"...",if(W2=0,"...",AC2/(AA2-AC2))) -> 0.36753259 | AC2: =if(X2=0,"...",if(W2=0,"...",sumifs($S$2:$S84,$B$2:$B84,W2,$D$2:$D84,"ABIERTA"))) -> 134.28627
A3: IOL | B3: AAPL | C3: 45301 | D3: ABIERTA | F3: =if($B3=0,"...", IF($E3=0,today()-$C3,$E3-$C3)) -> 695 | G3: USD | H3: 10 | I3: 9.625 | K3: =IFERROR(__xludf.DUMMYFUNCTION("if(B3=0,""..."",IF($G3=""PESOS"",GOOGLEFINANCE(""BCBA:""&$B3),GOOGLEFINANCE($B3)/20))"),14.007) -> 14.007 | L3: =if(B3=0,"...",$H3*I3) -> 96.25 | M3: =VLOOKUP(C3,CCLHistory!$A$3:$B84,2,FALSE) -> 1182.72 | N3: =L3/IF(G3="USD",1,M3) -> 96.25 | O3: =if(B3=0,"...",$H3*(IF(D3="ABIERTA",K3,J3)*(1-VLOOKUP(A3,Config!$A$3:$B$5,2,FALSE)))) -> 140.063 | P3: =IF(D3="ABIERTA",Config!$D$4,VLOOKUP(E3,CCLHistory!$A$6:$B84,2,FALSE)) -> 1269 | Q3: =O3/IF(G3="USD",1,P3) -> 140.063 | R3: =if(B3=0,"...",Q3/N3-1) -> 0.45519996 | S3: =if(B3=0,"...",Q3-N3) -> 43.812996 | T3: =if(B3=0,"...",O3/L3-1) -> 0.45519996 | U3: =if(B3=0,"...",O3-L3) -> 43.812996 | W3: KO | X3: =if(W3=0,"...",sumifs($H$2:$H85,$B$2:$B85,W3,$D$2:$D85,"ABIERTA")) -> 128 | Y3: =if(W3=0,"",AA3/$AF$20) -> 0.58627406 | Z3: =if(X3=0,"...",if(W3=0,"...",sumifs($N$2:$N85,$B$2:$B85,W3,$D$2:$D85,"ABIERTA")/X3)) -> 12.214398 | AA3: =if(W3=0,"...",sumifs($Q$2:$Q85,$B$2:$B85,W3,$D$2:$D85,"ABIERTA")) -> 2140.287 | AB3: =if(X3=0,"...",if(W3=0,"...",AC3/(AA3-AC3))) -> 0.36895749 | AC3: =if(X3=0,"...",if(W3=0,"...",sumifs($S$2:$S85,$B$2:$B85,W3,$D$2:$D85,"ABIERTA"))) -> 576.844
A4: IOL | B4: AAPL | C4: 45210 | D4: ABIERTA | F4: =if($B4=0,"...", IF($E4=0,today()-$C4,$E4-$C4)) -> 786 | G4: USD | H4: 2 | I4: 9.325 | K4: =IFERROR(__xludf.DUMMYFUNCTION("if(B4=0,""..."",IF($G4=""PESOS"",GOOGLEFINANCE(""BCBA:""&$B4),GOOGLEFINANCE($B4)/20))"),14.007) -> 14.007 | L4: =if(B4=0,"...",$H4*I4) -> 18.65 | M4: =VLOOKUP(C4,CCLHistory!$A$3:$B84,2,FALSE) -> 944,94 | N4: =L4/IF(G4="USD",1,M4) -> 18.65 | O4: =if(B4=0,"...",$H4*(IF(D4="ABIERTA",K4,J4)*(1-VLOOKUP(A4,Config!$A$3:$B$5,2,FALSE)))) -> 28.012599 | P4: =IF(D4="ABIERTA",Config!$D$4,VLOOKUP(E4,CCLHistory!$A$6:$B84,2,FALSE)) -> 1269 | Q4: =O4/IF(G4="USD",1,P4) -> 28.012599 | R4: =if(B4=0,"...",Q4/N4-1) -> 0.50201605 | S4: =if(B4=0,"...",Q4-N4) -> 9.3625993 | T4: =if(B4=0,"...",O4/L4-1) -> 0.50201605 | U4: =if(B4=0,"...",O4-L4) -> 9.3625993 | W4: DISN | X4: =if(W4=0,"...",sumifs($H$2:$H86,$B$2:$B86,W4,$D$2:$D86,"ABIERTA")) -> 6 | Y4: =if(W4=0,"",AA4/$AF$20) -> 0.017159809 | Z4: =if(X4=0,"...",if(W4=0,"...",sumifs($N$2:$N86,$B$2:$B86,W4,$D$2:$D86,"ABIERTA")/X4)) -> 7.6472113 | AA4: =if(W4=0,"...",sumifs($Q$2:$Q86,$B$2:$B86,W4,$D$2:$D86,"ABIERTA")) -> 62.644622 | AB4: =if(X4=0,"...",if(W4=0,"...",AC4/(AA4-AC4))) -> 0.36530428 | AC4: =if(X4=0,"...",if(W4=0,"...",sumifs($S$2:$S86,$B$2:$B86,W4,$D$2:$D86,"ABIERTA"))) -> 16.761354
A5: IOL | B5: KO | C5: 44138 | D5: ABIERTA | F5: =if($B5=0,"...", IF($E5=0,today()-$C5,$E5-$C5)) -> 1858 | G5: PESOS | H5: 1 | I5: 1477 | K5: =IFERROR(__xludf.DUMMYFUNCTION("if(B5=0,""..."",GOOGLEFINANCE(""BCBA:""&B5))"),21220.0) -> 21220 | L5: =if(B5=0,"...",$H5*I5) -> 1477 | M5: =VLOOKUP(C5,CCLHistory!$A$3:$B84,2,FALSE) -> 153,9 | N5: =L5/IF(G5="USD",1,M5) -> 9.597141 | O5: =if(B5=0,"...",$H5*(IF(D5="ABIERTA",K5,J5)*(1-VLOOKUP(A5,Config!$A$3:$B$5,2,FALSE)))) -> 21218.939 | P5: =IF(D5="ABIERTA",Config!$D$4,VLOOKUP(E5,CCLHistory!$A$6:$B84,2,FALSE)) -> 1269 | Q5: =O5/IF(G5="USD",1,P5) -> 16.720992 | R5: =if(B5=0,"...",Q5/N5-1) -> 0.74228889 | S5: =if(B5=0,"...",Q5-N5) -> 7.1238511 | T5: =if(B5=0,"...",O5/L5-1) -> 13.366242 | U5: =if(B5=0,"...",O5-L5) -> 19741.939 | W5: DIA | X5: =if(W5=0,"...",sumifs($H$2:$H87,$B$2:$B87,W5,$D$2:$D87,"ABIERTA")) -> 19 | Y5: =if(W5=0,"",AA5/$AF$20) -> 0.14821327 | Z5: =if(X5=0,"...",if(W5=0,"...",sumifs($N$2:$N87,$B$2:$B87,W5,$D$2:$D87,"ABIERTA")/X5)) -> 20.211455 | AA5: =if(W5=0,"...",sumifs($Q$2:$Q87,$B$2:$B87,W5,$D$2:$D87,"ABIERTA")) -> 541.07618 | AB5: =if(X5=0,"...",if(W5=0,"...",AC5/(AA5-AC5))) -> 0.40898782 | AC5: =if(X5=0,"...",if(W5=0,"...",sumifs($S$2:$S87,$B$2:$B87,W5,$D$2:$D87,"ABIERTA"))) -> 157.05854
A6: IOL | B6: KO | C6: 44148 | D6: ABIERTA | F6: =if($B6=0,"...", IF($E6=0,today()-$C6,$E6-$C6)) -> 1848 | G6: PESOS | H6: 1 | I6: 1605 | K6: =IFERROR(__xludf.DUMMYFUNCTION("if(B6=0,""..."",GOOGLEFINANCE(""BCBA:""&B6))"),21220.0) -> 21220 | L6: =if(B6=0,"...",$H6*I6) -> 1605 | M6: =VLOOKUP(C6,CCLHistory!$A$3:$B84,2,FALSE) -> 148,74 | N6: =L6/IF(G6="USD",1,M6) -> 10.790641 | O6: =if(B6=0,"...",$H6*(IF(D6="ABIERTA",K6,J6)*(1-VLOOKUP(A6,Config!$A$3:$B$5,2,FALSE)))) -> 21218.939 | P6: =IF(D6="ABIERTA",Config!$D$4,VLOOKUP(E6,CCLHistory!$A$6:$B84,2,FALSE)) -> 1269 | Q6: =O6/IF(G6="USD",1,P6) -> 16.720992 | R6: =if(B6=0,"...",Q6/N6-1) -> 0.54958278 | S6: =if(B6=0,"...",Q6-N6) -> 5.9303507 | T6: =if(B6=0,"...",O6/L6-1) -> 12.220523 | U6: =if(B6=0,"...",O6-L6) -> 19613.939 | W6: SPY | X6: =if(W6=0,"...",sumifs($H$2:$H88,$B$2:$B88,W6,$D$2:$D88,"ABIERTA")) -> 10 | Y6: =if(W6=0,"",AA6/$AF$20) -> 0.1114848 | Z6: =if(X6=0,"...",if(W6=0,"...",sumifs($N$2:$N88,$B$2:$B88,W6,$D$2:$D88,"ABIERTA")/X6)) -> 21.715348 | AA6: =if(W6=0,"...",sumifs($Q$2:$Q88,$B$2:$B88,W6,$D$2:$D88,"ABIERTA")) -> 406.99305 | AB6: =if(X6=0,"...",if(W6=0,"...",AC6/(AA6-AC6))) -> 0.87421843 | AC6: =if(X6=0,"...",if(W6=0,"...",sumifs($S$2:$S88,$B$2:$B88,W6,$D$2:$D88,"ABIERTA"))) -> 189.83957
A7: IOL | B7: KO | C7: 44151 | D7: ABIERTA | F7: =if($B7=0,"...", IF($E7=0,today()-$C7,$E7-$C7)) -> 1845 | G7: PESOS | H7: 1 | I7: 1580 | K7: =IFERROR(__xludf.DUMMYFUNCTION("if(B7=0,""..."",GOOGLEFINANCE(""BCBA:""&B7))"),21220.0) -> 21220 | L7: =if(B7=0,"...",$H7*I7) -> 1580 | M7: =VLOOKUP(C7,CCLHistory!$A$3:$B84,2,FALSE) -> 148,56 | N7: =L7/IF(G7="USD",1,M7) -> 10.635433 | O7: =if(B7=0,"...",$H7*(IF(D7="ABIERTA",K7,J7)*(1-VLOOKUP(A7,Config!$A$3:$B$5,2,FALSE)))) -> 21218.939 | P7: =IF(D7="ABIERTA",Config!$D$4,VLOOKUP(E7,CCLHistory!$A$6:$B84,2,FALSE)) -> 1269 | Q7: =O7/IF(G7="USD",1,P7) -> 16.720992 | R7: =if(B7=0,"...",Q7/N7-1) -> 0.57219658 | S7: =if(B7=0,"...",Q7-N7) -> 6.0855586 | T7: =if(B7=0,"...",O7/L7-1) -> 12.429708 | U7: =if(B7=0,"...",O7-L7) -> 19638.939 | W7: JNJ | X7: =if(W7=0,"...",sumifs($H$2:$H89,$B$2:$B89,W7,$D$2:$D89,"ABIERTA")) -> 0 | Y7: =if(W7=0,"",AA7/$AF$20) -> 0 | Z7: =if(X7=0,"...",if(W7=0,"...",sumifs($N$2:$N89,$B$2:$B89,W7,$D$2:$D89,"ABIERTA")/X7)) -> ... | AA7: =if(W7=0,"...",sumifs($Q$2:$Q89,$B$2:$B89,W7,$D$2:$D89,"ABIERTA")) -> 0 | AB7: =if(X7=0,"...",if(W7=0,"...",AC7/(AA7-AC7))) -> ... | AC7: =if(X7=0,"...",if(W7=0,"...",sumifs($S$2:$S89,$B$2:$B89,W7,$D$2:$D89,"ABIERTA"))) -> ...
A8: IOL | B8: KO | C8: 44175 | D8: ABIERTA | F8: =if($B8=0,"...", IF($E8=0,today()-$C8,$E8-$C8)) -> 1821 | G8: PESOS | H8: 3 | I8: 1552 | K8: =IFERROR(__xludf.DUMMYFUNCTION("if(B8=0,""..."",GOOGLEFINANCE(""BCBA:""&B8))"),21220.0) -> 21220 | L8: =if(B8=0,"...",$H8*I8) -> 4656 | M8: =VLOOKUP(C8,CCLHistory!$A$3:$B84,2,FALSE) -> 141,38 | N8: =L8/IF(G8="USD",1,M8) -> 32.932522 | O8: =if(B8=0,"...",$H8*(IF(D8="ABIERTA",K8,J8)*(1-VLOOKUP(A8,Config!$A$3:$B$5,2,FALSE)))) -> 63656.817 | P8: =IF(D8="ABIERTA",Config!$D$4,VLOOKUP(E8,CCLHistory!$A$6:$B84,2,FALSE)) -> 1269 | Q8: =O8/IF(G8="USD",1,P8) -> 50.162976 | R8: =if(B8=0,"...",Q8/N8-1) -> 0.52320481 | S8: =if(B8=0,"...",Q8-N8) -> 17.230454 | T8: =if(B8=0,"...",O8/L8-1) -> 12.671997 | U8: =if(B8=0,"...",O8-L8) -> 59000.817 | W8: BRKB | X8: =if(W8=0,"...",sumifs($H$2:$H90,$B$2:$B90,W8,$D$2:$D90,"ABIERTA")) -> 0 | Y8: =if(W8=0,"",AA8/$AF$20) -> 0 | Z8: =if(X8=0,"...",if(W8=0,"...",sumifs($N$2:$N90,$B$2:$B90,W8,$D$2:$D90,"ABIERTA")/X8)) -> ... | AA8: =if(W8=0,"...",sumifs($Q$2:$Q90,$B$2:$B90,W8,$D$2:$D90,"ABIERTA")) -> 0 | AB8: =if(X8=0,"...",if(W8=0,"...",AC8/(AA8-AC8))) -> ... | AC8: =if(X8=0,"...",if(W8=0,"...",sumifs($S$2:$S90,$B$2:$B90,W8,$D$2:$D90,"ABIERTA"))) -> ...
A9: IOL | B9: KO | C9: 44228 | D9: ABIERTA | F9: =if($B9=0,"...", IF($E9=0,today()-$C9,$E9-$C9)) -> 1768 | G9: PESOS | H9: 3 | I9: 1510 | K9: =IFERROR(__xludf.DUMMYFUNCTION("if(B9=0,""..."",GOOGLEFINANCE(""BCBA:""&B9))"),21220.0) -> 21220 | L9: =if(B9=0,"...",$H9*I9) -> 4530 | M9: =VLOOKUP(C9,CCLHistory!$A$3:$B84,2,FALSE) -> 154,69 | N9: =L9/IF(G9="USD",1,M9) -> 29.284375 | O9: =if(B9=0,"...",$H9*(IF(D9="ABIERTA",K9,J9)*(1-VLOOKUP(A9,Config!$A$3:$B$5,2,FALSE)))) -> 63656.817 | P9: =IF(D9="ABIERTA",Config!$D$4,VLOOKUP(E9,CCLHistory!$A$6:$B84,2,FALSE)) -> 1269 | Q9: =O9/IF(G9="USD",1,P9) -> 50.162976 | R9: =if(B9=0,"...",Q9/N9-1) -> 0.71296044 | S9: =if(B9=0,"...",Q9-N9) -> 20.878601 | T9: =if(B9=0,"...",O9/L9-1) -> 13.052277 | U9: =if(B9=0,"...",O9-L9) -> 59126.817 | W9: HMY | X9: =if(W9=0,"...",sumifs($H$2:$H91,$B$2:$B91,W9,$D$2:$D91,"ABIERTA")) -> 0 | Y9: =if(W9=0,"",AA9/$AF$20) -> 0 | Z9: =if(X9=0,"...",if(W9=0,"...",sumifs($N$2:$N91,$B$2:$B91,W9,$D$2:$D91,"ABIERTA")/X9)) -> ... | AA9: =if(W9=0,"...",sumifs($Q$2:$Q91,$B$2:$B91,W9,$D$2:$D91,"ABIERTA")) -> 0 | AB9: =if(X9=0,"...",if(W9=0,"...",AC9/(AA9-AC9))) -> ... | AC9: =if(X9=0,"...",if(W9=0,"...",sumifs($S$2:$S91,$B$2:$B91,W9,$D$2:$D91,"ABIERTA"))) -> ...
A10: IOL | B10: KO | C10: 44245 | D10: ABIERTA | F10: =if($B10=0,"...", IF($E10=0,today()-$C10,$E10-$C10)) -> 1751 | G10: PESOS | H10: 3 | I10: 1533 | K10: =IFERROR(__xludf.DUMMYFUNCTION("if(B10=0,""..."",GOOGLEFINANCE(""BCBA:""&B10))"),21220.0) -> 21220 | L10: =if(B10=0,"...",$H10*I10) -> 4599 | M10: =VLOOKUP(C10,CCLHistory!$A$3:$B84,2,FALSE) -> 145,18 | N10: =L10/IF(G10="USD",1,M10) -> 31.677917 | O10: =if(B10=0,"...",$H10*(IF(D10="ABIERTA",K10,J10)*(1-VLOOKUP(A10,Config!$A$3:$B$5,2,FALSE)))) -> 63656.817 | P10: =IF(D10="ABIERTA",Config!$D$4,VLOOKUP(E10,CCLHistory!$A$6:$B84,2,FALSE)) -> 1269 | Q10: =O10/IF(G10="USD",1,P10) -> 50.162976 | R10: =if(B10=0,"...",Q10/N10-1) -> 0.5835314 | S10: =if(B10=0,"...",Q10-N10) -> 18.485059 | T10: =if(B10=0,"...",O10/L10-1) -> 12.841447 | U10: =if(B10=0,"...",O10-L10) -> 59057.817 | W10: INTC | X10: =if(W10=0,"...",sumifs($H$2:$H92,$B$2:$B92,W10,$D$2:$D92,"ABIERTA")) -> 0 | Y10: =if(W10=0,"",AA10/$AF$20) -> 0 | Z10: =if(X10=0,"...",if(W10=0,"...",sumifs($N$2:$N92,$B$2:$B92,W10,$D$2:$D92,"ABIERTA")/X10)) -> ... | AA10: =if(W10=0,"...",sumifs($Q$2:$Q92,$B$2:$B92,W10,$D$2:$D92,"ABIERTA")) -> 0 | AB10: =if(X10=0,"...",if(W10=0,"...",AC10/(AA10-AC10))) -> ... | AC10: =if(X10=0,"...",if(W10=0,"...",sumifs($S$2:$S92,$B$2:$B92,W10,$D$2:$D92,"ABIERTA"))) -> ...
A11: IOL | B11: KO | C11: 44426 | D11: ABIERTA | F11: =if($B11=0,"...", IF($E11=0,today()-$C11,$E11-$C11)) -> 1570 | G11: PESOS | H11: 1 | I11: 2043 | K11: =IFERROR(__xludf.DUMMYFUNCTION("if(B11=0,""..."",GOOGLEFINANCE(""BCBA:""&B11))"),21220.0) -> 21220 | L11: =if(B11=0,"...",$H11*I11) -> 2043 | M11: =VLOOKUP(C11,CCLHistory!$A$3:$B84,2,FALSE) -> 177,04 | N11: =L11/IF(G11="USD",1,M11) -> 11.539765 | O11: =if(B11=0,"...",$H11*(IF(D11="ABIERTA",K11,J11)*(1-VLOOKUP(A11,Config!$A$3:$B$5,2,FALSE)))) -> 21218.939 | P11: =IF(D11="ABIERTA",Config!$D$4,VLOOKUP(E11,CCLHistory!$A$6:$B84,2,FALSE)) -> 1269 | Q11: =O11/IF(G11="USD",1,P11) -> 16.720992 | R11: =if(B11=0,"...",Q11/N11-1) -> 0.44898896 | S11: =if(B11=0,"...",Q11-N11) -> 5.1812271 | T11: =if(B11=0,"...",O11/L11-1) -> 9.3861669 | U11: =if(B11=0,"...",O11-L11) -> 19175.939 | W11: MELI | X11: =if(W11=0,"...",sumifs($H$2:$H93,$B$2:$B93,W11,$D$2:$D93,"ABIERTA")) -> 0 | Y11: =if(W11=0,"",AA11/$AF$20) -> 0 | Z11: =if(X11=0,"...",if(W11=0,"...",sumifs($N$2:$N93,$B$2:$B93,W11,$D$2:$D93,"ABIERTA")/X11)) -> ... | AA11: =if(W11=0,"...",sumifs($Q$2:$Q93,$B$2:$B93,W11,$D$2:$D93,"ABIERTA")) -> 0 | AB11: =if(X11=0,"...",if(W11=0,"...",AC11/(AA11-AC11))) -> ... | AC11: =if(X11=0,"...",if(W11=0,"...",sumifs($S$2:$S93,$B$2:$B93,W11,$D$2:$D93,"ABIERTA"))) -> ...
A12: IOL | B12: KO | C12: 44449 | D12: ABIERTA | F12: =if($B12=0,"...", IF($E12=0,today()-$C12,$E12-$C12)) -> 1547 | G12: PESOS | H12: 5 | I12: 2012 | K12: =IFERROR(__xludf.DUMMYFUNCTION("if(B12=0,""..."",GOOGLEFINANCE(""BCBA:""&B12))"),21220.0) -> 21220 | L12: =if(B12=0,"...",$H12*I12) -> 10060 | M12: =VLOOKUP(C12,CCLHistory!$A$3:$B84,2,FALSE) -> 183,42 | N12: =L12/IF(G12="USD",1,M12) -> 54.8468 | O12: =if(B12=0,"...",$H12*(IF(D12="ABIERTA",K12,J12)*(1-VLOOKUP(A12,Config!$A$3:$B$5,2,FALSE)))) -> 106094.7 | P12: =IF(D12="ABIERTA",Config!$D$4,VLOOKUP(E12,CCLHistory!$A$6:$B84,2,FALSE)) -> 1269 | Q12: =O12/IF(G12="USD",1,P12) -> 83.604961 | R12: =if(B12=0,"...",Q12/N12-1) -> 0.52433617 | S12: =if(B12=0,"...",Q12-N12) -> 28.758161 | T12: =if(B12=0,"...",O12/L12-1) -> 9.5461923 | U12: =if(B12=0,"...",O12-L12) -> 96034.695 | W12: MSFT | X12: =if(W12=0,"...",sumifs($H$2:$H94,$B$2:$B94,W12,$D$2:$D94,"ABIERTA")) -> 0 | Y12: =if(W12=0,"",AA12/$AF$20) -> 0 | Z12: =if(X12=0,"...",if(W12=0,"...",sumifs($N$2:$N94,$B$2:$B94,W12,$D$2:$D94,"ABIERTA")/X12)) -> ... | AA12: =if(W12=0,"...",sumifs($Q$2:$Q94,$B$2:$B94,W12,$D$2:$D94,"ABIERTA")) -> 0 | AB12: =if(X12=0,"...",if(W12=0,"...",AC12/(AA12-AC12))) -> ... | AC12: =if(X12=0,"...",if(W12=0,"...",sumifs($S$2:$S94,$B$2:$B94,W12,$D$2:$D94,"ABIERTA"))) -> ...
A13: IOL | B13: KO | C13: 44459 | D13: ABIERTA | F13: =if($B13=0,"...", IF($E13=0,today()-$C13,$E13-$C13)) -> 1537 | G13: PESOS | H13: 2 | I13: 1975.5 | K13: =IFERROR(__xludf.DUMMYFUNCTION("if(B13=0,""..."",GOOGLEFINANCE(""BCBA:""&B13))"),21220.0) -> 21220 | L13: =if(B13=0,"...",$H13*I13) -> 3951 | M13: =VLOOKUP(C13,CCLHistory!$A$3:$B84,2,FALSE) -> 185,38 | N13: =L13/IF(G13="USD",1,M13) -> 21.312979 | O13: =if(B13=0,"...",$H13*(IF(D13="ABIERTA",K13,J13)*(1-VLOOKUP(A13,Config!$A$3:$B$5,2,FALSE)))) -> 42437.878 | P13: =IF(D13="ABIERTA",Config!$D$4,VLOOKUP(E13,CCLHistory!$A$6:$B84,2,FALSE)) -> 1269 | Q13: =O13/IF(G13="USD",1,P13) -> 33.441984 | R13: =if(B13=0,"...",Q13/N13-1) -> 0.56909011 | S13: =if(B13=0,"...",Q13-N13) -> 12.129005 | T13: =if(B13=0,"...",O13/L13-1) -> 9.7410473 | U13: =if(B13=0,"...",O13-L13) -> 38486.878 | W13: SPOT | X13: =if(W13=0,"...",sumifs($H$2:$H95,$B$2:$B95,W13,$D$2:$D95,"ABIERTA")) -> 0 | Y13: =if(W13=0,"",AA13/$AF$20) -> 0 | Z13: =if(X13=0,"...",if(W13=0,"...",sumifs($N$2:$N95,$B$2:$B95,W13,$D$2:$D95,"ABIERTA")/X13)) -> ... | AA13: =if(W13=0,"...",sumifs($Q$2:$Q95,$B$2:$B95,W13,$D$2:$D95,"ABIERTA")) -> 0 | AB13: =if(X13=0,"...",if(W13=0,"...",AC13/(AA13-AC13))) -> ... | AC13: =if(X13=0,"...",if(W13=0,"...",sumifs($S$2:$S95,$B$2:$B95,W13,$D$2:$D95,"ABIERTA"))) -> ...
A14: IOL | B14: KO | C14: 44649 | D14: ABIERTA | F14: =if($B14=0,"...", IF($E14=0,today()-$C14,$E14-$C14)) -> 1347 | G14: PESOS | H14: 32 | I14: 2454 | K14: =IFERROR(__xludf.DUMMYFUNCTION("if(B14=0,""..."",GOOGLEFINANCE(""BCBA:""&B14))"),21220.0) -> 21220 | L14: =if(B14=0,"...",$H14*I14) -> 78528 | M14: =VLOOKUP(C14,CCLHistory!$A$3:$B84,2,FALSE) -> 191,52 | N14: =L14/IF(G14="USD",1,M14) -> 410.02506 | O14: =if(B14=0,"...",$H14*(IF(D14="ABIERTA",K14,J14)*(1-VLOOKUP(A14,Config!$A$3:$B$5,2,FALSE)))) -> 679006.05 | P14: =IF(D14="ABIERTA",Config!$D$4,VLOOKUP(E14,CCLHistory!$A$6:$B84,2,FALSE)) -> 1269 | Q14: =O14/IF(G14="USD",1,P14) -> 535.07175 | R14: =if(B14=0,"...",Q14/N14-1) -> 0.30497327 | S14: =if(B14=0,"...",Q14-N14) -> 125.04669 | T14: =if(B14=0,"...",O14/L14-1) -> 7.6466744 | U14: =if(B14=0,"...",O14-L14) -> 600478.05 | W14: WMT | X14: =if(W14=0,"...",sumifs($H$2:$H96,$B$2:$B96,W14,$D$2:$D96,"ABIERTA")) -> 0 | Y14: =if(W14=0,"",AA14/$AF$20) -> 0 | Z14: =if(X14=0,"...",if(W14=0,"...",sumifs($N$2:$N96,$B$2:$B96,W14,$D$2:$D96,"ABIERTA")/X14)) -> ... | AA14: =if(W14=0,"...",sumifs($Q$2:$Q96,$B$2:$B96,W14,$D$2:$D96,"ABIERTA")) -> 0 | AB14: =if(X14=0,"...",if(W14=0,"...",AC14/(AA14-AC14))) -> ... | AC14: =if(X14=0,"...",if(W14=0,"...",sumifs($S$2:$S96,$B$2:$B96,W14,$D$2:$D96,"ABIERTA"))) -> ...
A15: IOL | B15: KO | C15: 44687 | D15: ABIERTA | F15: =if($B15=0,"...", IF($E15=0,today()-$C15,$E15-$C15)) -> 1309 | G15: PESOS | H15: 11 | I15: 2650 | K15: =IFERROR(__xludf.DUMMYFUNCTION("if(B15=0,""..."",GOOGLEFINANCE(""BCBA:""&B15))"),21220.0) -> 21220 | L15: =if(B15=0,"...",$H15*I15) -> 29150 | M15: =VLOOKUP(C15,CCLHistory!$A$3:$B84,2,FALSE) -> 208,84 | N15: =L15/IF(G15="USD",1,M15) -> 139.58054 | O15: =if(B15=0,"...",$H15*(IF(D15="ABIERTA",K15,J15)*(1-VLOOKUP(A15,Config!$A$3:$B$5,2,FALSE)))) -> 233408.33 | P15: =IF(D15="ABIERTA",Config!$D$4,VLOOKUP(E15,CCLHistory!$A$6:$B84,2,FALSE)) -> 1269 | Q15: =O15/IF(G15="USD",1,P15) -> 183.93091 | R15: =if(B15=0,"...",Q15/N15-1) -> 0.31774038 | S15: =if(B15=0,"...",Q15-N15) -> 44.350373 | T15: =if(B15=0,"...",O15/L15-1) -> 7.0071468 | U15: =if(B15=0,"...",O15-L15) -> 204258.33 | X15: =if(W15=0,"...",sumifs($H$2:$H97,$B$2:$B97,W15,$D$2:$D97,"ABIERTA")) -> ... | Y15: =if(W15=0,"",AA15/$AF$20) | Z15: =if(X15=0,"...",if(W15=0,"...",sumifs($N$2:$N97,$B$2:$B97,W15,$D$2:$D97,"ABIERTA")/X15)) -> ... | AA15: =if(W15=0,"...",sumifs($Q$2:$Q97,$B$2:$B97,W15,$D$2:$D97,"ABIERTA")) -> ... | AB15: =if(X15=0,"...",if(W15=0,"...",AC15/(AA15-AC15))) -> ... | AC15: =if(X15=0,"...",if(W15=0,"...",sumifs($S$2:$S97,$B$2:$B97,W15,$D$2:$D97,"ABIERTA"))) -> ...
A16: IOL | B16: KO | C16: 44715 | D16: ABIERTA | F16: =if($B16=0,"...", IF($E16=0,today()-$C16,$E16-$C16)) -> 1281 | G16: PESOS | H16: 18 | I16: 2670.7778 | K16: =IFERROR(__xludf.DUMMYFUNCTION("if(B16=0,""..."",GOOGLEFINANCE(""BCBA:""&B16))"),21220.0) -> 21220 | L16: =if(B16=0,"...",$H16*I16) -> 48074 | M16: =VLOOKUP(C16,CCLHistory!$A$3:$B84,2,FALSE) -> 209,39 | N16: =L16/IF(G16="USD",1,M16) -> 229.59072 | O16: =if(B16=0,"...",$H16*(IF(D16="ABIERTA",K16,J16)*(1-VLOOKUP(A16,Config!$A$3:$B$5,2,FALSE)))) -> 381940.9 | P16: =IF(D16="ABIERTA",Config!$D$4,VLOOKUP(E16,CCLHistory!$A$6:$B84,2,FALSE)) -> 1269 | Q16: =O16/IF(G16="USD",1,P16) -> 300.97786 | R16: =if(B16=0,"...",Q16/N16-1) -> 0.31093217 | S16: =if(B16=0,"...",Q16-N16) -> 71.38714 | T16: =if(B16=0,"...",O16/L16-1) -> 6.9448537 | U16: =if(B16=0,"...",O16-L16) -> 333866.9 | X16: =if(W16=0,"...",sumifs($H$2:$H98,$B$2:$B98,W16,$D$2:$D98,"ABIERTA")) -> ... | Y16: =if(W16=0,"",AA16/$AF$20) | Z16: =if(X16=0,"...",if(W16=0,"...",sumifs($N$2:$N98,$B$2:$B98,W16,$D$2:$D98,"ABIERTA")/X16)) -> ... | AA16: =if(W16=0,"...",sumifs($Q$2:$Q98,$B$2:$B98,W16,$D$2:$D98,"ABIERTA")) -> ... | AB16: =if(X16=0,"...",if(W16=0,"...",AC16/(AA16-AC16))) -> ... | AC16: =if(X16=0,"...",if(W16=0,"...",sumifs($S$2:$S98,$B$2:$B98,W16,$D$2:$D98,"ABIERTA"))) -> ...
A17: IOL | B17: KO | C17: 44789 | D17: ABIERTA | F17: =if($B17=0,"...", IF($E17=0,today()-$C17,$E17-$C17)) -> 1207 | G17: PESOS | H17: 8 | I17: 3654 | K17: =IFERROR(__xludf.DUMMYFUNCTION("if(B17=0,""..."",GOOGLEFINANCE(""BCBA:""&B17))"),21220.0) -> 21220 | L17: =if(B17=0,"...",$H17*I17) -> 29232 | M17: =VLOOKUP(C17,CCLHistory!$A$3:$B84,2,FALSE) -> 282,06 | N17: =L17/IF(G17="USD",1,M17) -> 103.63752 | O17: =if(B17=0,"...",$H17*(IF(D17="ABIERTA",K17,J17)*(1-VLOOKUP(A17,Config!$A$3:$B$5,2,FALSE)))) -> 169751.51 | P17: =IF(D17="ABIERTA",Config!$D$4,VLOOKUP(E17,CCLHistory!$A$6:$B84,2,FALSE)) -> 1269 | Q17: =O17/IF(G17="USD",1,P17) -> 133.76794 | R17: =if(B17=0,"...",Q17/N17-1) -> 0.2907288 | S17: =if(B17=0,"...",Q17-N17) -> 30.130413 | T17: =if(B17=0,"...",O17/L17-1) -> 4.8070441 | U17: =if(B17=0,"...",O17-L17) -> 140519.51 | X17: =if(W17=0,"...",sumifs($H$2:$H99,$B$2:$B99,W17,$D$2:$D99,"ABIERTA")) -> ... | Y17: =if(W17=0,"",AA17/$AF$20) | Z17: =if(X17=0,"...",if(W17=0,"...",sumifs($N$2:$N99,$B$2:$B99,W17,$D$2:$D99,"ABIERTA")/X17)) -> ... | AA17: =if(W17=0,"...",sumifs($Q$2:$Q99,$B$2:$B99,W17,$D$2:$D99,"ABIERTA")) -> ... | AB17: =if(X17=0,"...",if(W17=0,"...",AC17/(AA17-AC17))) -> ... | AC17: =if(X17=0,"...",if(W17=0,"...",sumifs($S$2:$S99,$B$2:$B99,W17,$D$2:$D99,"ABIERTA"))) -> ...
A18: IOL | B18: KO | C18: 45104 | D18: ABIERTA | F18: =if($B18=0,"...", IF($E18=0,today()-$C18,$E18-$C18)) -> 892 | G18: PESOS | H18: 15 | I18: 6395.1667 | K18: =IFERROR(__xludf.DUMMYFUNCTION("if(B18=0,""..."",GOOGLEFINANCE(""BCBA:""&B18))"),21220.0) -> 21220 | L18: =if(B18=0,"...",$H18*I18) -> 95927.5 | M18: =VLOOKUP(C18,CCLHistory!$A$3:$B84,2,FALSE) -> 509,74 | N18: =L18/IF(G18="USD",1,M18) -> 188.18908 | O18: =if(B18=0,"...",$H18*(IF(D18="ABIERTA",K18,J18)*(1-VLOOKUP(A18,Config!$A$3:$B$5,2,FALSE)))) -> 318284.09 | P18: =IF(D18="ABIERTA",Config!$D$4,VLOOKUP(E18,CCLHistory!$A$6:$B84,2,FALSE)) -> 1269 | Q18: =O18/IF(G18="USD",1,P18) -> 250.81488 | R18: =if(B18=0,"...",Q18/N18-1) -> 0.33278129 | S18: =if(B18=0,"...",Q18-N18) -> 62.625804 | T18: =if(B18=0,"...",O18/L18-1) -> 2.317965 | U18: =if(B18=0,"...",O18-L18) -> 222356.58 | X18: =if(W18=0,"...",sumifs($H$2:$H100,$B$2:$B100,W18,$D$2:$D100,"ABIERTA")) -> ... | Y18: =if(W18=0,"",AA18/$AF$20) | Z18: =if(X18=0,"...",if(W18=0,"...",sumifs($N$2:$N100,$B$2:$B100,W18,$D$2:$D100,"ABIERTA")/X18)) -> ... | AA18: =if(W18=0,"...",sumifs($Q$2:$Q100,$B$2:$B100,W18,$D$2:$D100,"ABIERTA")) -> ... | AB18: =if(X18=0,"...",if(W18=0,"...",AC18/(AA18-AC18))) -> ... | AC18: =if(X18=0,"...",if(W18=0,"...",sumifs($S$2:$S100,$B$2:$B100,W18,$D$2:$D100,"ABIERTA"))) -> ...
A19: IOL | B19: KO | C19: 45142 | D19: ABIERTA | F19: =if($B19=0,"...", IF($E19=0,today()-$C19,$E19-$C19)) -> 854 | G19: PESOS | H19: 6 | I19: 7053 | K19: =IFERROR(__xludf.DUMMYFUNCTION("if(B19=0,""..."",GOOGLEFINANCE(""BCBA:""&B19))"),21220.0) -> 21220 | L19: =if(B19=0,"...",$H19*I19) -> 42318 | M19: =VLOOKUP(C19,CCLHistory!$A$3:$B84,2,FALSE) -> 585,41 | N19: =L19/IF(G19="USD",1,M19) -> 72.287798 | O19: =if(B19=0,"...",$H19*(IF(D19="ABIERTA",K19,J19)*(1-VLOOKUP(A19,Config!$A$3:$B$5,2,FALSE)))) -> 127313.63 | P19: =IF(D19="ABIERTA",Config!$D$4,VLOOKUP(E19,CCLHistory!$A$6:$B84,2,FALSE)) -> 1269 | Q19: =O19/IF(G19="USD",1,P19) -> 100.32595 | R19: =if(B19=0,"...",Q19/N19-1) -> 0.38786842 | S19: =if(B19=0,"...",Q19-N19) -> 28.038154 | T19: =if(B19=0,"...",O19/L19-1) -> 2.0084984 | U19: =if(B19=0,"...",O19-L19) -> 84995.634 | X19: =if(W19=0,"...",sumifs($H$2:$H101,$B$2:$B101,W19,$D$2:$D101,"ABIERTA")) -> ... | Y19: =if(W19=0,"",AA19/$AF$20) | Z19: =if(X19=0,"...",if(W19=0,"...",sumifs($N$2:$N101,$B$2:$B101,W19,$D$2:$D101,"ABIERTA")/X19)) -> ... | AA19: =if(W19=0,"...",sumifs($Q$2:$Q101,$B$2:$B101,W19,$D$2:$D101,"ABIERTA")) -> ... | AB19: =if(X19=0,"...",if(W19=0,"...",AC19/(AA19-AC19))) -> ... | AC19: =if(X19=0,"...",if(W19=0,"...",sumifs($S$2:$S101,$B$2:$B101,W19,$D$2:$D101,"ABIERTA"))) -> ...
A20: IOL | B20: KO | C20: 45149 | D20: ABIERTA | F20: =if($B20=0,"...", IF($E20=0,today()-$C20,$E20-$C20)) -> 847 | G20: PESOS | H20: 3 | I20: 7365 | K20: =IFERROR(__xludf.DUMMYFUNCTION("if(B20=0,""..."",GOOGLEFINANCE(""BCBA:""&B20))"),21220.0) -> 21220 | L20: =if(B20=0,"...",$H20*I20) -> 22095 | M20: =VLOOKUP(C20,CCLHistory!$A$3:$B84,2,FALSE) -> 601,44 | N20: =L20/IF(G20="USD",1,M20) -> 36.736832 | O20: =if(B20=0,"...",$H20*(IF(D20="ABIERTA",K20,J20)*(1-VLOOKUP(A20,Config!$A$3:$B$5,2,FALSE)))) -> 63656.817 | P20: =IF(D20="ABIERTA",Config!$D$4,VLOOKUP(E20,CCLHistory!$A$6:$B84,2,FALSE)) -> 1269 | Q20: =O20/IF(G20="USD",1,P20) -> 50.162976 | R20: =if(B20=0,"...",Q20/N20-1) -> 0.36546823 | S20: =if(B20=0,"...",Q20-N20) -> 13.426145 | T20: =if(B20=0,"...",O20/L20-1) -> 1.8810508 | U20: =if(B20=0,"...",O20-L20) -> 41561.817 | X20: =if(W20=0,"...",sumifs($H$2:$H102,$B$2:$B102,W20,$D$2:$D102,"ABIERTA")) -> ... | Y20: =if(W20=0,"",AA20/$AF$20) | Z20: =if(X20=0,"...",if(W20=0,"...",sumifs($N$2:$N102,$B$2:$B102,W20,$D$2:$D102,"ABIERTA")/X20)) -> ... | AA20: =if(W20=0,"...",sumifs($Q$2:$Q102,$B$2:$B102,W20,$D$2:$D102,"ABIERTA")) -> ... | AB20: =if(X20=0,"...",if(W20=0,"...",AC20/(AA20-AC20))) -> ... | AC20: =if(X20=0,"...",if(W20=0,"...",sumifs($S$2:$S102,$B$2:$B102,W20,$D$2:$D102,"ABIERTA"))) -> ... | AE20: Total Abierto | AF20: =sumifs(Q2:Q84,D2:D84,"ABIERTA") -> 3650.6595 | AG20: Total Acumulado | AH20: =sum(Q2:Q84) -> 7398.3682
A21: IOL | B21: KO | C21: 45184 | D21: ABIERTA | F21: =if($B21=0,"...", IF($E21=0,today()-$C21,$E21-$C21)) -> 812 | G21: PESOS | H21: 11 | I21: 8678.5 | K21: =IFERROR(__xludf.DUMMYFUNCTION("if(B21=0,""..."",GOOGLEFINANCE(""BCBA:""&B21))"),21220.0) -> 21220 | L21: =if(B21=0,"...",$H21*I21) -> 95463.5 | M21: =VLOOKUP(C21,CCLHistory!$A$3:$B84,2,FALSE) -> 740,08 | N21: =L21/IF(G21="USD",1,M21) -> 128.99078 | O21: =if(B21=0,"...",$H21*(IF(D21="ABIERTA",K21,J21)*(1-VLOOKUP(A21,Config!$A$3:$B$5,2,FALSE)))) -> 233408.33 | P21: =IF(D21="ABIERTA",Config!$D$4,VLOOKUP(E21,CCLHistory!$A$6:$B84,2,FALSE)) -> 1269 | Q21: =O21/IF(G21="USD",1,P21) -> 183.93091 | R21: =if(B21=0,"...",Q21/N21-1) -> 0.4259229 | S21: =if(B21=0,"...",Q21-N21) -> 54.940129 | T21: =if(B21=0,"...",O21/L21-1) -> 1.4450007 | U21: =if(B21=0,"...",O21-L21) -> 137944.83 | X21: =if(W21=0,"...",sumifs($H$2:$H103,$B$2:$B103,W21,$D$2:$D103,"ABIERTA")) -> ... | Y21: =if(W21=0,"",AA21/$AF$20) | Z21: =if(X21=0,"...",if(W21=0,"...",sumifs($N$2:$N103,$B$2:$B103,W21,$D$2:$D103,"ABIERTA")/X21)) -> ... | AA21: =if(W21=0,"...",sumifs($Q$2:$Q103,$B$2:$B103,W21,$D$2:$D103,"ABIERTA")) -> ... | AB21: =if(X21=0,"...",if(W21=0,"...",AC21/(AA21-AC21))) -> ... | AC21: =if(X21=0,"...",if(W21=0,"...",sumifs($S$2:$S103,$B$2:$B103,W21,$D$2:$D103,"ABIERTA"))) -> ...
A22: IOL | B22: KO | C22: 45216 | D22: ABIERTA | F22: =if($B22=0,"...", IF($E22=0,today()-$C22,$E22-$C22)) -> 780 | G22: PESOS | H22: 4 | I22: 10057 | K22: =IFERROR(__xludf.DUMMYFUNCTION("if(B22=0,""..."",GOOGLEFINANCE(""BCBA:""&B22))"),21220.0) -> 21220 | L22: =if(B22=0,"...",$H22*I22) -> 40228 | M22: =VLOOKUP(C22,CCLHistory!$A$3:$B84,2,FALSE) -> 962,69 | N22: =L22/IF(G22="USD",1,M22) -> 41.787076 | O22: =if(B22=0,"...",$H22*(IF(D22="ABIERTA",K22,J22)*(1-VLOOKUP(A22,Config!$A$3:$B$5,2,FALSE)))) -> 84875.756 | P22: =IF(D22="ABIERTA",Config!$D$4,VLOOKUP(E22,CCLHistory!$A$6:$B84,2,FALSE)) -> 1269 | Q22: =O22/IF(G22="USD",1,P22) -> 66.883968 | R22: =if(B22=0,"...",Q22/N22-1) -> 0.60058983 | S22: =if(B22=0,"...",Q22-N22) -> 25.096893 | T22: =if(B22=0,"...",O22/L22-1) -> 1.1098677 | U22: =if(B22=0,"...",O22-L22) -> 44647.756 | X22: =if(W22=0,"...",sumifs($H$2:$H104,$B$2:$B104,W22,$D$2:$D104,"ABIERTA")) -> ... | Y22: =if(W22=0,"",AA22/$AF$20) | Z22: =if(X22=0,"...",if(W22=0,"...",sumifs($N$2:$N104,$B$2:$B104,W22,$D$2:$D104,"ABIERTA")/X22)) -> ... | AA22: =if(W22=0,"...",sumifs($Q$2:$Q104,$B$2:$B104,W22,$D$2:$D104,"ABIERTA")) -> ... | AB22: =if(X22=0,"...",if(W22=0,"...",AC22/(AA22-AC22))) -> ... | AC22: =if(X22=0,"...",if(W22=0,"...",sumifs($S$2:$S104,$B$2:$B104,W22,$D$2:$D104,"ABIERTA"))) -> ... | AE22: Ganancia Abierto | AF22: =sumifs(S2:S84,D2:D84,"ABIERTA") -> 1074.7897 | AG22: Ganancia Acumulada | AH22: =sum(S2:S84) -> 1121.3373
A23: IOL | B23: DISN | C23: 45104 | D23: CERRADA | E23: 45551 | F23: =if($B23=0,"...", IF($E23=0,today()-$C23,$E23-$C23)) -> 447 | G23: PESOS | H23: 25 | I23: 3818 | J23: 9510 | K23: =IFERROR(__xludf.DUMMYFUNCTION("if(B23=0,""..."",GOOGLEFINANCE(""BCBA:""&B23))"),13250.0) -> 13250 | L23: =if(B23=0,"...",$H23*I23) -> 95450 | M23: =VLOOKUP(C23,CCLHistory!$A$3:$B84,2,FALSE) -> 509,74 | N23: =L23/IF(G23="USD",1,M23) -> 187.25232 | O23: =if(B23=0,"...",$H23*(IF(D23="ABIERTA",K23,J23)*(1-VLOOKUP(A23,Config!$A$3:$B$5,2,FALSE)))) -> 237738.11 | P23: =IF(D23="ABIERTA",Config!$D$4,VLOOKUP(E23,CCLHistory!$A$6:$B84,2,FALSE)) -> 1238.0086 | Q23: =O23/IF(G23="USD",1,P23) -> 192.03268 | R23: =if(B23=0,"...",Q23/N23-1) -> 0.025528972 | S23: =if(B23=0,"...",Q23-N23) -> 4.7803593 | T23: =if(B23=0,"...",O23/L23-1) -> 1.4907084 | U23: =if(B23=0,"...",O23-L23) -> 142288.11 | X23: =if(W23=0,"...",sumifs($H$2:$H105,$B$2:$B105,W23,$D$2:$D105,"ABIERTA")) -> ... | Y23: =if(W23=0,"",AA23/$AF$20) | Z23: =if(X23=0,"...",if(W23=0,"...",sumifs($N$2:$N105,$B$2:$B105,W23,$D$2:$D105,"ABIERTA")/X23)) -> ... | AA23: =if(W23=0,"...",sumifs($Q$2:$Q105,$B$2:$B105,W23,$D$2:$D105,"ABIERTA")) -> ... | AB23: =if(X23=0,"...",if(W23=0,"...",AC23/(AA23-AC23))) -> ... | AC23: =if(X23=0,"...",if(W23=0,"...",sumifs($S$2:$S105,$B$2:$B105,W23,$D$2:$D105,"ABIERTA"))) -> ...
A24: IOL | B24: DISN | C24: 45303 | D24: CERRADA | E24: 45551 | F24: =if($B24=0,"...", IF($E24=0,today()-$C24,$E24-$C24)) -> 248 | G24: PESOS | H24: 8 | I24: 8448.5 | J24: 9510 | K24: =IFERROR(__xludf.DUMMYFUNCTION("if(B24=0,""..."",GOOGLEFINANCE(""BCBA:""&B24))"),13250.0) -> 13250 | L24: =if(B24=0,"...",$H24*I24) -> 67588 | M24: =VLOOKUP(C24,CCLHistory!$A$3:$B84,2,FALSE) -> 1136.65 | N24: =L24/IF(G24="USD",1,M24) -> 59.462455 | O24: =if(B24=0,"...",$H24*(IF(D24="ABIERTA",K24,J24)*(1-VLOOKUP(A24,Config!$A$3:$B$5,2,FALSE)))) -> 76076.196 | P24: =IF(D24="ABIERTA",Config!$D$4,VLOOKUP(E24,CCLHistory!$A$7:$B84,2,FALSE)) -> 1238.0086 | Q24: =O24/IF(G24="USD",1,P24) -> 61.450459 | R24: =if(B24=0,"...",Q24/N24-1) -> 0.033432918 | S24: =if(B24=0,"...",Q24-N24) -> 1.9880034 | T24: =if(B24=0,"...",O24/L24-1) -> 0.12558732 | U24: =if(B24=0,"...",O24-L24) -> 8488.196
A25: IOL | B25: DISN | C25: 45308 | D25: ABIERTA | F25: =if($B25=0,"...", IF($E25=0,today()-$C25,$E25-$C25)) -> 688 | G25: PESOS | H25: 6 | I25: 9737.5 | K25: =IFERROR(__xludf.DUMMYFUNCTION("if(B25=0,""..."",GOOGLEFINANCE(""BCBA:""&B25))"),13250.0) -> 13250 | L25: =if(B25=0,"...",$H25*I25) -> 58425 | M25: =VLOOKUP(C25,CCLHistory!$A$3:$B84,2,FALSE) -> 1273.34 | N25: =L25/IF(G25="USD",1,M25) -> 45.883268 | O25: =if(B25=0,"...",$H25*(IF(D25="ABIERTA",K25,J25)*(1-VLOOKUP(A25,Config!$A$3:$B$5,2,FALSE)))) -> 79496.025 | P25: =IF(D25="ABIERTA",Config!$D$4,VLOOKUP(E25,CCLHistory!$A$6:$B84,2,FALSE)) -> 1269 | Q25: =O25/IF(G25="USD",1,P25) -> 62.644622 | R25: =if(B25=0,"...",Q25/N25-1) -> 0.36530428 | S25: =if(B25=0,"...",Q25-N25) -> 16.761354 | T25: =if(B25=0,"...",O25/L25-1) -> 0.36065083 | U25: =if(B25=0,"...",O25-L25) -> 21071.025
A26: IOL | B26: DIA | C26: 44789 | D26: ABIERTA | F26: =if($B26=0,"...", IF($E26=0,today()-$C26,$E26-$C26)) -> 1207 | G26: PESOS | H26: 8 | I26: 6865 | K26: =IFERROR(__xludf.DUMMYFUNCTION("if(B26=0,""..."",GOOGLEFINANCE(""BCBA:""&B26))"),36140.0) -> 36140 | L26: =if(B26=0,"...",$H26*I26) -> 54920 | M26: =VLOOKUP(C26,CCLHistory!$A$3:$B84,2,FALSE) -> 282,06 | N26: =L26/IF(G26="USD",1,M26) -> 194.71035 | O26: =if(B26=0,"...",$H26*(IF(D26="ABIERTA",K26,J26)*(1-VLOOKUP(A26,Config!$A$3:$B$5,2,FALSE)))) -> 289105.54 | P26: =IF(D26="ABIERTA",Config!$D$4,VLOOKUP(E26,CCLHistory!$A$6:$B84,2,FALSE)) -> 1269 | Q26: =O26/IF(G26="USD",1,P26) -> 227.82155 | R26: =if(B26=0,"...",Q26/N26-1) -> 0.17005364 | S26: =if(B26=0,"...",Q26-N26) -> 33.111202 | T26: =if(B26=0,"...",O26/L26-1) -> 4.2641213 | U26: =if(B26=0,"...",O26-L26) -> 234185.54 | X26: =if(W26=0,"...",sumifs($H$2:$H84,$B$2:$B84,W26,$D$2:$D84,"ABIERTA")) -> ... | Y26: =if(W26=0,"",AA26/$AF$20) | Z26: =if(X26=0,"...",if(W26=0,"...",sumifs($N$2:$N84,$B$2:$B84,W26,$D$2:$D84,"ABIERTA")/X26)) -> ... | AA26: =if(W26=0,"...",sumifs($Q$2:$Q84,$B$2:$B84,W26,$D$2:$D84,"ABIERTA")) -> ... | AB26: =if(X26=0,"...",if(W26=0,"...",AC26/(AA26-AC26))) -> ... | AC26: =if(X26=0,"...",if(W26=0,"...",sumifs($S$2:$S84,$B$2:$B84,W26,$D$2:$D84,"ABIERTA"))) -> ... | AE26: (%) | AF26: =AF22/(AF20-AF22) -> 0.41725313 | AG26: (%) | AH26: =AH22/(AH20-AH22) -> 0.17864135
A27: IOL | B27: DIA | C27: 44840 | D27: CERRADA | E27: 45294 | F27: =if($B27=0,"...", IF($E27=0,today()-$C27,$E27-$C27)) -> 454 | G27: PESOS | H27: 4 | I27: 4647 | J27: 19424 | K27: =IFERROR(__xludf.DUMMYFUNCTION("if(B27=0,""..."",GOOGLEFINANCE(""BCBA:""&B27))"),36140.0) -> 36140 | L27: =if(B27=0,"...",$H27*I27) -> 18588 | M27: =VLOOKUP(C27,CCLHistory!$A$6:$B84,2,FALSE) -> 307,38 | N27: =L27/M27 -> 60.472379 | O27: =if(B27=0,"...",$H27*(IF(D27="ABIERTA",K27,J27)*(1-VLOOKUP(A27,Config!$A$3:$B$5,2,FALSE)))) -> 77692.115 | P27: 1029.75 | Q27: =O27/P27 -> 75.447551 | R27: =if(B27=0,"...",Q27/N27-1) -> 0.24763654 | S27: =if(B27=0,"...",Q27-N27) -> 14.975171 | T27: =if(B27=0,"...",O27/L27-1) -> 3.179692 | U27: =if(B27=0,"...",O27-L27) -> 59104.115 | X27: =if(W27=0,"...",sumifs($H$2:$H85,$B$2:$B85,W27,$D$2:$D85,"ABIERTA")) -> ... | Y27: =if(W27=0,"",AA27/$AF$20) | Z27: =if(X27=0,"...",if(W27=0,"...",sumifs($N$2:$N85,$B$2:$B85,W27,$D$2:$D85,"ABIERTA")/X27)) -> ... | AA27: =if(W27=0,"...",sumifs($Q$2:$Q85,$B$2:$B85,W27,$D$2:$D85,"ABIERTA")) -> ... | AB27: =if(X27=0,"...",if(W27=0,"...",AC27/(AA27-AC27))) -> ... | AC27: =if(X27=0,"...",if(W27=0,"...",sumifs($S$2:$S85,$B$2:$B85,W27,$D$2:$D85,"ABIERTA"))) -> ...
A28: IOL | B28: DIA | C28: 45104 | D28: ABIERTA | F28: =if($B28=0,"...", IF($E28=0,today()-$C28,$E28-$C28)) -> 892 | G28: PESOS | H28: 11 | I28: 8772.5 | K28: =IFERROR(__xludf.DUMMYFUNCTION("if(B28=0,""..."",GOOGLEFINANCE(""BCBA:""&B28))"),36140.0) -> 36140 | L28: =if(B28=0,"...",$H28*I28) -> 96497.5 | M28: =VLOOKUP(C28,CCLHistory!$A$3:$B84,2,FALSE) -> 509,74 | N28: =L28/IF(G28="USD",1,M28) -> 189.30729 | O28: =if(B28=0,"...",$H28*(IF(D28="ABIERTA",K28,J31)*(1-VLOOKUP(A28,Config!$A$3:$B$5,2,FALSE)))) -> 397520.12 | P28: =IF(D28="ABIERTA",Config!$D$4,VLOOKUP(E28,CCLHistory!$A$6:$B84,2,FALSE)) -> 1269 | Q28: =O28/IF(G28="USD",1,P28) -> 313.25463 | R28: =if(B28=0,"...",Q28/N28-1) -> 0.65474146 | S28: =if(B28=0,"...",Q28-N28) -> 123.94733 | T28: =if(B28=0,"...",O28/L28-1) -> 3.1194862 | U28: =if(B28=0,"...",O28-L28) -> 301022.62 | X28: =if(W28=0,"...",sumifs($H$2:$H86,$B$2:$B86,W28,$D$2:$D86,"ABIERTA")) -> ... | Y28: =if(W28=0,"",AA28/$AF$20) | Z28: =if(X28=0,"...",if(W28=0,"...",sumifs($N$2:$N86,$B$2:$B86,W28,$D$2:$D86,"ABIERTA")/X28)) -> ... | AA28: =if(W28=0,"...",sumifs($Q$2:$Q86,$B$2:$B86,W28,$D$2:$D86,"ABIERTA")) -> ... | AB28: =if(X28=0,"...",if(W28=0,"...",AC28/(AA28-AC28))) -> ... | AC28: =if(X28=0,"...",if(W28=0,"...",sumifs($S$2:$S86,$B$2:$B86,W28,$D$2:$D86,"ABIERTA"))) -> ...
A29: IOL | B29: SPY | C29: 45104 | D29: ABIERTA | F29: =if($B29=0,"...", IF($E29=0,today()-$C29,$E29-$C29)) -> 892 | G29: PESOS | H29: 4 | I29: 11285 | K29: =IFERROR(__xludf.DUMMYFUNCTION("if(B29=0,""..."",GOOGLEFINANCE(""BCBA:""&B29))"),51650.0) -> 51650 | L29: =if(B29=0,"...",$H29*I29) -> 45140 | M29: =VLOOKUP(C29,CCLHistory!$A$3:$B84,2,FALSE) -> 509,74 | N29: =L29/IF(G29="USD",1,M29) -> 88.55495 | O29: =if(B29=0,"...",$H29*(IF(D29="ABIERTA",K29,J29)*(1-VLOOKUP(A29,Config!$A$3:$B$5,2,FALSE)))) -> 206589.67 | P29: =IF(D29="ABIERTA",Config!$D$4,VLOOKUP(E29,CCLHistory!$A$6:$B84,2,FALSE)) -> 1269 | Q29: =O29/IF(G29="USD",1,P29) -> 162.79722 | R29: =if(B29=0,"...",Q29/N29-1) -> 0.83837514 | S29: =if(B29=0,"...",Q29-N29) -> 74.242269 | T29: =if(B29=0,"...",O29/L29-1) -> 3.5766431 | U29: =if(B29=0,"...",O29-L29) -> 161449.67 | X29: =if(W29=0,"...",sumifs($H$2:$H87,$B$2:$B87,W29,$D$2:$D87,"ABIERTA")) -> ... | Y29: =if(W29=0,"",AA29/$AF$20) | Z29: =if(X29=0,"...",if(W29=0,"...",sumifs($N$2:$N87,$B$2:$B87,W29,$D$2:$D87,"ABIERTA")/X29)) -> ... | AA29: =if(W29=0,"...",sumifs($Q$2:$Q87,$B$2:$B87,W29,$D$2:$D87,"ABIERTA")) -> ... | AB29: =if(X29=0,"...",if(W29=0,"...",AC29/(AA29-AC29))) -> ... | AC29: =if(X29=0,"...",if(W29=0,"...",sumifs($S$2:$S87,$B$2:$B87,W29,$D$2:$D87,"ABIERTA"))) -> ...
A30: IOL | B30: SPY | C30: 44789 | D30: ABIERTA | F30: =if($B30=0,"...", IF($E30=0,today()-$C30,$E30-$C30)) -> 1207 | G30: PESOS | H30: 6 | I30: 6045.4167 | K30: =IFERROR(__xludf.DUMMYFUNCTION("if(B30=0,""..."",GOOGLEFINANCE(""BCBA:""&B30))"),51650.0) -> 51650 | L30: =if(B30=0,"...",$H30*I30) -> 36272.5 | M30: =VLOOKUP(C30,CCLHistory!$A$3:$B84,2,FALSE) -> 282,06 | N30: =L30/IF(G30="USD",1,M30) -> 128.59853 | O30: =if(B30=0,"...",$H30*(IF(D30="ABIERTA",K30,J30)*(1-VLOOKUP(A30,Config!$A$3:$B$5,2,FALSE)))) -> 309884.51 | P30: =IF(D30="ABIERTA",Config!$D$4,VLOOKUP(E30,CCLHistory!$A$6:$B84,2,FALSE)) -> 1269 | Q30: =O30/IF(G30="USD",1,P30) -> 244.19583 | R30: =if(B30=0,"...",Q30/N30-1) -> 0.89890067 | S30: =if(B30=0,"...",Q30-N30) -> 115.5973 | T30: =if(B30=0,"...",O30/L30-1) -> 7.5432353 | U30: =if(B30=0,"...",O30-L30) -> 273612 | X30: =if(W30=0,"...",sumifs($H$2:$H88,$B$2:$B88,W30,$D$2:$D88,"ABIERTA")) -> ... | Y30: =if(W30=0,"",AA30/$AF$20) | Z30: =if(X30=0,"...",if(W30=0,"...",sumifs($N$2:$N88,$B$2:$B88,W30,$D$2:$D88,"ABIERTA")/X30)) -> ... | AA30: =if(W30=0,"...",sumifs($Q$2:$Q88,$B$2:$B88,W30,$D$2:$D88,"ABIERTA")) -> ... | AB30: =if(X30=0,"...",if(W30=0,"...",AC30/(AA30-AC30))) -> ... | AC30: =if(X30=0,"...",if(W30=0,"...",sumifs($S$2:$S88,$B$2:$B88,W30,$D$2:$D88,"ABIERTA"))) -> ...
A31: IOL | B31: SPY | C31: 44840 | D31: CERRADA | E31: 45294 | F31: =if($B31=0,"...", IF($E31=0,today()-$C31,$E31-$C31)) -> 454 | G31: PESOS | H31: 3 | I31: 5804.5 | J31: 24350 | K31: =IFERROR(__xludf.DUMMYFUNCTION("if(B31=0,""..."",GOOGLEFINANCE(""BCBA:""&B31))"),51650.0) -> 51650 | L31: =if(B31=0,"...",$H31*I31) -> 17413.5 | M31: =VLOOKUP(C31,CCLHistory!$A$6:$B84,2,FALSE) -> 307,38 | N31: =L31/M31 -> 56.651376 | O31: =if(B31=0,"...",$H31*(IF(D31="ABIERTA",K31,J31)*(1-VLOOKUP(A31,Config!$A$3:$B$5,2,FALSE)))) -> 73046.348 | P31: 1030 | Q31: =O31/P31 -> 70.918784 | R31: =if(B31=0,"...",Q31/N31-1) -> 0.25184574 | S31: =if(B31=0,"...",Q31-N31) -> 14.267408 | T31: =if(B31=0,"...",O31/L31-1) -> 3.1948114 | U31: =if(B31=0,"...",O31-L31) -> 55632.848 | X31: =if(W31=0,"...",sumifs($H$2:$H89,$B$2:$B89,W31,$D$2:$D89,"ABIERTA")) -> ... | Y31: =if(W31=0,"",AA31/$AF$20) | Z31: =if(X31=0,"...",if(W31=0,"...",sumifs($N$2:$N89,$B$2:$B89,W31,$D$2:$D89,"ABIERTA")/X31)) -> ... | AA31: =if(W31=0,"...",sumifs($Q$2:$Q89,$B$2:$B89,W31,$D$2:$D89,"ABIERTA")) -> ... | AB31: =if(X31=0,"...",if(W31=0,"...",AC31/(AA31-AC31))) -> ... | AC31: =if(X31=0,"...",if(W31=0,"...",sumifs($S$2:$S89,$B$2:$B89,W31,$D$2:$D89,"ABIERTA"))) -> ...
A32: IOL | B32: SPY | C32: 45020 | D32: CERRADA | E32: 45294 | F32: =if($B32=0,"...", IF($E32=0,today()-$C32,$E32-$C32)) -> 274 | G32: PESOS | H32: 5 | I32: 8278 | J32: 24350 | K32: =IFERROR(__xludf.DUMMYFUNCTION("if(B32=0,""..."",GOOGLEFINANCE(""BCBA:""&B32))"),51650.0) -> 51650 | L32: =if(B32=0,"...",$H32*I32) -> 41390 | M32: =VLOOKUP(C32,CCLHistory!$A$6:$B84,2,FALSE) -> 409,82 | N32: =L32/M32 -> 100.99556 | O32: =if(B32=0,"...",$H32*(IF(D32="ABIERTA",K32,J32)*(1-VLOOKUP(A32,Config!$A$3:$B$5,2,FALSE)))) -> 121743.91 | P32: 1030 | Q32: =O32/P32 -> 118.19797 | R32: =if(B32=0,"...",Q32/N32-1) -> 0.17032842 | S32: =if(B32=0,"...",Q32-N32) -> 17.202414 | T32: =if(B32=0,"...",O32/L32-1) -> 1.9413847 | U32: =if(B32=0,"...",O32-L32) -> 80353.913 | X32: =if(W32=0,"...",sumifs($H$2:$H90,$B$2:$B90,W32,$D$2:$D90,"ABIERTA")) -> ... | Y32: =if(W32=0,"",AA32/$AF$20) | Z32: =if(X32=0,"...",if(W32=0,"...",sumifs($N$2:$N90,$B$2:$B90,W32,$D$2:$D90,"ABIERTA")/X32)) -> ... | AA32: =if(W32=0,"...",sumifs($Q$2:$Q90,$B$2:$B90,W32,$D$2:$D90,"ABIERTA")) -> ... | AB32: =if(X32=0,"...",if(W32=0,"...",AC32/(AA32-AC32))) -> ... | AC32: =if(X32=0,"...",if(W32=0,"...",sumifs($S$2:$S90,$B$2:$B90,W32,$D$2:$D90,"ABIERTA"))) -> ...
A33: IOL | B33: AAPL | C33: 44148 | D33: CERRADA | E33: 44305 | F33: =if(B33=0,"...", IF(E33=0,today()-C33,E33-C33)) -> 157 | G33: PESOS | H33: 2 | I33: =1765*(1-VLOOKUP(A33,Config!A3:B5,2,FALSE)) -> 1764.9117 | J33: 2036 | K33: =IFERROR(__xludf.DUMMYFUNCTION("if(B33=0,""..."",GOOGLEFINANCE(""BCBA:""&B33))"),21040.0) -> 21040 | L33: =if(B33=0,"...",$H33*I33) -> 3529.8235 | M33: =VLOOKUP(C33,CCLHistory!$A$6:$B84,2,FALSE) -> 148,74 | N33: =L33/M33 -> 23.731501 | O33: =if(B33=0,"...",$H33*(IF(D33="ABIERTA",K33,J33)*(1-VLOOKUP(A33,Config!$A$3:$B$5,2,FALSE)))) -> 4071.7964 | P33: =IF(D33="ABIERTA",Config!$D$4,VLOOKUP(E33,CCLHistory!$A$6:$B84,2,FALSE)) -> 151,81 | Q33: =O33/P33 -> 26.821661 | R33: =if(B33=0,"...",Q33/N33-1) -> 0.13021342 | S33: =if(B33=0,"...",Q33-N33) -> 3.09016 | T33: =if(B33=0,"...",O33/L33-1) -> 0.15354108 | U33: =if(B33=0,"...",O33-L33) -> 541.9729 | X33: =if(W33=0,"...",sumifs($H$2:$H91,$B$2:$B91,W33,$D$2:$D91,"ABIERTA")) -> ... | Y33: =if(W33=0,"",AA33/$AF$20) | Z33: =if(X33=0,"...",if(W33=0,"...",sumifs($N$2:$N91,$B$2:$B91,W33,$D$2:$D91,"ABIERTA")/X33)) -> ... | AA33: =if(W33=0,"...",sumifs($Q$2:$Q91,$B$2:$B91,W33,$D$2:$D91,"ABIERTA")) -> ... | AB33: =if(X33=0,"...",if(W33=0,"...",AC33/(AA33-AC33))) -> ... | AC33: =if(X33=0,"...",if(W33=0,"...",sumifs($S$2:$S91,$B$2:$B91,W33,$D$2:$D91,"ABIERTA"))) -> ...
A34: IOL | B34: AAPL | C34: 44155 | D34: CERRADA | E34: 44799 | F34: =if(B34=0,"...", IF(E34=0,today()-C34,E34-C34)) -> 644 | G34: PESOS | H34: 2 | I34: =1805 -> 1805 | J34: 5030 | K34: =IFERROR(__xludf.DUMMYFUNCTION("if(B34=0,""..."",GOOGLEFINANCE(""BCBA:""&B34))"),21040.0) -> 21040 | L34: =if(B34=0,"...",$H34*I34) -> 3610 | M34: =VLOOKUP(C34,CCLHistory!$A$6:$B84,2,FALSE) -> 154,26 | N34: =L34/M34 -> 23.402048 | O34: =if(B34=0,"...",$H34*(IF(D34="ABIERTA",K34,J34)*(1-VLOOKUP(A34,Config!$A$3:$B$5,2,FALSE)))) -> 10059.497 | P34: =IF(D34="ABIERTA",Config!$D$4,VLOOKUP(E34,CCLHistory!$A$6:$B84,2,FALSE)) -> 289,2 | Q34: =O34/P34 -> 34.783876 | R34: =if(B34=0,"...",Q34/N34-1) -> 0.48636032 | S34: =if(B34=0,"...",Q34-N34) -> 11.381828 | T34: =if(B34=0,"...",O34/L34-1) -> 1.7865643 | U34: =if(B34=0,"...",O34-L34) -> 6449.497 | X34: =if(W34=0,"...",sumifs($H$2:$H92,$B$2:$B92,W34,$D$2:$D92,"ABIERTA")) -> ... | Y34: =if(W34=0,"",AA34/$AF$20) | Z34: =if(X34=0,"...",if(W34=0,"...",sumifs($N$2:$N92,$B$2:$B92,W34,$D$2:$D92,"ABIERTA")/X34)) -> ... | AA34: =if(W34=0,"...",sumifs($Q$2:$Q92,$B$2:$B92,W34,$D$2:$D92,"ABIERTA")) -> ... | AB34: =if(X34=0,"...",if(W34=0,"...",AC34/(AA34-AC34))) -> ... | AC34: =if(X34=0,"...",if(W34=0,"...",sumifs($S$2:$S92,$B$2:$B92,W34,$D$2:$D92,"ABIERTA"))) -> ...
A35: IOL | B35: AAPL | C35: 44334 | D35: CERRADA | E35: 44799 | F35: =if(B35=0,"...", IF(E35=0,today()-C35,E35-C35)) -> 465 | G35: PESOS | H35: 2 | I35: 1997 | J35: 5030 | K35: =IFERROR(__xludf.DUMMYFUNCTION("if(B35=0,""..."",GOOGLEFINANCE(""BCBA:""&B35))"),21040.0) -> 21040 | L35: =if(B35=0,"...",$H35*I35) -> 3994 | M35: =VLOOKUP(C35,CCLHistory!$A$6:$B84,2,FALSE) -> 162,45 | N35: =L35/M35 -> 24.586026 | O35: =if(B35=0,"...",$H35*(IF(D35="ABIERTA",K35,J35)*(1-VLOOKUP(A35,Config!$A$3:$B$5,2,FALSE)))) -> 10059.497 | P35: =IF(D35="ABIERTA",Config!$D$4,VLOOKUP(E35,CCLHistory!$A$6:$B84,2,FALSE)) -> 289,2 | Q35: =O35/P35 -> 34.783876 | R35: =if(B35=0,"...",Q35/N35-1) -> 0.41478235 | S35: =if(B35=0,"...",Q35-N35) -> 10.19785 | T35: =if(B35=0,"...",O35/L35-1) -> 1.5186522 | U35: =if(B35=0,"...",O35-L35) -> 6065.497 | X35: =if(W35=0,"...",sumifs($H$2:$H93,$B$2:$B93,W35,$D$2:$D93,"ABIERTA")) -> ... | Y35: =if(W35=0,"",AA35/$AF$20) | Z35: =if(X35=0,"...",if(W35=0,"...",sumifs($N$2:$N93,$B$2:$B93,W35,$D$2:$D93,"ABIERTA")/X35)) -> ... | AA35: =if(W35=0,"...",sumifs($Q$2:$Q93,$B$2:$B93,W35,$D$2:$D93,"ABIERTA")) -> ... | AB35: =if(X35=0,"...",if(W35=0,"...",AC35/(AA35-AC35))) -> ... | AC35: =if(X35=0,"...",if(W35=0,"...",sumifs($S$2:$S93,$B$2:$B93,W35,$D$2:$D93,"ABIERTA"))) -> ...
A36: IOL | B36: AAPL | C36: 44649 | D36: CERRADA | E36: 44799 | F36: =if(B36=0,"...", IF(E36=0,today()-C36,E36-C36)) -> 150 | G36: PESOS | H36: 5 | I36: 3490 | J36: 5030 | K36: =IFERROR(__xludf.DUMMYFUNCTION("if(B36=0,""..."",GOOGLEFINANCE(""BCBA:""&B36))"),21040.0) -> 21040 | L36: =if(B36=0,"...",$H36*I36) -> 17450 | M36: =VLOOKUP(C36,CCLHistory!$A$6:$B84,2,FALSE) -> 191,52 | N36: =L36/M36 -> 91.1132 | O36: =if(B36=0,"...",$H36*(IF(D36="ABIERTA",K36,J36)*(1-VLOOKUP(A36,Config!$A$3:$B$5,2,FALSE)))) -> 25148.743 | P36: =IF(D36="ABIERTA",Config!$D$4,VLOOKUP(E36,CCLHistory!$A$6:$B84,2,FALSE)) -> 289,2 | Q36: =O36/P36 -> 86.959691 | R36: =if(B36=0,"...",Q36/N36-1) -> -0.04558625 | S36: =if(B36=0,"...",Q36-N36) -> -4.1535091 | T36: =if(B36=0,"...",O36/L36-1) -> 0.44118868 | U36: =if(B36=0,"...",O36-L36) -> 7698.7425 | X36: =if(W36=0,"...",sumifs($H$2:$H94,$B$2:$B94,W36,$D$2:$D94,"ABIERTA")) -> ... | Y36: =if(W36=0,"",AA36/$AF$20) | Z36: =if(X36=0,"...",if(W36=0,"...",sumifs($N$2:$N94,$B$2:$B94,W36,$D$2:$D94,"ABIERTA")/X36)) -> ... | AA36: =if(W36=0,"...",sumifs($Q$2:$Q94,$B$2:$B94,W36,$D$2:$D94,"ABIERTA")) -> ... | AB36: =if(X36=0,"...",if(W36=0,"...",AC36/(AA36-AC36))) -> ... | AC36: =if(X36=0,"...",if(W36=0,"...",sumifs($S$2:$S94,$B$2:$B94,W36,$D$2:$D94,"ABIERTA"))) -> ...
A37: IOL | B37: AAPL | C37: 44687 | D37: CERRADA | E37: 44799 | F37: =if(B37=0,"...", IF(E37=0,today()-C37,E37-C37)) -> 112 | G37: PESOS | H37: 5 | I37: 3339.5 | J37: 5030 | K37: =IFERROR(__xludf.DUMMYFUNCTION("if(B37=0,""..."",GOOGLEFINANCE(""BCBA:""&B37))"),21040.0) -> 21040 | L37: =if(B37=0,"...",$H37*I37) -> 16697.5 | M37: =VLOOKUP(C37,CCLHistory!$A$6:$B84,2,FALSE) -> 208,84 | N37: =L37/M37 -> 79.953553 | O37: =if(B37=0,"...",$H37*(IF(D37="ABIERTA",K37,J37)*(1-VLOOKUP(A37,Config!$A$3:$B$5,2,FALSE)))) -> 25148.743 | P37: =IF(D37="ABIERTA",Config!$D$4,VLOOKUP(E37,CCLHistory!$A$6:$B84,2,FALSE)) -> 289,2 | Q37: =O37/P37 -> 86.959691 | R37: =if(B37=0,"...",Q37/N37-1) -> 0.087627595 | S37: =if(B37=0,"...",Q37-N37) -> 7.0061376 | T37: =if(B37=0,"...",O37/L37-1) -> 0.50613819 | U37: =if(B37=0,"...",O37-L37) -> 8451.2425 | X37: =if(W37=0,"...",sumifs($H$2:$H95,$B$2:$B95,W37,$D$2:$D95,"ABIERTA")) -> ... | Y37: =if(W37=0,"",AA37/$AF$20) | Z37: =if(X37=0,"...",if(W37=0,"...",sumifs($N$2:$N95,$B$2:$B95,W37,$D$2:$D95,"ABIERTA")/X37)) -> ... | AA37: =if(W37=0,"...",sumifs($Q$2:$Q95,$B$2:$B95,W37,$D$2:$D95,"ABIERTA")) -> ... | AB37: =if(X37=0,"...",if(W37=0,"...",AC37/(AA37-AC37))) -> ... | AC37: =if(X37=0,"...",if(W37=0,"...",sumifs($S$2:$S95,$B$2:$B95,W37,$D$2:$D95,"ABIERTA"))) -> ...
A38: IOL | B38: AAPL | C38: 44715 | D38: CERRADA | E38: 44799 | F38: =if(B38=0,"...", IF(E38=0,today()-C38,E38-C38)) -> 84 | G38: PESOS | H38: 3 | I38: 3160 | J38: 5030 | K38: =IFERROR(__xludf.DUMMYFUNCTION("if(B38=0,""..."",GOOGLEFINANCE(""BCBA:""&B38))"),21040.0) -> 21040 | L38: =if(B38=0,"...",$H38*I38) -> 9480 | M38: =VLOOKUP(C38,CCLHistory!$A$6:$B84,2,FALSE) -> 209,39 | N38: =L38/M38 -> 45.274368 | O38: =if(B38=0,"...",$H38*(IF(D38="ABIERTA",K38,J38)*(1-VLOOKUP(A38,Config!$A$3:$B$5,2,FALSE)))) -> 15089.246 | P38: =IF(D38="ABIERTA",Config!$D$4,VLOOKUP(E38,CCLHistory!$A$6:$B84,2,FALSE)) -> 289,2 | Q38: =O38/P38 -> 52.175814 | R38: =if(B38=0,"...",Q38/N38-1) -> 0.15243605 | S38: =if(B38=0,"...",Q38-N38) -> 6.9014459 | T38: =if(B38=0,"...",O38/L38-1) -> 0.59169256 | U38: =if(B38=0,"...",O38-L38) -> 5609.2455 | X38: =if(W38=0,"...",sumifs($H$2:$H96,$B$2:$B96,W38,$D$2:$D96,"ABIERTA")) -> ... | Y38: =if(W38=0,"",AA38/$AF$20) | Z38: =if(X38=0,"...",if(W38=0,"...",sumifs($N$2:$N96,$B$2:$B96,W38,$D$2:$D96,"ABIERTA")/X38)) -> ... | AA38: =if(W38=0,"...",sumifs($Q$2:$Q96,$B$2:$B96,W38,$D$2:$D96,"ABIERTA")) -> ... | AB38: =if(X38=0,"...",if(W38=0,"...",AC38/(AA38-AC38))) -> ... | AC38: =if(X38=0,"...",if(W38=0,"...",sumifs($S$2:$S96,$B$2:$B96,W38,$D$2:$D96,"ABIERTA"))) -> ...
A39: IOL | B39: AAPL | C39: 44715 | D39: CERRADA | E39: 44811 | F39: =if(B39=0,"...", IF(E39=0,today()-C39,E39-C39)) -> 96 | G39: PESOS | H39: 6 | I39: 3160 | J39: 4449.5 | K39: =IFERROR(__xludf.DUMMYFUNCTION("if(B39=0,""..."",GOOGLEFINANCE(""BCBA:""&B39))"),21040.0) -> 21040 | L39: =if(B39=0,"...",$H39*I39) -> 18960 | M39: =VLOOKUP(C39,CCLHistory!$A$6:$B84,2,FALSE) -> 209,39 | N39: =L39/M39 -> 90.548737 | O39: =if(B39=0,"...",$H39*(IF(D39="ABIERTA",K39,J39)*(1-VLOOKUP(A39,Config!$A$3:$B$5,2,FALSE)))) -> 26695.665 | P39: =IF(D39="ABIERTA",Config!$D$4,VLOOKUP(E39,CCLHistory!$A$6:$B84,2,FALSE)) -> 282,46 | Q39: =O39/P39 -> 94.511312 | R39: =if(B39=0,"...",Q39/N39-1) -> 0.043761793 | S39: =if(B39=0,"...",Q39-N39) -> 3.9625751 | T39: =if(B39=0,"...",O39/L39-1) -> 0.40799922 | U39: =if(B39=0,"...",O39-L39) -> 7735.6651 | X39: =if(W39=0,"...",sumifs($H$2:$H97,$B$2:$B97,W39,$D$2:$D97,"ABIERTA")) -> ... | Y39: =if(W39=0,"",AA39/$AF$20) | Z39: =if(X39=0,"...",if(W39=0,"...",sumifs($N$2:$N97,$B$2:$B97,W39,$D$2:$D97,"ABIERTA")/X39)) -> ... | AA39: =if(W39=0,"...",sumifs($Q$2:$Q97,$B$2:$B97,W39,$D$2:$D97,"ABIERTA")) -> ... | AB39: =if(X39=0,"...",if(W39=0,"...",AC39/(AA39-AC39))) -> ... | AC39: =if(X39=0,"...",if(W39=0,"...",sumifs($S$2:$S97,$B$2:$B97,W39,$D$2:$D97,"ABIERTA"))) -> ...
A40: IOL | B40: AAPL | C40: 44777 | D40: CERRADA | E40: 44811 | F40: =if(B40=0,"...", IF(E40=0,today()-C40,E40-C40)) -> 34 | G40: PESOS | H40: 6 | I40: 4616 | J40: 4449.5 | K40: =IFERROR(__xludf.DUMMYFUNCTION("if(B40=0,""..."",GOOGLEFINANCE(""BCBA:""&B40))"),21040.0) -> 21040 | L40: =if(B40=0,"...",$H40*I40) -> 27696 | M40: =VLOOKUP(C40,CCLHistory!$A$6:$B84,2,FALSE) -> 293,31 | N40: =L40/M40 -> 94.425693 | O40: =if(B40=0,"...",$H40*(IF(D40="ABIERTA",K40,J40)*(1-VLOOKUP(A40,Config!$A$3:$B$5,2,FALSE)))) -> 26695.665 | P40: =IF(D40="ABIERTA",Config!$D$4,VLOOKUP(E40,CCLHistory!$A$6:$B84,2,FALSE)) -> 282,46 | Q40: =O40/P40 -> 94.511312 | R40: =if(B40=0,"...",Q40/N40-1) -> 0.00090673324 | S40: =if(B40=0,"...",Q40-N40) -> 0.085618914 | T40: =if(B40=0,"...",O40/L40-1) -> -0.036118387 | U40: =if(B40=0,"...",O40-L40) -> -1000.3348 | X40: =if(W40=0,"...",sumifs($H$2:$H98,$B$2:$B98,W40,$D$2:$D98,"ABIERTA")) -> ... | Y40: =if(W40=0,"",AA40/$AF$20) | Z40: =if(X40=0,"...",if(W40=0,"...",sumifs($N$2:$N98,$B$2:$B98,W40,$D$2:$D98,"ABIERTA")/X40)) -> ... | AA40: =if(W40=0,"...",sumifs($Q$2:$Q98,$B$2:$B98,W40,$D$2:$D98,"ABIERTA")) -> ... | AB40: =if(X40=0,"...",if(W40=0,"...",AC40/(AA40-AC40))) -> ... | AC40: =if(X40=0,"...",if(W40=0,"...",sumifs($S$2:$S98,$B$2:$B98,W40,$D$2:$D98,"ABIERTA"))) -> ...
A41: IOL | B41: AAPL | C41: 44778 | D41: CERRADA | E41: 45070 | F41: =if(B41=0,"...", IF(E41=0,today()-C41,E41-C41)) -> 292 | G41: PESOS | H41: 6 | I41: 4616 | J41: 9700 | K41: =IFERROR(__xludf.DUMMYFUNCTION("if(B41=0,""..."",GOOGLEFINANCE(""BCBA:""&B41))"),21040.0) -> 21040 | L41: =if(B41=0,"...",$H41*I41) -> 27696 | M41: =VLOOKUP(C41,CCLHistory!$A$6:$B84,2,FALSE) -> 285,54 | N41: =L41/M41 -> 96.995167 | O41: =if(B41=0,"...",$H41*(IF(D41="ABIERTA",K41,J41)*(1-VLOOKUP(A41,Config!$A$3:$B$5,2,FALSE)))) -> 58197.09 | P41: =IF(D41="ABIERTA",Config!$D$4,VLOOKUP(E41,CCLHistory!$A$6:$B84,2,FALSE)) -> 492,32 | Q41: =O41/P41 -> 118.20988 | R41: =if(B41=0,"...",Q41/N41-1) -> 0.21871932 | S41: =if(B41=0,"...",Q41-N41) -> 21.214717 | T41: =if(B41=0,"...",O41/L41-1) -> 1.1012814 | U41: =if(B41=0,"...",O41-L41) -> 30501.09 | X41: =if(W41=0,"...",sumifs($H$2:$H99,$B$2:$B99,W41,$D$2:$D99,"ABIERTA")) -> ... | Y41: =if(W41=0,"",AA41/$AF$20) | Z41: =if(X41=0,"...",if(W41=0,"...",sumifs($N$2:$N99,$B$2:$B99,W41,$D$2:$D99,"ABIERTA")/X41)) -> ... | AA41: =if(W41=0,"...",sumifs($Q$2:$Q99,$B$2:$B99,W41,$D$2:$D99,"ABIERTA")) -> ... | AB41: =if(X41=0,"...",if(W41=0,"...",AC41/(AA41-AC41))) -> ... | AC41: =if(X41=0,"...",if(W41=0,"...",sumifs($S$2:$S99,$B$2:$B99,W41,$D$2:$D99,"ABIERTA"))) -> ...
A42: IOL | B42: AAPL | C42: 44840 | D42: CERRADA | E42: 45070 | F42: =if(B42=0,"...", IF(E42=0,today()-C42,E42-C42)) -> 230 | G42: PESOS | H42: 4 | I42: 4483.5 | J42: 9700 | K42: =IFERROR(__xludf.DUMMYFUNCTION("if(B42=0,""..."",GOOGLEFINANCE(""BCBA:""&B42))"),21040.0) -> 21040 | L42: =if(B42=0,"...",$H42*I42) -> 17934 | M42: =VLOOKUP(C42,CCLHistory!$A$6:$B84,2,FALSE) -> 307,38 | N42: =L42/M42 -> 58.34472 | O42: =if(B42=0,"...",$H42*(IF(D42="ABIERTA",K42,J42)*(1-VLOOKUP(A42,Config!$A$3:$B$5,2,FALSE)))) -> 38798.06 | P42: =IF(D42="ABIERTA",Config!$D$4,VLOOKUP(E42,CCLHistory!$A$6:$B84,2,FALSE)) -> 492,32 | Q42: =O42/P42 -> 78.806589 | R42: =if(B42=0,"...",Q42/N42-1) -> 0.35070645 | S42: =if(B42=0,"...",Q42-N42) -> 20.461869 | T42: =if(B42=0,"...",O42/L42-1) -> 1.1633802 | U42: =if(B42=0,"...",O42-L42) -> 20864.06 | X42: =if(W42=0,"...",sumifs($H$2:$H100,$B$2:$B100,W42,$D$2:$D100,"ABIERTA")) -> ... | Y42: =if(W42=0,"",AA42/$AF$20) | Z42: =if(X42=0,"...",if(W42=0,"...",sumifs($N$2:$N100,$B$2:$B100,W42,$D$2:$D100,"ABIERTA")/X42)) -> ... | AA42: =if(W42=0,"...",sumifs($Q$2:$Q100,$B$2:$B100,W42,$D$2:$D100,"ABIERTA")) -> ... | AB42: =if(X42=0,"...",if(W42=0,"...",AC42/(AA42-AC42))) -> ... | AC42: =if(X42=0,"...",if(W42=0,"...",sumifs($S$2:$S100,$B$2:$B100,W42,$D$2:$D100,"ABIERTA"))) -> ...
A43: IOL | B43: AAPL | C43: 44939 | D43: CERRADA | E43: 45070 | F43: =if(B43=0,"...", IF(E43=0,today()-C43,E43-C43)) -> 131 | G43: PESOS | H43: 1 | I43: 4374 | J43: 9700 | K43: =IFERROR(__xludf.DUMMYFUNCTION("if(B43=0,""..."",GOOGLEFINANCE(""BCBA:""&B43))"),21040.0) -> 21040 | L43: =if(B43=0,"...",$H43*I43) -> 4374 | M43: =VLOOKUP(C43,CCLHistory!$A$6:$B84,2,FALSE) -> 349,26 | N43: =L43/M43 -> 12.523621 | O43: =if(B43=0,"...",$H43*(IF(D43="ABIERTA",K43,J43)*(1-VLOOKUP(A43,Config!$A$3:$B$5,2,FALSE)))) -> 9699.515 | P43: =IF(D43="ABIERTA",Config!$D$4,VLOOKUP(E43,CCLHistory!$A$6:$B84,2,FALSE)) -> 492,32 | Q43: =O43/P43 -> 19.701647 | R43: =if(B43=0,"...",Q43/N43-1) -> 0.57315897 | S43: =if(B43=0,"...",Q43-N43) -> 7.1780259 | T43: =if(B43=0,"...",O43/L43-1) -> 1.2175389 | U43: =if(B43=0,"...",O43-L43) -> 5325.515 | X43: =if(W43=0,"...",sumifs($H$2:$H101,$B$2:$B101,W43,$D$2:$D101,"ABIERTA")) -> ... | Y43: =if(W43=0,"",AA43/$AF$20) | Z43: =if(X43=0,"...",if(W43=0,"...",sumifs($N$2:$N101,$B$2:$B101,W43,$D$2:$D101,"ABIERTA")/X43)) -> ... | AA43: =if(W43=0,"...",sumifs($Q$2:$Q101,$B$2:$B101,W43,$D$2:$D101,"ABIERTA")) -> ... | AB43: =if(X43=0,"...",if(W43=0,"...",AC43/(AA43-AC43))) -> ... | AC43: =if(X43=0,"...",if(W43=0,"...",sumifs($S$2:$S101,$B$2:$B101,W43,$D$2:$D101,"ABIERTA"))) -> ...
A44: IOL | B44: DISN | C44: 44421 | D44: CERRADA | E44: 44473 | F44: =if(B44=0,"...", IF(E44=0,today()-C44,E44-C44)) -> 52 | G44: PESOS | H44: 4 | I44: 8075 | J44: 8312 | K44: =IFERROR(__xludf.DUMMYFUNCTION("if(B44=0,""..."",GOOGLEFINANCE(""BCBA:""&B44))"),13250.0) -> 13250 | L44: =if(B44=0,"...",$H44*I44) -> 32300 | M44: =VLOOKUP(C44,CCLHistory!$A$6:$B84,2,FALSE) -> 178,97 | N44: =L44/M44 -> 180.47717 | O44: =if(B44=0,"...",$H44*(IF(D44="ABIERTA",K44,J44)*(1-VLOOKUP(A44,Config!$A$3:$B$5,2,FALSE)))) -> 33246.338 | P44: =IF(D44="ABIERTA",Config!$D$4,VLOOKUP(E44,CCLHistory!$A$6:$B84,2,FALSE)) -> 192,82 | Q44: =O44/P44 -> 172.42162 | R44: =if(B44=0,"...",Q44/N44-1) -> -0.044634734 | S44: =if(B44=0,"...",Q44-N44) -> -8.0555506 | T44: =if(B44=0,"...",O44/L44-1) -> 0.029298378 | U44: =if(B44=0,"...",O44-L44) -> 946.3376 | X44: =if(W44=0,"...",sumifs($H$2:$H102,$B$2:$B102,W44,$D$2:$D102,"ABIERTA")) -> ... | Y44: =if(W44=0,"",AA44/$AF$20) | Z44: =if(X44=0,"...",if(W44=0,"...",sumifs($N$2:$N102,$B$2:$B102,W44,$D$2:$D102,"ABIERTA")/X44)) -> ... | AA44: =if(W44=0,"...",sumifs($Q$2:$Q102,$B$2:$B102,W44,$D$2:$D102,"ABIERTA")) -> ... | AB44: =if(X44=0,"...",if(W44=0,"...",AC44/(AA44-AC44))) -> ... | AC44: =if(X44=0,"...",if(W44=0,"...",sumifs($S$2:$S102,$B$2:$B102,W44,$D$2:$D102,"ABIERTA"))) -> ...
A45: IOL | B45: DISN | C45: 44516 | D45: CERRADA | E45: 44536 | F45: =if(B45=0,"...", IF(E45=0,today()-C45,E45-C45)) -> 20 | G45: PESOS | H45: 3 | I45: 8587 | J45: 7723.3333 | K45: =IFERROR(__xludf.DUMMYFUNCTION("if(B45=0,""..."",GOOGLEFINANCE(""BCBA:""&B45))"),13250.0) -> 13250 | L45: =if(B45=0,"...",$H45*I45) -> 25761 | M45: =VLOOKUP(C45,CCLHistory!$A$6:$B84,2,FALSE) -> 211,85 | N45: =L45/M45 -> 121.60019 | O45: =if(B45=0,"...",$H45*(IF(D45="ABIERTA",K45,J45)*(1-VLOOKUP(A45,Config!$A$3:$B$5,2,FALSE)))) -> 23168.841 | P45: =IF(D45="ABIERTA",Config!$D$4,VLOOKUP(E45,CCLHistory!$A$6:$B84,2,FALSE)) -> 219,77 | Q45: =O45/P45 -> 105.42313 | R45: =if(B45=0,"...",Q45/N45-1) -> -0.13303481 | S45: =if(B45=0,"...",Q45-N45) -> -16.177058 | T45: =if(B45=0,"...",O45/L45-1) -> -0.10062337 | U45: =if(B45=0,"...",O45-L45) -> -2592.1586 | X45: =if(W45=0,"...",sumifs($H$2:$H103,$B$2:$B103,W45,$D$2:$D103,"ABIERTA")) -> ... | Y45: =if(W45=0,"",AA45/$AF$20) | Z45: =if(X45=0,"...",if(W45=0,"...",sumifs($N$2:$N103,$B$2:$B103,W45,$D$2:$D103,"ABIERTA")/X45)) -> ... | AA45: =if(W45=0,"...",sumifs($Q$2:$Q103,$B$2:$B103,W45,$D$2:$D103,"ABIERTA")) -> ... | AB45: =if(X45=0,"...",if(W45=0,"...",AC45/(AA45-AC45))) -> ... | AC45: =if(X45=0,"...",if(W45=0,"...",sumifs($S$2:$S103,$B$2:$B103,W45,$D$2:$D103,"ABIERTA"))) -> ...
A46: IOL | B46: DISN | C46: 44516 | D46: CERRADA | E46: 44578 | F46: =IF(B46=0,"...", IF(E46=0,TODAY()-C46,E46-C46)) -> 62 | G46: PESOS | H46: 1 | I46: 8587 | J46: 8254 | K46: =IFERROR(__xludf.DUMMYFUNCTION("if(B46=0,""..."",GOOGLEFINANCE(""BCBA:""&B46))"),13250.0) -> 13250 | L46: =IF(B46=0,"...",$H46*I46) -> 8587 | M46: =VLOOKUP(C46,CCLHistory!$A$6:$B84,2,FALSE) -> 211,85 | N46: =L46/M46 -> 40.533396 | O46: =if(B46=0,"...",$H46*(IF(D46="ABIERTA",K46,J46)*(1-VLOOKUP(A46,Config!$A$3:$B$5,2,FALSE)))) -> 8253.5873 | P46: =IF(D46="ABIERTA",Config!$D$4,VLOOKUP(E46,CCLHistory!$A$6:$B84,2,FALSE)) -> 210,25 | Q46: =O46/P46 -> 39.256063 | R46: =if(B46=0,"...",Q46/N46-1) -> -0.031513101 | S46: =if(B46=0,"...",Q46-N46) -> -1.277333 | T46: =IF(B46=0,"...",O46/L46-1) -> -0.038827612 | U46: =IF(B46=0,"...",O46-L46) -> -333.4127 | X46: =if(W46=0,"...",sumifs($H$2:$H104,$B$2:$B104,W46,$D$2:$D104,"ABIERTA")) -> ... | Y46: =if(W46=0,"",AA46/$AF$20) | Z46: =if(X46=0,"...",if(W46=0,"...",sumifs($N$2:$N104,$B$2:$B104,W46,$D$2:$D104,"ABIERTA")/X46)) -> ... | AA46: =if(W46=0,"...",sumifs($Q$2:$Q104,$B$2:$B104,W46,$D$2:$D104,"ABIERTA")) -> ... | AB46: =if(X46=0,"...",if(W46=0,"...",AC46/(AA46-AC46))) -> ... | AC46: =if(X46=0,"...",if(W46=0,"...",sumifs($S$2:$S104,$B$2:$B104,W46,$D$2:$D104,"ABIERTA"))) -> ...
A47: IOL | B47: DISN | C47: 44518 | D47: CERRADA | E47: 44579 | F47: =if(B47=0,"...", IF(E47=0,today()-C47,E47-C47)) -> 61 | G47: PESOS | H47: 2 | I47: 8344 | J47: 8254 | K47: =IFERROR(__xludf.DUMMYFUNCTION("if(B47=0,""..."",GOOGLEFINANCE(""BCBA:""&B47))"),13250.0) -> 13250 | L47: =if(B47=0,"...",$H47*I47) -> 16688 | M47: =VLOOKUP(C47,CCLHistory!$A$6:$B84,2,FALSE) -> 213,32 | N47: =L47/M47 -> 78.229889 | O47: =if(B47=0,"...",$H47*(IF(D47="ABIERTA",K47,J47)*(1-VLOOKUP(A47,Config!$A$3:$B$5,2,FALSE)))) -> 16507.175 | P47: =IF(D47="ABIERTA",Config!$D$4,VLOOKUP(E47,CCLHistory!$A$6:$B84,2,FALSE)) -> 211,08 | Q47: =O47/P47 -> 78.203404 | R47: =if(B47=0,"...",Q47/N47-1) -> -0.0003385531 | S47: =if(B47=0,"...",Q47-N47) -> -0.026484972 | T47: =if(B47=0,"...",O47/L47-1) -> -0.010835654 | U47: =if(B47=0,"...",O47-L47) -> -180.8254 | X47: =if(W47=0,"...",sumifs($H$2:$H105,$B$2:$B105,W47,$D$2:$D105,"ABIERTA")) -> ... | Y47: =if(W47=0,"",AA47/$AF$20) | Z47: =if(X47=0,"...",if(W47=0,"...",sumifs($N$2:$N105,$B$2:$B105,W47,$D$2:$D105,"ABIERTA")/X47)) -> ... | AA47: =if(W47=0,"...",sumifs($Q$2:$Q105,$B$2:$B105,W47,$D$2:$D105,"ABIERTA")) -> ... | AB47: =if(X47=0,"...",if(W47=0,"...",AC47/(AA47-AC47))) -> ... | AC47: =if(X47=0,"...",if(W47=0,"...",sumifs($S$2:$S105,$B$2:$B105,W47,$D$2:$D105,"ABIERTA"))) -> ...
A48: IOL | B48: JNJ | C48: 44425 | D48: CERRADA | E48: 44516 | F48: =if(B48=0,"...", IF(E48=0,today()-C48,E48-C48)) -> 91 | G48: PESOS | H48: 3 | I48: 6155.5 | J48: 7133.9 | K48: =IFERROR(__xludf.DUMMYFUNCTION("if(B48=0,""..."",GOOGLEFINANCE(""BCBA:""&B48))"),20200.0) -> 20200 | L48: =if(B48=0,"...",$H48*I48) -> 18466.5 | M48: =VLOOKUP(C48,CCLHistory!$A$6:$B84,2,FALSE) -> 177,07 | N48: =L48/M48 -> 104.28926 | O48: =if(B48=0,"...",$H48*(IF(D48="ABIERTA",K48,J48)*(1-VLOOKUP(A48,Config!$A$3:$B$5,2,FALSE)))) -> 21400.63 | P48: =IF(D48="ABIERTA",Config!$D$4,VLOOKUP(E48,CCLHistory!$A$6:$B84,2,FALSE)) -> 211,85 | Q48: =O48/P48 -> 101.01784 | R48: =if(B48=0,"...",Q48/N48-1) -> -0.03136873 | S48: =if(B48=0,"...",Q48-N48) -> -3.2714217 | T48: =if(B48=0,"...",O48/L48-1) -> 0.15888934 | U48: =if(B48=0,"...",O48-L48) -> 2934.1299 | X48: =if(W48=0,"...",sumifs($H$2:$H106,$B$2:$B106,W48,$D$2:$D106,"ABIERTA")) -> ... | Y48: =if(W48=0,"",AA48/$AF$20) | Z48: =if(X48=0,"...",if(W48=0,"...",sumifs($N$2:$N106,$B$2:$B106,W48,$D$2:$D106,"ABIERTA")/X48)) -> ... | AA48: =if(W48=0,"...",sumifs($Q$2:$Q106,$B$2:$B106,W48,$D$2:$D106,"ABIERTA")) -> ... | AB48: =if(X48=0,"...",if(W48=0,"...",AC48/(AA48-AC48))) -> ... | AC48: =if(X48=0,"...",if(W48=0,"...",sumifs($S$2:$S106,$B$2:$B106,W48,$D$2:$D106,"ABIERTA"))) -> ...
A49: IOL | B49: JNJ | C49: 44459 | D49: CERRADA | E49: 44517 | F49: =if(B49=0,"...", IF(E49=0,today()-C49,E49-C49)) -> 58 | G49: PESOS | H49: 2 | I49: 5925 | J49: 7133.9 | K49: =IFERROR(__xludf.DUMMYFUNCTION("if(B49=0,""..."",GOOGLEFINANCE(""BCBA:""&B49))"),20200.0) -> 20200 | L49: =if(B49=0,"...",$H49*I49) -> 11850 | M49: =VLOOKUP(C49,CCLHistory!$A$6:$B84,2,FALSE) -> 185,38 | N49: =L49/M49 -> 63.922753 | O49: =if(B49=0,"...",$H49*(IF(D49="ABIERTA",K49,J49)*(1-VLOOKUP(A49,Config!$A$3:$B$5,2,FALSE)))) -> 14267.087 | P49: =IF(D49="ABIERTA",Config!$D$4,VLOOKUP(E49,CCLHistory!$A$6:$B84,2,FALSE)) -> 212,66 | Q49: =O49/P49 -> 67.088717 | R49: =if(B49=0,"...",Q49/N49-1) -> 0.049527967 | S49: =if(B49=0,"...",Q49-N49) -> 3.165964 | T49: =if(B49=0,"...",O49/L49-1) -> 0.20397355 | U49: =if(B49=0,"...",O49-L49) -> 2417.0866 | X49: =if(W49=0,"...",sumifs($H$2:$H107,$B$2:$B107,W49,$D$2:$D107,"ABIERTA")) -> ... | Y49: =if(W49=0,"",AA49/$AF$20) | Z49: =if(X49=0,"...",if(W49=0,"...",sumifs($N$2:$N107,$B$2:$B107,W49,$D$2:$D107,"ABIERTA")/X49)) -> ... | AA49: =if(W49=0,"...",sumifs($Q$2:$Q107,$B$2:$B107,W49,$D$2:$D107,"ABIERTA")) -> ... | AB49: =if(X49=0,"...",if(W49=0,"...",AC49/(AA49-AC49))) -> ... | AC49: =if(X49=0,"...",if(W49=0,"...",sumifs($S$2:$S107,$B$2:$B107,W49,$D$2:$D107,"ABIERTA"))) -> ...
A50: IOL | B50: JNJ | C50: 44533 | D50: CERRADA | E50: 44578 | F50: =if(B50=0,"...", IF(E50=0,today()-C50,E50-C50)) -> 45 | G50: PESOS | H50: 5 | I50: 6865 | J50: 7090 | K50: =IFERROR(__xludf.DUMMYFUNCTION("if(B50=0,""..."",GOOGLEFINANCE(""BCBA:""&B50))"),20200.0) -> 20200 | L50: =if(B50=0,"...",$H50*I50) -> 34325 | M50: =VLOOKUP(C50,CCLHistory!$A$6:$B84,2,FALSE) -> 218,34 | N50: =L50/M50 -> 157.20894 | O50: =if(B50=0,"...",$H50*(IF(D50="ABIERTA",K50,J50)*(1-VLOOKUP(A50,Config!$A$3:$B$5,2,FALSE)))) -> 35448.228 | P50: =IF(D50="ABIERTA",Config!$D$4,VLOOKUP(E50,CCLHistory!$A$6:$B84,2,FALSE)) -> 210,25 | Q50: =O50/P50 -> 168.60037 | R50: =if(B50=0,"...",Q50/N50-1) -> 0.072460436 | S50: =if(B50=0,"...",Q50-N50) -> 11.391428 | T50: =if(B50=0,"...",O50/L50-1) -> 0.032723307 | U50: =if(B50=0,"...",O50-L50) -> 1123.2275 | X50: =if(W50=0,"...",sumifs($H$2:$H108,$B$2:$B108,W50,$D$2:$D108,"ABIERTA")) -> ... | Y50: =if(W50=0,"",AA50/$AF$20) | Z50: =if(X50=0,"...",if(W50=0,"...",sumifs($N$2:$N108,$B$2:$B108,W50,$D$2:$D108,"ABIERTA")/X50)) -> ... | AA50: =if(W50=0,"...",sumifs($Q$2:$Q108,$B$2:$B108,W50,$D$2:$D108,"ABIERTA")) -> ... | AB50: =if(X50=0,"...",if(W50=0,"...",AC50/(AA50-AC50))) -> ... | AC50: =if(X50=0,"...",if(W50=0,"...",sumifs($S$2:$S108,$B$2:$B108,W50,$D$2:$D108,"ABIERTA"))) -> ...
A51: IOL | B51: BRKB | C51: 44582 | D51: CERRADA | E51: 44707 | F51: =if(B51=0,"...", IF(E51=0,today()-C51,E51-C51)) -> 125 | G51: PESOS | H51: 4 | I51: 3075 | J51: 2938 | K51: =IFERROR(__xludf.DUMMYFUNCTION("if(B51=0,""..."",GOOGLEFINANCE(""BCBA:""&B51))"),34340.0) -> 34340 | L51: =if(B51=0,"...",$H51*I51) -> 12300 | M51: =VLOOKUP(C51,CCLHistory!$A$6:$B84,2,FALSE) -> 225,1 | N51: =L51/M51 -> 54.642381 | O51: =if(B51=0,"...",$H51*(IF(D51="ABIERTA",K51,J51)*(1-VLOOKUP(A51,Config!$A$3:$B$5,2,FALSE)))) -> 11751.412 | P51: =IF(D51="ABIERTA",Config!$D$4,VLOOKUP(E51,CCLHistory!$A$6:$B84,2,FALSE)) -> 214,35 | Q51: =O51/P51 -> 54.823477 | R51: =if(B51=0,"...",Q51/N51-1) -> 0.00331421 | S51: =if(B51=0,"...",Q51-N51) -> 0.18109633 | T51: =if(B51=0,"...",O51/L51-1) -> -0.044600618 | U51: =if(B51=0,"...",O51-L51) -> -548.5876
A52: IOL | B52: BRKB | C52: 44582 | D52: CERRADA | E52: 44697 | F52: =if(B52=0,"...", IF(E52=0,today()-C52,E52-C52)) -> 115 | G52: PESOS | H52: 7 | I52: 3073 | J52: 2876 | K52: =IFERROR(__xludf.DUMMYFUNCTION("if(B52=0,""..."",GOOGLEFINANCE(""BCBA:""&B52))"),34340.0) -> 34340 | L52: =if(B52=0,"...",$H52*I52) -> 21511 | M52: =VLOOKUP(C52,CCLHistory!$A$6:$B84,2,FALSE) -> 225,1 | N52: =L52/M52 -> 95.561972 | O52: =if(B52=0,"...",$H52*(IF(D52="ABIERTA",K52,J52)*(1-VLOOKUP(A52,Config!$A$3:$B$5,2,FALSE)))) -> 20130.993 | P52: =IF(D52="ABIERTA",Config!$D$4,VLOOKUP(E52,CCLHistory!$A$6:$B84,2,FALSE)) -> 213,54 | Q52: =O52/P52 -> 94.272705 | R52: =if(B52=0,"...",Q52/N52-1) -> -0.013491429 | S52: =if(B52=0,"...",Q52-N52) -> -1.2892676 | T52: =if(B52=0,"...",O52/L52-1) -> -0.064153531 | U52: =if(B52=0,"...",O52-L52) -> -1380.0066
A53: IOL | B53: BRKB | C53: 44649 | D53: CERRADA | E53: 44707 | F53: =if(B53=0,"...", IF(E53=0,today()-C53,E53-C53)) -> 58 | G53: PESOS | H53: 6 | I53: 3245 | J53: 2938 | K53: =IFERROR(__xludf.DUMMYFUNCTION("if(B53=0,""..."",GOOGLEFINANCE(""BCBA:""&B53))"),34340.0) -> 34340 | L53: =if(B53=0,"...",$H53*I53) -> 19470 | M53: =VLOOKUP(C53,CCLHistory!$A$6:$B84,2,FALSE) -> 191,52 | N53: =L53/M53 -> 101.6604 | O53: =if(B53=0,"...",$H53*(IF(D53="ABIERTA",K53,J53)*(1-VLOOKUP(A53,Config!$A$3:$B$5,2,FALSE)))) -> 17627.119 | P53: =IF(D53="ABIERTA",Config!$D$4,VLOOKUP(E53,CCLHistory!$A$6:$B84,2,FALSE)) -> 214,35 | Q53: =O53/P53 -> 82.235216 | R53: =if(B53=0,"...",Q53/N53-1) -> -0.19107917 | S53: =if(B53=0,"...",Q53-N53) -> -19.425185 | T53: =if(B53=0,"...",O53/L53-1) -> -0.094652357 | U53: =if(B53=0,"...",O53-L53) -> -1842.8814
A54: IOL | B54: BRKB | C54: 44693 | D54: CERRADA | E54: 44697 | F54: =if(B54=0,"...", IF(E54=0,today()-C54,E54-C54)) -> 4 | G54: PESOS | H54: 2 | I54: 2948 | J54: 2876 | K54: =IFERROR(__xludf.DUMMYFUNCTION("if(B54=0,""..."",GOOGLEFINANCE(""BCBA:""&B54))"),34340.0) -> 34340 | L54: =if(B54=0,"...",$H54*I54) -> 5896 | M54: =VLOOKUP(C54,CCLHistory!$A$6:$B84,2,FALSE) -> 209,81 | N54: =L54/M54 -> 28.101616 | O54: =if(B54=0,"...",$H54*(IF(D54="ABIERTA",K54,J54)*(1-VLOOKUP(A54,Config!$A$3:$B$5,2,FALSE)))) -> 5751.7124 | P54: =IF(D54="ABIERTA",Config!$D$4,VLOOKUP(E54,CCLHistory!$A$6:$B84,2,FALSE)) -> 213,54 | Q54: =O54/P54 -> 26.935059 | R54: =if(B54=0,"...",Q54/N54-1) -> -0.041512105 | S54: =if(B54=0,"...",Q54-N54) -> -1.1665572 | T54: =if(B54=0,"...",O54/L54-1) -> -0.024472117 | U54: =if(B54=0,"...",O54-L54) -> -144.2876
A55: IOL | B55: HMY | C55: 44600 | D55: CERRADA | E55: 45126 | F55: =if(B55=0,"...", IF(E55=0,today()-C55,E55-C55)) -> 526 | G55: PESOS | H55: 24 | I55: 804.4375 | J55: 2425 | K55: =IFERROR(__xludf.DUMMYFUNCTION("if(B55=0,""..."",GOOGLEFINANCE(""BCBA:""&B55))"),29860.0) -> 29860 | L55: =if(B55=0,"...",$H55*I55) -> 19306.5 | M55: =VLOOKUP(C55,CCLHistory!$A$6:$B84,2,FALSE) -> 215,04 | N55: =L55/M55 -> 89.780971 | O55: =if(B55=0,"...",$H55*(IF(D55="ABIERTA",K55,J55)*(1-VLOOKUP(A55,Config!$A$3:$B$5,2,FALSE)))) -> 58197.09 | P55: =IF(D55="ABIERTA",Config!$D$4,VLOOKUP(E55,CCLHistory!$A$6:$B84,2,FALSE)) -> 528,27 | Q55: =O55/P55 -> 110.16543 | R55: =if(B55=0,"...",Q55/N55-1) -> 0.22704651 | S55: =if(B55=0,"...",Q55-N55) -> 20.384456 | T55: =if(B55=0,"...",O55/L55-1) -> 2.0143781 | U55: =if(B55=0,"...",O55-L55) -> 38890.59
A56: IOL | B56: HMY | C56: 44649 | D56: CERRADA | E56: 45126 | F56: =if(B56=0,"...", IF(E56=0,today()-C56,E56-C56)) -> 477 | G56: PESOS | H56: 11 | I56: 1038 | J56: 2425 | K56: =IFERROR(__xludf.DUMMYFUNCTION("if(B56=0,""..."",GOOGLEFINANCE(""BCBA:""&B56))"),29860.0) -> 29860 | L56: =if(B56=0,"...",$H56*I56) -> 11418 | M56: =VLOOKUP(C56,CCLHistory!$A$6:$B84,2,FALSE) -> 191,52 | N56: =L56/M56 -> 59.617794 | O56: =if(B56=0,"...",$H56*(IF(D56="ABIERTA",K56,J56)*(1-VLOOKUP(A56,Config!$A$3:$B$5,2,FALSE)))) -> 26673.666 | P56: =IF(D56="ABIERTA",Config!$D$4,VLOOKUP(E56,CCLHistory!$A$6:$B84,2,FALSE)) -> 528,27 | Q56: =O56/P56 -> 50.492487 | R56: =if(B56=0,"...",Q56/N56-1) -> -0.15306348 | S56: =if(B56=0,"...",Q56-N56) -> -9.1253072 | T56: =if(B56=0,"...",O56/L56-1) -> 1.3361067 | U56: =if(B56=0,"...",O56-L56) -> 15255.666
A57: IOL | B57: HMY | C57: 44701 | D57: CERRADA | E57: 45126 | F57: =if(B57=0,"...", IF(E57=0,today()-C57,E57-C57)) -> 425 | G57: PESOS | H57: 13 | I57: 760 | J57: 2425 | K57: =IFERROR(__xludf.DUMMYFUNCTION("if(B57=0,""..."",GOOGLEFINANCE(""BCBA:""&B57))"),29860.0) -> 29860 | L57: =if(B57=0,"...",$H57*I57) -> 9880 | M57: =VLOOKUP(C57,CCLHistory!$A$6:$B84,2,FALSE) -> 211,22 | N57: =L57/M57 -> 46.775874 | O57: =if(B57=0,"...",$H57*(IF(D57="ABIERTA",K57,J57)*(1-VLOOKUP(A57,Config!$A$3:$B$5,2,FALSE)))) -> 31523.424 | P57: =IF(D57="ABIERTA",Config!$D$4,VLOOKUP(E57,CCLHistory!$A$6:$B84,2,FALSE)) -> 528,27 | Q57: =O57/P57 -> 59.672939 | R57: =if(B57=0,"...",Q57/N57-1) -> 0.27572047 | S57: =if(B57=0,"...",Q57-N57) -> 12.897066 | T57: =if(B57=0,"...",O57/L57-1) -> 2.1906299 | U57: =if(B57=0,"...",O57-L57) -> 21643.424
A58: IOL | B58: INTC | C58: 44133 | D58: CERRADA | E58: 44425 | F58: =if(B58=0,"...", IF(E58=0,today()-C58,E58-C58)) -> 292 | G58: PESOS | H58: 2 | I58: 1530 | J58: 1896.5 | K58: =IFERROR(__xludf.DUMMYFUNCTION("if(B58=0,""..."",GOOGLEFINANCE(""BCBA:""&B58))"),12660.0) -> 12660 | L58: =if(B58=0,"...",$H58*I58) -> 3060 | M58: =VLOOKUP(C58,CCLHistory!$A$6:$B84,2,FALSE) -> 159,83 | N58: =L58/M58 -> 19.145342 | O58: =if(B58=0,"...",$H58*(IF(D58="ABIERTA",K58,J58)*(1-VLOOKUP(A58,Config!$A$3:$B$5,2,FALSE)))) -> 3792.8104 | P58: =IF(D58="ABIERTA",Config!$D$4,VLOOKUP(E58,CCLHistory!$A$6:$B84,2,FALSE)) -> 177,07 | Q58: =O58/P58 -> 21.419836 | R58: =if(B58=0,"...",Q58/N58-1) -> 0.11880143 | S58: =if(B58=0,"...",Q58-N58) -> 2.274494 | T58: =if(B58=0,"...",O58/L58-1) -> 0.23948051 | U58: =if(B58=0,"...",O58-L58) -> 732.81035
A59: IOL | B59: INTC | C59: 44138 | D59: CERRADA | E59: 44425 | F59: =if(B59=0,"...", IF(E59=0,today()-C59,E59-C59)) -> 287 | G59: PESOS | H59: 1 | I59: 1362.5 | J59: 1896.5 | K59: =IFERROR(__xludf.DUMMYFUNCTION("if(B59=0,""..."",GOOGLEFINANCE(""BCBA:""&B59))"),12660.0) -> 12660 | L59: =if(B59=0,"...",$H59*I59) -> 1362.5 | M59: =VLOOKUP(C59,CCLHistory!$A$6:$B84,2,FALSE) -> 153,9 | N59: =L59/M59 -> 8.8531514 | O59: =if(B59=0,"...",$H59*(IF(D59="ABIERTA",K59,J59)*(1-VLOOKUP(A59,Config!$A$3:$B$5,2,FALSE)))) -> 1896.4052 | P59: =IF(D59="ABIERTA",Config!$D$4,VLOOKUP(E59,CCLHistory!$A$6:$B84,2,FALSE)) -> 177,07 | Q59: =O59/P59 -> 10.709918 | R59: =if(B59=0,"...",Q59/N59-1) -> 0.20972945 | S59: =if(B59=0,"...",Q59-N59) -> 1.8567666 | T59: =if(B59=0,"...",O59/L59-1) -> 0.39185701 | U59: =if(B59=0,"...",O59-L59) -> 533.90517
A60: IOL | B60: INTC | C60: 44322 | D60: CERRADA | E60: 44425 | F60: =if(B60=0,"...", IF(E60=0,today()-C60,E60-C60)) -> 103 | G60: PESOS | H60: 1 | I60: 1830.5 | J60: 1896.5 | K60: =IFERROR(__xludf.DUMMYFUNCTION("if(B60=0,""..."",GOOGLEFINANCE(""BCBA:""&B60))"),12660.0) -> 12660 | L60: =if(B60=0,"...",$H60*I60) -> 1830.5 | M60: =VLOOKUP(C60,CCLHistory!$A$6:$B84,2,FALSE) -> 158,55 | N60: =L60/M60 -> 11.545254 | O60: =if(B60=0,"...",$H60*(IF(D60="ABIERTA",K60,J60)*(1-VLOOKUP(A60,Config!$A$3:$B$5,2,FALSE)))) -> 1896.4052 | P60: =IF(D60="ABIERTA",Config!$D$4,VLOOKUP(E60,CCLHistory!$A$6:$B84,2,FALSE)) -> 177,07 | Q60: =O60/P60 -> 10.709918 | R60: =if(B60=0,"...",Q60/N60-1) -> -0.072353185 | S60: =if(B60=0,"...",Q60-N60) -> -0.83533589 | T60: =if(B60=0,"...",O60/L60-1) -> 0.03600392 | U60: =if(B60=0,"...",O60-L60) -> 65.905175
A61: IOL | B61: INTC | C61: 44323 | D61: CERRADA | E61: 44217 | F61: =if(B61=0,"...", IF(E61=0,today()-C61,E61-C61)) -> -106 | G61: PESOS | H61: 1 | I61: 1830.5 | J61: 1735.5 | K61: =IFERROR(__xludf.DUMMYFUNCTION("if(B61=0,""..."",GOOGLEFINANCE(""BCBA:""&B61))"),12660.0) -> 12660 | L61: =if(B61=0,"...",$H61*I61) -> 1830.5 | M61: =VLOOKUP(C61,CCLHistory!$A$6:$B84,2,FALSE) -> 159,15 | N61: =L61/M61 -> 11.501728 | O61: =if(B61=0,"...",$H61*(IF(D61="ABIERTA",K61,J61)*(1-VLOOKUP(A61,Config!$A$3:$B$5,2,FALSE)))) -> 1735.4132 | P61: =IF(D61="ABIERTA",Config!$D$4,VLOOKUP(E61,CCLHistory!$A$6:$B84,2,FALSE)) -> 152,55 | Q61: =O61/P61 -> 11.376029 | R61: =if(B61=0,"...",Q61/N61-1) -> -0.010928699 | S61: =if(B61=0,"...",Q61-N61) -> -0.12569892 | T61: =if(B61=0,"...",O61/L61-1) -> -0.051945793 | U61: =if(B61=0,"...",O61-L61) -> -95.086775
A62: IOL | B62: INTC | C62: 44337 | D62: CERRADA | E62: 44217 | F62: =if(B62=0,"...", IF(E62=0,today()-C62,E62-C62)) -> -120 | G62: PESOS | H62: 2 | I62: 1786 | J62: 1735.5 | K62: =IFERROR(__xludf.DUMMYFUNCTION("if(B62=0,""..."",GOOGLEFINANCE(""BCBA:""&B62))"),12660.0) -> 12660 | L62: =if(B62=0,"...",$H62*I62) -> 3572 | M62: =VLOOKUP(C62,CCLHistory!$A$6:$B84,2,FALSE) -> 165,32 | N62: =L62/M62 -> 21.606581 | O62: =if(B62=0,"...",$H62*(IF(D62="ABIERTA",K62,J62)*(1-VLOOKUP(A62,Config!$A$3:$B$5,2,FALSE)))) -> 3470.8265 | P62: =IF(D62="ABIERTA",Config!$D$4,VLOOKUP(E62,CCLHistory!$A$6:$B84,2,FALSE)) -> 152,55 | Q62: =O62/P62 -> 22.752058 | R62: =if(B62=0,"...",Q62/N62-1) -> 0.053015182 | S62: =if(B62=0,"...",Q62-N62) -> 1.1454768 | T62: =if(B62=0,"...",O62/L62-1) -> -0.028324062 | U62: =if(B62=0,"...",O62-L62) -> -101.17355
A63: IOL | B63: INTC | C63: 44799 | D63: CERRADA | E63: 45126 | F63: =if(B63=0,"...", IF(E63=0,today()-C63,E63-C63)) -> 327 | G63: PESOS | H63: 19 | I63: 2032 | J63: 3623 | K63: =IFERROR(__xludf.DUMMYFUNCTION("if(B63=0,""..."",GOOGLEFINANCE(""BCBA:""&B63))"),12660.0) -> 12660 | L63: =if(B63=0,"...",$H63*I63) -> 38608 | M63: =VLOOKUP(C63,CCLHistory!$A$6:$B84,2,FALSE) -> 289,2 | N63: =L63/M63 -> 133.49931 | O63: =if(B63=0,"...",$H63*(IF(D63="ABIERTA",K63,J63)*(1-VLOOKUP(A63,Config!$A$3:$B$5,2,FALSE)))) -> 68833.558 | P63: =IF(D63="ABIERTA",Config!$D$4,VLOOKUP(E63,CCLHistory!$A$6:$B84,2,FALSE)) -> 528,27 | Q63: =O63/P63 -> 130.29996 | R63: =if(B63=0,"...",Q63/N63-1) -> -0.023965305 | S63: =if(B63=0,"...",Q63-N63) -> -3.1993517 | T63: =if(B63=0,"...",O63/L63-1) -> 0.78288329 | U63: =if(B63=0,"...",O63-L63) -> 30225.558
A64: IOL | B64: INTC | C64: 44840 | D64: CERRADA | E64: 45126 | F64: =if(B64=0,"...", IF(E64=0,today()-C64,E64-C64)) -> 286 | G64: PESOS | H64: 4 | I64: 1706.5 | J64: 3623 | K64: =IFERROR(__xludf.DUMMYFUNCTION("if(B64=0,""..."",GOOGLEFINANCE(""BCBA:""&B64))"),12660.0) -> 12660 | L64: =if(B64=0,"...",$H64*I64) -> 6826 | M64: =VLOOKUP(C64,CCLHistory!$A$6:$B84,2,FALSE) -> 307,38 | N64: =L64/M64 -> 22.20704 | O64: =if(B64=0,"...",$H64*(IF(D64="ABIERTA",K64,J64)*(1-VLOOKUP(A64,Config!$A$3:$B$5,2,FALSE)))) -> 14491.275 | P64: =IF(D64="ABIERTA",Config!$D$4,VLOOKUP(E64,CCLHistory!$A$6:$B84,2,FALSE)) -> 528,27 | Q64: =O64/P64 -> 27.43157 | R64: =if(B64=0,"...",Q64/N64-1) -> 0.23526457 | S64: =if(B64=0,"...",Q64-N64) -> 5.2245297 | T64: =if(B64=0,"...",O64/L64-1) -> 1.1229527 | U64: =if(B64=0,"...",O64-L64) -> 7665.2754
A65: IOL | B65: MELI | C65: 44144 | D65: CERRADA | E65: 44169 | F65: =if(B65=0,"...", IF(E65=0,today()-C65,E65-C65)) -> 25 | G65: PESOS | H65: 1 | I65: 3312 | J65: 3728 | K65: =IFERROR(__xludf.DUMMYFUNCTION("if(B65=0,""..."",GOOGLEFINANCE(""BCBA:""&B65))"),27020.0) -> 27020 | L65: =if(B65=0,"...",$H65*I65) -> 3312 | M65: =VLOOKUP(C65,CCLHistory!$A$6:$B84,2,FALSE) -> 149,8 | N65: =L65/M65 -> 22.109479 | O65: =if(B65=0,"...",$H65*(IF(D65="ABIERTA",K65,J65)*(1-VLOOKUP(A65,Config!$A$3:$B$5,2,FALSE)))) -> 3727.8136 | P65: =IF(D65="ABIERTA",Config!$D$4,VLOOKUP(E65,CCLHistory!$A$6:$B84,2,FALSE)) -> 144,1 | Q65: =O65/P65 -> 25.869629 | R65: =if(B65=0,"...",Q65/N65-1) -> 0.17006959 | S65: =if(B65=0,"...",Q65-N65) -> 3.7601501 | T65: =if(B65=0,"...",O65/L65-1) -> 0.12554758 | U65: =if(B65=0,"...",O65-L65) -> 415.8136
A66: IOL | B66: MELI | C66: 44259 | D66: CERRADA | E66: 44356 | F66: =if(B66=0,"...", IF(E66=0,today()-C66,E66-C66)) -> 97 | G66: PESOS | H66: 1 | I66: 4100 | J66: 3666 | K66: =IFERROR(__xludf.DUMMYFUNCTION("if(B66=0,""..."",GOOGLEFINANCE(""BCBA:""&B66))"),27020.0) -> 27020 | L66: =if(B66=0,"...",$H66*I66) -> 4100 | M66: =VLOOKUP(C66,CCLHistory!$A$6:$B84,2,FALSE) -> 151,56 | N66: =L66/M66 -> 27.051993 | O66: =if(B66=0,"...",$H66*(IF(D66="ABIERTA",K66,J66)*(1-VLOOKUP(A66,Config!$A$3:$B$5,2,FALSE)))) -> 3665.8167 | P66: =IF(D66="ABIERTA",Config!$D$4,VLOOKUP(E66,CCLHistory!$A$6:$B84,2,FALSE)) -> 166,49 | Q66: =O66/P66 -> 22.01824 | R66: =if(B66=0,"...",Q66/N66-1) -> -0.18607698 | S66: =if(B66=0,"...",Q66-N66) -> -5.0337531 | T66: =if(B66=0,"...",O66/L66-1) -> -0.10589837 | U66: =if(B66=0,"...",O66-L66) -> -434.1833
A67: IOL | B67: MELI | C67: 44270 | D67: CERRADA | E67: 44356 | F67: =if(B67=0,"...", IF(E67=0,today()-C67,E67-C67)) -> 86 | G67: PESOS | H67: 1 | I67: 3910 | J67: 3666 | K67: =IFERROR(__xludf.DUMMYFUNCTION("if(B67=0,""..."",GOOGLEFINANCE(""BCBA:""&B67))"),27020.0) -> 27020 | L67: =if(B67=0,"...",$H67*I67) -> 3910 | M67: =VLOOKUP(C67,CCLHistory!$A$6:$B84,2,FALSE) -> 151,48 | N67: =L67/M67 -> 25.811988 | O67: =if(B67=0,"...",$H67*(IF(D67="ABIERTA",K67,J67)*(1-VLOOKUP(A67,Config!$A$3:$B$5,2,FALSE)))) -> 3665.8167 | P67: =IF(D67="ABIERTA",Config!$D$4,VLOOKUP(E67,CCLHistory!$A$6:$B84,2,FALSE)) -> 166,49 | Q67: =O67/P67 -> 22.01824 | R67: =if(B67=0,"...",Q67/N67-1) -> -0.14697623 | S67: =if(B67=0,"...",Q67-N67) -> -3.7937488 | T67: =if(B67=0,"...",O67/L67-1) -> -0.062450972 | U67: =if(B67=0,"...",O67-L67) -> -244.1833
A68: IOL | B68: MELI | C68: 44306 | D68: CERRADA | E68: 44356 | F68: =if(B68=0,"...", IF(E68=0,today()-C68,E68-C68)) -> 50 | G68: PESOS | H68: 2 | I68: 4015 | J68: 3666 | K68: =IFERROR(__xludf.DUMMYFUNCTION("if(B68=0,""..."",GOOGLEFINANCE(""BCBA:""&B68))"),27020.0) -> 27020 | L68: =if(B68=0,"...",$H68*I68) -> 8030 | M68: =VLOOKUP(C68,CCLHistory!$A$6:$B84,2,FALSE) -> 153,55 | N68: =L68/M68 -> 52.295669 | O68: =if(B68=0,"...",$H68*(IF(D68="ABIERTA",K68,J68)*(1-VLOOKUP(A68,Config!$A$3:$B$5,2,FALSE)))) -> 7331.6334 | P68: =IF(D68="ABIERTA",Config!$D$4,VLOOKUP(E68,CCLHistory!$A$6:$B84,2,FALSE)) -> 166,49 | Q68: =O68/P68 -> 44.036479 | R68: =if(B68=0,"...",Q68/N68-1) -> -0.15793258 | S68: =if(B68=0,"...",Q68-N68) -> -8.2591901 | T68: =if(B68=0,"...",O68/L68-1) -> -0.086969689 | U68: =if(B68=0,"...",O68-L68) -> -698.3666
A69: IOL | B69: MELI | C69: 44337 | D69: CERRADA | E69: 44356 | F69: =if(B69=0,"...", IF(E69=0,today()-C69,E69-C69)) -> 19 | G69: PESOS | H69: 1 | I69: 3596 | J69: 3666 | K69: =IFERROR(__xludf.DUMMYFUNCTION("if(B69=0,""..."",GOOGLEFINANCE(""BCBA:""&B69))"),27020.0) -> 27020 | L69: =if(B69=0,"...",$H69*I69) -> 3596 | M69: =VLOOKUP(C69,CCLHistory!$A$6:$B84,2,FALSE) -> 165,32 | N69: =L69/M69 -> 21.751754 | O69: =if(B69=0,"...",$H69*(IF(D69="ABIERTA",K69,J69)*(1-VLOOKUP(A69,Config!$A$3:$B$5,2,FALSE)))) -> 3665.8167 | P69: =IF(D69="ABIERTA",Config!$D$4,VLOOKUP(E69,CCLHistory!$A$6:$B84,2,FALSE)) -> 166,49 | Q69: =O69/P69 -> 22.01824 | R69: =if(B69=0,"...",Q69/N69-1) -> 0.012251212 | S69: =if(B69=0,"...",Q69-N69) -> 0.26648536 | T69: =if(B69=0,"...",O69/L69-1) -> 0.0194151 | U69: =if(B69=0,"...",O69-L69) -> 69.8167
A70: IOL | B70: MELI | C70: 44365 | D70: CERRADA | E70: 44425 | F70: =if(B70=0,"...", IF(E70=0,today()-C70,E70-C70)) -> 60 | G70: PESOS | H70: 3 | I70: 3947 | J70: 5501 | K70: =IFERROR(__xludf.DUMMYFUNCTION("if(B70=0,""..."",GOOGLEFINANCE(""BCBA:""&B70))"),27020.0) -> 27020 | L70: =if(B70=0,"...",$H70*I70) -> 11841 | M70: =VLOOKUP(C70,CCLHistory!$A$6:$B84,2,FALSE) -> 167,24 | N70: =L70/M70 -> 70.80244 | O70: =if(B70=0,"...",$H70*(IF(D70="ABIERTA",K70,J70)*(1-VLOOKUP(A70,Config!$A$3:$B$5,2,FALSE)))) -> 16502.175 | P70: =IF(D70="ABIERTA",Config!$D$4,VLOOKUP(E70,CCLHistory!$A$6:$B84,2,FALSE)) -> 177,07 | Q70: =O70/P70 -> 93.195769 | R70: =if(B70=0,"...",Q70/N70-1) -> 0.31627907 | S70: =if(B70=0,"...",Q70-N70) -> 22.39333 | T70: =if(B70=0,"...",O70/L70-1) -> 0.39364706 | U70: =if(B70=0,"...",O70-L70) -> 4661.1749
A71: IOL | B71: MELI | C71: 44365 | D71: CERRADA | E71: 44447 | F71: =if(B71=0,"...", IF(E71=0,today()-C71,E71-C71)) -> 82 | G71: PESOS | H71: 2 | I71: 3947 | J71: 5720 | K71: =IFERROR(__xludf.DUMMYFUNCTION("if(B71=0,""..."",GOOGLEFINANCE(""BCBA:""&B71))"),27020.0) -> 27020 | L71: =if(B71=0,"...",$H71*I71) -> 7894 | M71: =VLOOKUP(C71,CCLHistory!$A$6:$B84,2,FALSE) -> 167,24 | N71: =L71/M71 -> 47.201626 | O71: =if(B71=0,"...",$H71*(IF(D71="ABIERTA",K71,J71)*(1-VLOOKUP(A71,Config!$A$3:$B$5,2,FALSE)))) -> 11439.428 | P71: =IF(D71="ABIERTA",Config!$D$4,VLOOKUP(E71,CCLHistory!$A$6:$B84,2,FALSE)) -> 178,48 | Q71: =O71/P71 -> 64.093613 | R71: =if(B71=0,"...",Q71/N71-1) -> 0.35786873 | S71: =if(B71=0,"...",Q71-N71) -> 16.891986 | T71: =if(B71=0,"...",O71/L71-1) -> 0.44912947 | U71: =if(B71=0,"...",O71-L71) -> 3545.428
A72: IOL | B72: MELI | C72: 44365 | D72: CERRADA | E72: 44578 | F72: =if(B72=0,"...", IF(E72=0,today()-C72,E72-C72)) -> 213 | G72: PESOS | H72: 1 | I72: 3947 | J72: 4199.5 | K72: =IFERROR(__xludf.DUMMYFUNCTION("if(B72=0,""..."",GOOGLEFINANCE(""BCBA:""&B72))"),27020.0) -> 27020 | L72: =if(B72=0,"...",$H72*I72) -> 3947 | M72: =VLOOKUP(C72,CCLHistory!$A$6:$B84,2,FALSE) -> 167,24 | N72: =L72/M72 -> 23.600813 | O72: =if(B72=0,"...",$H72*(IF(D72="ABIERTA",K72,J72)*(1-VLOOKUP(A72,Config!$A$3:$B$5,2,FALSE)))) -> 4199.29 | P72: =IF(D72="ABIERTA",Config!$D$4,VLOOKUP(E72,CCLHistory!$A$6:$B84,2,FALSE)) -> 210,25 | Q72: =O72/P72 -> 19.972842 | R72: =if(B72=0,"...",Q72/N72-1) -> -0.1537223 | S72: =if(B72=0,"...",Q72-N72) -> -3.6279712 | T72: =if(B72=0,"...",O72/L72-1) -> 0.063919439 | U72: =if(B72=0,"...",O72-L72) -> 252.29003
A73: IOL | B73: MELI | C73: 44516 | D73: CERRADA | E73: 44578 | F73: =if(B73=0,"...", IF(E73=0,today()-C73,E73-C73)) -> 62 | G73: PESOS | H73: 4 | I73: 5750 | J73: 4199.5 | K73: =IFERROR(__xludf.DUMMYFUNCTION("if(B73=0,""..."",GOOGLEFINANCE(""BCBA:""&B73))"),27020.0) -> 27020 | L73: =if(B73=0,"...",$H73*I73) -> 23000 | M73: =VLOOKUP(C73,CCLHistory!$A$6:$B84,2,FALSE) -> 211,85 | N73: =L73/M73 -> 108.56738 | O73: =if(B73=0,"...",$H73*(IF(D73="ABIERTA",K73,J73)*(1-VLOOKUP(A73,Config!$A$3:$B$5,2,FALSE)))) -> 16797.16 | P73: =IF(D73="ABIERTA",Config!$D$4,VLOOKUP(E73,CCLHistory!$A$6:$B84,2,FALSE)) -> 210,25 | Q73: =O73/P73 -> 79.891368 | R73: =if(B73=0,"...",Q73/N73-1) -> -0.26413103 | S73: =if(B73=0,"...",Q73-N73) -> -28.676015 | T73: =if(B73=0,"...",O73/L73-1) -> -0.26968869 | U73: =if(B73=0,"...",O73-L73) -> -6202.8399
A74: IOL | B74: MELI | C74: 44517 | D74: CERRADA | E74: 44600 | F74: =if(B74=0,"...", IF(E74=0,today()-C74,E74-C74)) -> 83 | G74: PESOS | H74: 1 | I74: 5750 | J74: 3753.8 | K74: =IFERROR(__xludf.DUMMYFUNCTION("if(B74=0,""..."",GOOGLEFINANCE(""BCBA:""&B74))"),27020.0) -> 27020 | L74: =if(B74=0,"...",$H74*I74) -> 5750 | M74: =VLOOKUP(C74,CCLHistory!$A$6:$B84,2,FALSE) -> 212,66 | N74: =L74/M74 -> 27.038465 | O74: =if(B74=0,"...",$H74*(IF(D74="ABIERTA",K74,J74)*(1-VLOOKUP(A74,Config!$A$3:$B$5,2,FALSE)))) -> 3753.6123 | P74: =IF(D74="ABIERTA",Config!$D$4,VLOOKUP(E74,CCLHistory!$A$6:$B84,2,FALSE)) -> 215,04 | Q74: =O74/P74 -> 17.455414 | R74: =if(B74=0,"...",Q74/N74-1) -> -0.35442288 | S74: =if(B74=0,"...",Q74-N74) -> -9.5830508 | T74: =if(B74=0,"...",O74/L74-1) -> -0.34719786 | U74: =if(B74=0,"...",O74-L74) -> -1996.3877
A75: IOL | B75: MELI | C75: 44516 | D75: CERRADA | E75: 44600 | F75: =if(B75=0,"...", IF(E75=0,today()-C75,E75-C75)) -> 84 | G75: PESOS | H75: 4 | I75: 5750 | J75: 3753.8 | K75: =IFERROR(__xludf.DUMMYFUNCTION("if(B75=0,""..."",GOOGLEFINANCE(""BCBA:""&B75))"),27020.0) -> 27020 | L75: =if(B75=0,"...",$H75*I75) -> 23000 | M75: =VLOOKUP(C75,CCLHistory!$A$6:$B84,2,FALSE) -> 211,85 | N75: =L75/M75 -> 108.56738 | O75: =if(B75=0,"...",$H75*(IF(D75="ABIERTA",K75,J75)*(1-VLOOKUP(A75,Config!$A$3:$B$5,2,FALSE)))) -> 15014.449 | P75: =IF(D75="ABIERTA",Config!$D$4,VLOOKUP(E75,CCLHistory!$A$6:$B84,2,FALSE)) -> 215,04 | Q75: =O75/P75 -> 69.821658 | R75: =if(B75=0,"...",Q75/N75-1) -> -0.35688182 | S75: =if(B75=0,"...",Q75-N75) -> -38.745725 | T75: =if(B75=0,"...",O75/L75-1) -> -0.34719786 | U75: =if(B75=0,"...",O75-L75) -> -7985.5508
A76: IOL | B76: MSFT | C76: 44582 | D76: CERRADA | E76: 44692 | F76: =if(B76=0,"...", IF(E76=0,today()-C76,E76-C76)) -> 110 | G76: PESOS | H76: 4 | I76: 6610 | J76: 5581.3333 | K76: =IFERROR(__xludf.DUMMYFUNCTION("if(B76=0,""..."",GOOGLEFINANCE(""BCBA:""&B76))"),24150.0) -> 24150 | L76: =if(B76=0,"...",$H76*I76) -> 26440 | M76: =VLOOKUP(C76,CCLHistory!$A$6:$B84,2,FALSE) -> 225,1 | N76: =L76/M76 -> 117.45891 | O76: =if(B76=0,"...",$H76*(IF(D76="ABIERTA",K76,J76)*(1-VLOOKUP(A76,Config!$A$3:$B$5,2,FALSE)))) -> 22324.217 | P76: =IF(D76="ABIERTA",Config!$D$4,VLOOKUP(E76,CCLHistory!$A$6:$B84,2,FALSE)) -> 207,94 | Q76: =O76/P76 -> 107.35893 | R76: =if(B76=0,"...",Q76/N76-1) -> -0.085987282 | S76: =if(B76=0,"...",Q76-N76) -> -10.099972 | T76: =if(B76=0,"...",O76/L76-1) -> -0.15566502 | U76: =if(B76=0,"...",O76-L76) -> -4115.7831
A77: IOL | B77: MSFT | C77: 44582 | D77: CERRADA | E77: 44692 | F77: =if(B77=0,"...", IF(E77=0,today()-C77,E77-C77)) -> 110 | G77: PESOS | H77: 1 | I77: 6480 | J77: 5581.3333 | K77: =IFERROR(__xludf.DUMMYFUNCTION("if(B77=0,""..."",GOOGLEFINANCE(""BCBA:""&B77))"),24150.0) -> 24150 | L77: =if(B77=0,"...",$H77*I77) -> 6480 | M77: =VLOOKUP(C77,CCLHistory!$A$6:$B84,2,FALSE) -> 225,1 | N77: =L77/M77 -> 28.787206 | O77: =if(B77=0,"...",$H77*(IF(D77="ABIERTA",K77,J77)*(1-VLOOKUP(A77,Config!$A$3:$B$5,2,FALSE)))) -> 5581.0542 | P77: =IF(D77="ABIERTA",Config!$D$4,VLOOKUP(E77,CCLHistory!$A$6:$B84,2,FALSE)) -> 207,94 | Q77: =O77/P77 -> 26.839734 | R77: =if(B77=0,"...",Q77/N77-1) -> -0.067650607 | S77: =if(B77=0,"...",Q77-N77) -> -1.9474719 | T77: =if(B77=0,"...",O77/L77-1) -> -0.1387262 | U77: =if(B77=0,"...",O77-L77) -> -898.94577
A78: IOL | B78: MSFT | C78: 44649 | D78: CERRADA | E78: 44692 | F78: =if(B78=0,"...", IF(E78=0,today()-C78,E78-C78)) -> 43 | G78: PESOS | H78: 3 | I78: 6053.5 | J78: 5581.3333 | K78: =IFERROR(__xludf.DUMMYFUNCTION("if(B78=0,""..."",GOOGLEFINANCE(""BCBA:""&B78))"),24150.0) -> 24150 | L78: =if(B78=0,"...",$H78*I78) -> 18160.5 | M78: =VLOOKUP(C78,CCLHistory!$A$6:$B84,2,FALSE) -> 191,52 | N78: =L78/M78 -> 94.822995 | O78: =if(B78=0,"...",$H78*(IF(D78="ABIERTA",K78,J78)*(1-VLOOKUP(A78,Config!$A$3:$B$5,2,FALSE)))) -> 16743.163 | P78: =IF(D78="ABIERTA",Config!$D$4,VLOOKUP(E78,CCLHistory!$A$6:$B84,2,FALSE)) -> 207,94 | Q78: =O78/P78 -> 80.519201 | R78: =if(B78=0,"...",Q78/N78-1) -> -0.15084731 | S78: =if(B78=0,"...",Q78-N78) -> -14.303794 | T78: =if(B78=0,"...",O78/L78-1) -> -0.078045059 | U78: =if(B78=0,"...",O78-L78) -> -1417.3373
A79: IOL | B79: MSFT | C79: 44687 | D79: CERRADA | E79: 44692 | F79: =if(B79=0,"...", IF(E79=0,today()-C79,E79-C79)) -> 5 | G79: PESOS | H79: 1 | I79: 5823.5 | J79: 5581.3333 | K79: =IFERROR(__xludf.DUMMYFUNCTION("if(B79=0,""..."",GOOGLEFINANCE(""BCBA:""&B79))"),24150.0) -> 24150 | L79: =if(B79=0,"...",$H79*I79) -> 5823.5 | M79: =VLOOKUP(C79,CCLHistory!$A$6:$B84,2,FALSE) -> 208,84 | N79: =L79/M79 -> 27.884984 | O79: =if(B79=0,"...",$H79*(IF(D79="ABIERTA",K79,J79)*(1-VLOOKUP(A79,Config!$A$3:$B$5,2,FALSE)))) -> 5581.0542 | P79: =IF(D79="ABIERTA",Config!$D$4,VLOOKUP(E79,CCLHistory!$A$6:$B84,2,FALSE)) -> 207,94 | Q79: =O79/P79 -> 26.839734 | R79: =if(B79=0,"...",Q79/N79-1) -> -0.037484332 | S79: =if(B79=0,"...",Q79-N79) -> -1.04525 | T79: =if(B79=0,"...",O79/L79-1) -> -0.041632312 | U79: =if(B79=0,"...",O79-L79) -> -242.44577
A80: IOL | B80: SPOT | C80: 44425 | D80: CERRADA | E80: 44473 | F80: =if(B80=0,"...", IF(E80=0,today()-C80,E80-C80)) -> 48 | G80: PESOS | H80: 5 | I80: 1339.3 | J80: 1512 | K80: =IFERROR(__xludf.DUMMYFUNCTION("if(B80=0,""..."",GOOGLEFINANCE(""BCBA:""&B80))"),30700.0) -> 30700 | L80: =if(B80=0,"...",$H80*I80) -> 6696.5 | M80: =VLOOKUP(C80,CCLHistory!$A$6:$B84,2,FALSE) -> 177,07 | N80: =L80/M80 -> 37.818377 | O80: =if(B80=0,"...",$H80*(IF(D80="ABIERTA",K80,J80)*(1-VLOOKUP(A80,Config!$A$3:$B$5,2,FALSE)))) -> 7559.622 | P80: =IF(D80="ABIERTA",Config!$D$4,VLOOKUP(E80,CCLHistory!$A$6:$B84,2,FALSE)) -> 192,82 | Q80: =O80/P80 -> 39.205591 | R80: =if(B80=0,"...",Q80/N80-1) -> 0.036680945 | S80: =if(B80=0,"...",Q80-N80) -> 1.3872138 | T80: =if(B80=0,"...",O80/L80-1) -> 0.12889151 | U80: =if(B80=0,"...",O80-L80) -> 863.122
A81: IOL | B81: WMT | C81: 44580 | D81: CERRADA | E81: 44603 | F81: =if(B81=0,"...", IF(E81=0,today()-C81,E81-C81)) -> 23 | G81: PESOS | H81: 2 | I81: 5050 | J81: 4930 | K81: =IFERROR(__xludf.DUMMYFUNCTION("if(B81=0,""..."",GOOGLEFINANCE(""BCBA:""&B81))"),9650.0) -> 9650 | L81: =if(B81=0,"...",$H81*I81) -> 10100 | M81: =VLOOKUP(C81,CCLHistory!$A$6:$B84,2,FALSE) -> 214,34 | N81: =L81/M81 -> 47.121396 | O81: =if(B81=0,"...",$H81*(IF(D81="ABIERTA",K81,J81)*(1-VLOOKUP(A81,Config!$A$3:$B$5,2,FALSE)))) -> 9859.507 | P81: =IF(D81="ABIERTA",Config!$D$4,VLOOKUP(E81,CCLHistory!$A$6:$B84,2,FALSE)) -> 215,83 | Q81: =O81/P81 -> 45.681819 | R81: =if(B81=0,"...",Q81/N81-1) -> -0.030550387 | S81: =if(B81=0,"...",Q81-N81) -> -1.4395769 | T81: =if(B81=0,"...",O81/L81-1) -> -0.023811188 | U81: =if(B81=0,"...",O81-L81) -> -240.493
A82: IOL | B82: WMT | C82: 44581 | D82: CERRADA | E82: 44701 | F82: =if(B82=0,"...", IF(E82=0,today()-C82,E82-C82)) -> 120 | G82: PESOS | H82: 5 | I82: 5050 | J82: 4930 | K82: =IFERROR(__xludf.DUMMYFUNCTION("if(B82=0,""..."",GOOGLEFINANCE(""BCBA:""&B82))"),9650.0) -> 9650 | L82: =if(B82=0,"...",$H82*I82) -> 25250 | M82: =VLOOKUP(C82,CCLHistory!$A$6:$B84,2,FALSE) -> 222,3 | N82: =L82/M82 -> 113.58525 | O82: =if(B82=0,"...",$H82*(IF(D82="ABIERTA",K82,J82)*(1-VLOOKUP(A82,Config!$A$3:$B$5,2,FALSE)))) -> 24648.768 | P82: =IF(D82="ABIERTA",Config!$D$4,VLOOKUP(E82,CCLHistory!$A$6:$B84,2,FALSE)) -> 211,22 | Q82: =O82/P82 -> 116.69713 | R82: =if(B82=0,"...",Q82/N82-1) -> 0.027396898 | S82: =if(B82=0,"...",Q82-N82) -> 3.1118834 | T82: =if(B82=0,"...",O82/L82-1) -> -0.023811188 | U82: =if(B82=0,"...",O82-L82) -> -601.2325
A83: IOL | B83: WMT | C83: 44596 | D83: CERRADA | E83: 44701 | F83: =if(B83=0,"...", IF(E83=0,today()-C83,E83-C83)) -> 105 | G83: PESOS | H83: 2 | I83: 5153.5 | J83: 4668 | K83: =IFERROR(__xludf.DUMMYFUNCTION("if(B83=0,""..."",GOOGLEFINANCE(""BCBA:""&B83))"),9650.0) -> 9650 | L83: =if(B83=0,"...",$H83*I83) -> 10307 | M83: =VLOOKUP(C83,CCLHistory!$A$6:$B84,2,FALSE) -> 220,47 | N83: =L83/M83 -> 46.750125 | O83: =if(B83=0,"...",$H83*(IF(D83="ABIERTA",K83,J83)*(1-VLOOKUP(A83,Config!$A$3:$B$5,2,FALSE)))) -> 9335.5332 | P83: =IF(D83="ABIERTA",Config!$D$4,VLOOKUP(E83,CCLHistory!$A$6:$B84,2,FALSE)) -> 211,22 | Q83: =O83/P83 -> 44.19815 | R83: =if(B83=0,"...",Q83/N83-1) -> -0.054587554 | S83: =if(B83=0,"...",Q83-N83) -> -2.5519749 | T83: =if(B83=0,"...",O83/L83-1) -> -0.09425311 | U83: =if(B83=0,"...",O83-L83) -> -971.4668
A84: IOL | B84: WMT | C84: 44645 | D84: CERRADA | E84: 44701 | F84: =if(B84=0,"...", IF(E84=0,today()-C84,E84-C84)) -> 56 | G84: PESOS | H84: 4 | I84: 4770 | J84: 4668 | K84: =IFERROR(__xludf.DUMMYFUNCTION("if(B84=0,""..."",GOOGLEFINANCE(""BCBA:""&B84))"),9650.0) -> 9650 | L84: =if(B84=0,"...",$H84*I84) -> 19080 | M84: =VLOOKUP(C84,CCLHistory!$A$6:$B84,2,FALSE) -> 199,5 | N84: =L84/M84 -> 95.639098 | O84: =if(B84=0,"...",$H84*(IF(D84="ABIERTA",K84,J84)*(1-VLOOKUP(A84,Config!$A$3:$B$5,2,FALSE)))) -> 18671.066 | P84: =IF(D84="ABIERTA",Config!$D$4,VLOOKUP(E84,CCLHistory!$A$6:$B84,2,FALSE)) -> 211,22 | Q84: =O84/P84 -> 88.3963 | R84: =if(B84=0,"...",Q84/N84-1) -> -0.075730515 | S84: =if(B84=0,"...",Q84-N84) -> -7.2427982 | T84: =if(B84=0,"...",O84/L84-1) -> -0.021432579 | U84: =if(B84=0,"...",O84-L84) -> -408.9336

Sheet ONs
B1: 10/30/23 | C1: Apertura | D1: Estado | E1: Cierre | F1: Dias | G1: Moneda | H1: Unidades | I1: Valor Compra | J1: Valor Venta | K1: Valor Actual | L1: Valor Actual USD | M1: Total Compra | N1: MEP Compra | O1: TC USD | P1: Total Venta | Q1: MEP Venta | R1: TV USD | S1: Ganancias (%) | T1: Ganancias Bruta | U1: GAN USD% | V1: GAN USD | X1: Ticker | Y1: Valor Actual | Z1: Unidades | AA1: % Cartera | AB1: PPC | AC1: Total (Abierto) | AD1: Ganancias (%) | AE1: Ganancias Tot | AL1: ONs
A2: IOL | B2: MTCGO | C2: 45126 | D2: ABIERTA | F2: =if(B2=0,"...", IF(E2=0,today()-C2,E2-C2)) -> 870 | G2: PESOS | H2: 362 | I2: 54149.903 | K2: =if(B2=0,"...",VLOOKUP(B2,$X$2:$Y1095,2,false)) -> 153140 | L2: =if(B2=0,"...",K2/IF(G2="DOLARES",1,Q2)) -> 120.92546 | M2: =if(B2=0,"...",$H2*I2/IF(G2="DOLARES",1,100)) -> 196022.65 | N2: =IF($F3=0,Config!$D$3,VLOOKUP(C3,MEPHistory!$A$3:$B1095,2,FALSE)) -> 505,75 | O2: =M2/IF(G2="DOLARES",1,N2) -> 387.58804 | P2: =if(B2=0,"...",$H2*(IF(D2="ABIERTA",K2,J2)*(1-VLOOKUP(A2,Config!$A$3:$B$5,2,FALSE)))/IF(G2="DOLARES",1,100)) -> 554339.08 | Q2: =IF(D2="ABIERTA",Config!$D$3,VLOOKUP(E2,CCLHistory!$A$6:$B1095,2,FALSE)) -> 1266.4 | R2: =P2/IF(G2="DOLARES",1,Q2) -> 437.72827 | S2: =if(B2=0,"...",P2/M2-1) -> 1.8279338 | T2: =if(B2=0,"...",P2-M2) -> 358316.43 | U2: =if(B2=0,"...",R2/O2-1) -> 0.12936476 | V2: =if(B2=0,"...",R2-O2) -> 50.140233 | X2: {=Unique(B2:B1095)} -> MTCGO | Y2: =if(X2=0,"...",VLOOKUP("*"&X2&"*",$AL$2:$AM1095,2,false)) -> 153140 | Z2: =if(X2=0,"...",sumifs($H$2:$H1095,$B$2:$B1095,X2,$D$2:$D1095,"ABIERTA")) -> 362 | AA2: =if(X2=0,"",AC2/$AH$18) -> 0.28537692 | AB2: =if(Z2=0,"...",if(X2=0,"...",sumifs($O$2:$O1095,$B$2:$B1095,X2,$D$2:$D1095,"ABIERTA")/Z2)) -> 1.0706852 | AC2: =if(X2=0,"...",sumifs($R$2:$R1095,$B$2:$B1095,X2,$D$2:$D1095,"ABIERTA")) -> 437.72827 | AD2: =if(Z2=0,"...",if(X2=0,"...",AE2/(AC2-AE2))) -> 0.12936476 | AE2: =if(Z2=0,"...",if(X2=0,"...",sumifs($V$2:$V1095,$B$2:$B1095,X2,$D$2:$D1095,"ABIERTA"))) -> 50.140233 | AL2: =IFERROR(__xludf.DUMMYFUNCTION("QUERY(IMPORTHTML(DataImports!B6,DataImports!D6,1),""select Col1, Col2"",1)"),"Símbolo") -> Símbolo | AM2: =IFERROR(__xludf.DUMMYFUNCTION("""COMPUTED_VALUE"""),"Último Operado") -> Último Operado
A3: IOL | B3: IRCFO | C3: 45134 | D3: ABIERTA | F3: =if(B3=0,"...", IF(E3=0,today()-C3,E3-C3)) -> 862 | G3: PESOS | H3: 363 | I3: 53888.567 | K3: =if(B3=0,"...",VLOOKUP(B3,$X$2:$Y1096,2,false)) -> 103540 | L3: =if(B3=0,"...",K3/IF(G3="DOLARES",1,Q3)) -> 81.759318 | M3: =if(B3=0,"...",$H3*I3/IF(G3="DOLARES",1,100)) -> 195615.5 | N3: =IF($F4=0,Config!$D$3,VLOOKUP(C4,MEPHistory!$A$3:$B1095,2,FALSE)) -> 509,94 | O3: =M3/IF(G3="DOLARES",1,N3) -> 383.60493 | P3: =if(B3=0,"...",$H3*(IF(D3="ABIERTA",K3,J3)*(1-VLOOKUP(A3,Config!$A$3:$B$5,2,FALSE)))/IF(G3="DOLARES",1,100)) -> 375831.41 | Q3: =IF(D3="ABIERTA",Config!$D$3,VLOOKUP(E3,CCLHistory!$A$6:$B1095,2,FALSE)) -> 1266.4 | R3: =P3/IF(G3="DOLARES",1,Q3) -> 296.77148 | S3: =if(B3=0,"...",P3/M3-1) -> 0.92127622 | T3: =if(B3=0,"...",P3-M3) -> 180215.91 | U3: =if(B3=0,"...",R3/O3-1) -> -0.22636166 | V3: =if(B3=0,"...",R3-O3) -> -86.83345 | X3: IRCFO | Y3: =if(X3=0,"...",VLOOKUP("*"&X3&"*",$AL$2:$AM1096,2,false)) -> 103540 | Z3: =if(X3=0,"...",sumifs($H$2:$H1096,$B$2:$B1096,X3,$D$2:$D1096,"ABIERTA")) -> 418 | AA3: =if(X3=0,"",AC3/$AH$18) -> 0.22279533 | AB3: =if(Z3=0,"...",if(X3=0,"...",sumifs($O$2:$O1096,$B$2:$B1096,X3,$D$2:$D1096,"ABIERTA")/Z3)) -> 1.0099004 | AC3: =if(X3=0,"...",sumifs($R$2:$R1096,$B$2:$B1096,X3,$D$2:$D1096,"ABIERTA")) -> 341.73686 | AD3: =if(Z3=0,"...",if(X3=0,"...",AE3/(AC3-AE3))) -> -0.19046246 | AE3: =if(Z3=0,"...",if(X3=0,"...",sumifs($V$2:$V1096,$B$2:$B1096,X3,$D$2:$D1096,"ABIERTA"))) -> -80.401515 | AL3: =IFERROR(__xludf.DUMMYFUNCTION("""COMPUTED_VALUE"""),"* AER1O *") -> * AER1O * | AM3: =IFERROR(__xludf.DUMMYFUNCTION("""COMPUTED_VALUE"""),15390.4) -> 15390.4
A4: IOL | B4: YMCIO | C4: 45135 | D4: ABIERTA | F4: =if(B4=0,"...", IF(E4=0,today()-C4,E4-C4)) -> 861 | G4: PESOS | H4: 375 | I4: 53229 | K4: =if(B4=0,"...",VLOOKUP(B4,$X$2:$Y1097,2,false)) -> 161330 | L4: =if(B4=0,"...",K4/IF(G4="DOLARES",1,Q4)) -> 127.39261 | M4: =if(B4=0,"...",$H4*I4/IF(G4="DOLARES",1,100)) -> 199608.75 | N4: =IF($F5=0,Config!$D$3,VLOOKUP(C5,MEPHistory!$A$3:$B1095,2,FALSE)) -> 899,33 | O4: =M4/IF(G4="DOLARES",1,N4) -> 221.95273 | P4: =if(B4=0,"...",$H4*(IF(D4="ABIERTA",K4,J4)*(1-VLOOKUP(A4,Config!$A$3:$B$5,2,FALSE)))/IF(G4="DOLARES",1,100)) -> 604957.25 | Q4: =IF(D4="ABIERTA",Config!$D$3,VLOOKUP(E4,CCLHistory!$A$6:$B1095,2,FALSE)) -> 1266.4 | R4: =P4/IF(G4="DOLARES",1,Q4) -> 477.6984 | S4: =if(B4=0,"...",P4/M4-1) -> 2.0307151 | T4: =if(B4=0,"...",P4-M4) -> 405348.5 | U4: =if(B4=0,"...",R4/O4-1) -> 1.1522528 | V4: =if(B4=0,"...",R4-O4) -> 255.74567 | X4: YMCIO | Y4: =if(X4=0,"...",VLOOKUP("*"&X4&"*",$AL$2:$AM1097,2,false)) -> 161330 | Z4: =if(X4=0,"...",sumifs($H$2:$H1097,$B$2:$B1097,X4,$D$2:$D1097,"ABIERTA")) -> 505 | AA4: =if(X4=0,"",AC4/$AH$18) -> 0.41939973 | AB4: =if(Z4=0,"...",if(X4=0,"...",sumifs($O$2:$O1097,$B$2:$B1097,X4,$D$2:$D1097,"ABIERTA")/Z4)) -> 0.6777955 | AC4: =if(X4=0,"...",sumifs($R$2:$R1097,$B$2:$B1097,X4,$D$2:$D1097,"ABIERTA")) -> 643.30051 | AD4: =if(Z4=0,"...",if(X4=0,"...",AE4/(AC4-AE4))) -> 0.87941995 | AE4: =if(Z4=0,"...",if(X4=0,"...",sumifs($V$2:$V1097,$B$2:$B1097,X4,$D$2:$D1097,"ABIERTA"))) -> 301.01378 | AL4: =IFERROR(__xludf.DUMMYFUNCTION("""COMPUTED_VALUE"""),"* AER9O *") -> * AER9O * | AM4: =IFERROR(__xludf.DUMMYFUNCTION("""COMPUTED_VALUE"""),150000.0) -> 150000
A5: IOL | B5: YMCID | C5: 45222 | D5: ABIERTA | F5: =if(B5=0,"...", IF(E5=0,today()-C5,E5-C5)) -> 774 | G5: DOLARES | H5: 1 | I5: 97.9 | K5: =if(B5=0,"...",VLOOKUP(B5,$X$2:$Y1098,2,false)) -> 111.1 | L5: =if(B5=0,"...",K5/IF(G5="DOLARES",1,Q5)) -> 111.1 | M5: =if(B5=0,"...",$H5*I5/IF(G5="DOLARES",1,100)) -> 97.9 | N5: =IF($F6=0,Config!$D$3,VLOOKUP(C6,MEPHistory!$A$3:$B1095,2,FALSE)) -> 857,14 | O5: =M5/IF(G5="DOLARES",1,N5) -> 97.9 | P5: =if(B5=0,"...",$H5*(IF(D5="ABIERTA",K5,J5)*(1-VLOOKUP(A5,Config!$A$3:$B$5,2,FALSE)))/IF(G5="DOLARES",1,100)) -> 111.09444 | Q5: =IF(D5="ABIERTA",Config!$D$3,VLOOKUP(E5,CCLHistory!$A$6:$B1095,2,FALSE)) -> 1266.4 | R5: =P5/IF(G5="DOLARES",1,Q5) -> 111.09444 | S5: =if(B5=0,"...",P5/M5-1) -> 0.13477472 | T5: =if(B5=0,"...",P5-M5) -> 13.194445 | U5: =if(B5=0,"...",R5/O5-1) -> 0.13477472 | V5: =if(B5=0,"...",R5-O5) -> 13.194445 | X5: YMCID | Y5: =if(X5=0,"...",VLOOKUP("*"&X5&"*",$AL$2:$AM1098,2,false)) -> 111.1 | Z5: =if(X5=0,"...",sumifs($H$2:$H1098,$B$2:$B1098,X5,$D$2:$D1098,"ABIERTA")) -> 1 | AA5: =if(X5=0,"",AC5/$AH$18) -> 0.072428017 | AB5: =if(Z5=0,"...",if(X5=0,"...",sumifs($O$2:$O1098,$B$2:$B1098,X5,$D$2:$D1098,"ABIERTA")/Z5)) -> 97.9 | AC5: =if(X5=0,"...",sumifs($R$2:$R1098,$B$2:$B1098,X5,$D$2:$D1098,"ABIERTA")) -> 111.09444 | AD5: =if(Z5=0,"...",if(X5=0,"...",AE5/(AC5-AE5))) -> 0.13477472 | AE5: =if(Z5=0,"...",if(X5=0,"...",sumifs($V$2:$V1098,$B$2:$B1098,X5,$D$2:$D1098,"ABIERTA"))) -> 13.194445 | AL5: =IFERROR(__xludf.DUMMYFUNCTION("""COMPUTED_VALUE"""),"* AERBD *") -> * AERBD * | AM5: =IFERROR(__xludf.DUMMYFUNCTION("""COMPUTED_VALUE"""),102.0) -> 102
A6: IOL | B6: YMCIO | C6: 45246 | D6: ABIERTA | F6: =if(B6=0,"...", IF(E6=0,today()-C6,E6-C6)) -> 750 | G6: PESOS | H6: 71 | I6: 82500 | K6: =if(B6=0,"...",VLOOKUP(B6,$X$2:$Y1099,2,false)) -> 161330 | L6: =if(B6=0,"...",K6/IF(G6="DOLARES",1,Q6)) -> 127.39261 | M6: =if(B6=0,"...",$H6*I6/IF(G6="DOLARES",1,100)) -> 58575 | N6: =IF($F7=0,Config!$D$3,VLOOKUP(C6,MEPHistory!$A$3:$B1095,2,FALSE)) -> 857,14 | O6: =M6/IF(G6="DOLARES",1,N6) -> 68.337728 | P6: =if(B6=0,"...",$H6*(IF(D6="ABIERTA",K6,J6)*(1-VLOOKUP(A6,Config!$A$3:$B$5,2,FALSE)))/IF(G6="DOLARES",1,100)) -> 114538.57 | Q6: =IF(D6="ABIERTA",Config!$D$3,VLOOKUP(E6,CCLHistory!$A$6:$B1095,2,FALSE)) -> 1266.4 | R6: =P6/IF(G6="DOLARES",1,Q6) -> 90.44423 | S6: =if(B6=0,"...",P6/M6-1) -> 0.95541738 | T6: =if(B6=0,"...",P6-M6) -> 55963.573 | U6: =if(B6=0,"...",R6/O6-1) -> 0.32348898 | V6: =if(B6=0,"...",R6-O6) -> 22.106502 | Y6: =if(X6=0,"...",VLOOKUP("*"&X6&"*",$AL$2:$AM1099,2,false)) -> ... | Z6: =if(X6=0,"...",sumifs($H$2:$H1099,$B$2:$B1099,X6,$D$2:$D1099,"ABIERTA")) -> ... | AA6: =if(X6=0,"",AC6/$AH$18) | AB6: =if(Z6=0,"...",if(X6=0,"...",sumifs($O$2:$O1099,$B$2:$B1099,X6,$D$2:$D1099,"ABIERTA")/Z6)) -> ... | AC6: =if(X6=0,"...",sumifs($R$2:$R1099,$B$2:$B1099,X6,$D$2:$D1099,"ABIERTA")) -> ... | AD6: =if(Z6=0,"...",if(X6=0,"...",AE6/(AC6-AE6))) -> ... | AE6: =if(Z6=0,"...",if(X6=0,"...",sumifs($V$2:$V1099,$B$2:$B1099,X6,$D$2:$D1099,"ABIERTA"))) -> ... | AL6: =IFERROR(__xludf.DUMMYFUNCTION("""COMPUTED_VALUE"""),"* AERBO *") -> * AERBO * | AM6: =IFERROR(__xludf.DUMMYFUNCTION("""COMPUTED_VALUE"""),151990.0) -> 151990
A7: IOL | B7: YMCIO | C7: 45251 | D7: ABIERTA | F7: =if(B7=0,"...", IF(E7=0,today()-C7,E7-C7)) -> 745 | G7: PESOS | H7: 59 | I7: 81999 | K7: =if(B7=0,"...",VLOOKUP(B7,$X$2:$Y1100,2,false)) -> 161330 | L7: =if(B7=0,"...",K7/IF(G7="DOLARES",1,Q7)) -> 127.39261 | M7: =if(B7=0,"...",$H7*I7/IF(G7="DOLARES",1,100)) -> 48379.41 | N7: =IF($F8=0,Config!$D$3,VLOOKUP(C7,MEPHistory!$A$3:$B1095,2,FALSE)) -> 930,44 | O7: =M7/IF(G7="DOLARES",1,N7) -> 51.996271 | P7: =if(B7=0,"...",$H7*(IF(D7="ABIERTA",K7,J7)*(1-VLOOKUP(A7,Config!$A$3:$B$5,2,FALSE)))/IF(G7="DOLARES",1,100)) -> 95179.941 | Q7: =IF(D7="ABIERTA",Config!$D$3,VLOOKUP(E7,CCLHistory!$A$6:$B1095,2,FALSE)) -> 1266.4 | R7: =P7/IF(G7="DOLARES",1,Q7) -> 75.157881 | S7: =if(B7=0,"...",P7/M7-1) -> 0.96736464 | T7: =if(B7=0,"...",P7-M7) -> 46800.531 | U7: =if(B7=0,"...",R7/O7-1) -> 0.44544754 | V7: =if(B7=0,"...",R7-O7) -> 23.161611 | Y7: =if(X7=0,"...",VLOOKUP("*"&X7&"*",$AL$2:$AM1100,2,false)) -> ... | Z7: =if(X7=0,"...",sumifs($H$2:$H1100,$B$2:$B1100,X7,$D$2:$D1100,"ABIERTA")) -> ... | AA7: =if(X7=0,"",AC7/$AH$18) | AB7: =if(Z7=0,"...",if(X7=0,"...",sumifs($O$2:$O1100,$B$2:$B1100,X7,$D$2:$D1100,"ABIERTA")/Z7)) -> ... | AC7: =if(X7=0,"...",sumifs($R$2:$R1100,$B$2:$B1100,X7,$D$2:$D1100,"ABIERTA")) -> ... | AD7: =if(Z7=0,"...",if(X7=0,"...",AE7/(AC7-AE7))) -> ... | AE7: =if(Z7=0,"...",if(X7=0,"...",sumifs($V$2:$V1100,$B$2:$B1100,X7,$D$2:$D1100,"ABIERTA"))) -> ... | AL7: =IFERROR(__xludf.DUMMYFUNCTION("""COMPUTED_VALUE"""),"* AFCID *") -> * AFCID * | AM7: =IFERROR(__xludf.DUMMYFUNCTION("""COMPUTED_VALUE"""),100.15) -> 100.15
A8: IOL | B8: IRCFO | C8: 45251 | D8: ABIERTA | F8: =if(B8=0,"...", IF(E8=0,today()-C8,E8-C8)) -> 745 | G8: PESOS | H8: 55 | I8: 88725 | K8: =if(B8=0,"...",VLOOKUP(B8,$X$2:$Y1101,2,false)) -> 103540 | L8: =if(B8=0,"...",K8/IF(G8="DOLARES",1,Q8)) -> 81.759318 | M8: =if(B8=0,"...",$H8*I8/IF(G8="DOLARES",1,100)) -> 48798.75 | N8: =IF($F9=0,Config!$D$3,VLOOKUP(C8,MEPHistory!$A$3:$B1095,2,FALSE)) -> 1266.4 | O8: =M8/IF(G8="DOLARES",1,N8) -> 38.533441 | P8: =if(B8=0,"...",$H8*(IF(D8="ABIERTA",K8,J8)*(1-VLOOKUP(A8,Config!$A$3:$B$5,2,FALSE)))/IF(G8="DOLARES",1,100)) -> 56944.153 | Q8: =IF(D8="ABIERTA",Config!$D$3,VLOOKUP(E8,CCLHistory!$A$6:$B1095,2,FALSE)) -> 1266.4 | R8: =P8/IF(G8="DOLARES",1,Q8) -> 44.965376 | S8: =if(B8=0,"...",P8/M8-1) -> 0.16691826 | T8: =if(B8=0,"...",P8-M8) -> 8145.4026 | U8: =if(B8=0,"...",R8/O8-1) -> 0.16691826 | V8: =if(B8=0,"...",R8-O8) -> 6.4319351 | Y8: =if(X8=0,"...",VLOOKUP("*"&X8&"*",$AL$2:$AM1101,2,false)) -> ... | Z8: =if(X8=0,"...",sumifs($H$2:$H1101,$B$2:$B1101,X8,$D$2:$D1101,"ABIERTA")) -> ... | AA8: =if(X8=0,"",AC8/$AH$18) | AB8: =if(Z8=0,"...",if(X8=0,"...",sumifs($O$2:$O1101,$B$2:$B1101,X8,$D$2:$D1101,"ABIERTA")/Z8)) -> ... | AC8: =if(X8=0,"...",sumifs($R$2:$R1101,$B$2:$B1101,X8,$D$2:$D1101,"ABIERTA")) -> ... | AD8: =if(Z8=0,"...",if(X8=0,"...",AE8/(AC8-AE8))) -> ... | AE8: =if(Z8=0,"...",if(X8=0,"...",sumifs($V$2:$V1101,$B$2:$B1101,X8,$D$2:$D1101,"ABIERTA"))) -> ... | AL8: =IFERROR(__xludf.DUMMYFUNCTION("""COMPUTED_VALUE"""),"* AFCIO *") -> * AFCIO * | AM8: =IFERROR(__xludf.DUMMYFUNCTION("""COMPUTED_VALUE"""),147000.0) -> 147000
K9: =if(B9=0,"...",VLOOKUP(B9,$X$2:$Y1102,2,false)) -> ... | L9: =if(B9=0,"...",K9/IF(G9="DOLARES",1,Q9)) -> ... | P9: =if(B9=0,"...",$H9*(IF(D9="ABIERTA",K9,J9)*(1-VLOOKUP(A9,Config!$A$3:$B$5,2,FALSE)))/100) -> ... | S9: =if(B9=0,"...",P9/M9-1) -> ... | T9: =if(B9=0,"...",P9-M9) -> ... | U9: =if(B9=0,"...",R9/O9-1) -> ... | V9: =if(B9=0,"...",R9-O9) -> ... | Y9: =if(X9=0,"...",VLOOKUP("*"&X9&"*",$AL$2:$AM1102,2,false)) -> ... | Z9: =if(X9=0,"...",sumifs($H$2:$H1102,$B$2:$B1102,X9,$D$2:$D1102,"ABIERTA")) -> ... | AA9: =if(X9=0,"",AC9/$AH$18) | AB9: =if(Z9=0,"...",if(X9=0,"...",sumifs($O$2:$O1102,$B$2:$B1102,X9,$D$2:$D1102,"ABIERTA")/Z9)) -> ... | AC9: =if(X9=0,"...",sumifs($R$2:$R1102,$B$2:$B1102,X9,$D$2:$D1102,"ABIERTA")) -> ... | AD9: =if(Z9=0,"...",if(X9=0,"...",AE9/(AC9-AE9))) -> ... | AE9: =if(Z9=0,"...",if(X9=0,"...",sumifs($V$2:$V1102,$B$2:$B1102,X9,$D$2:$D1102,"ABIERTA"))) -> ... | AL9: =IFERROR(__xludf.DUMMYFUNCTION("""COMPUTED_VALUE"""),"* ARC1C *") -> * ARC1C * | AM9: =IFERROR(__xludf.DUMMYFUNCTION("""COMPUTED_VALUE"""),106.0) -> 106
K10: =if(B10=0,"...",VLOOKUP(B10,$X$2:$Y1103,2,false)) -> ... | L10: =if(B10=0,"...",K10/IF(G10="DOLARES",1,Q10)) -> ... | P10: =if(B10=0,"...",$H10*(IF(D10="ABIERTA",K10,J10)*(1-VLOOKUP(A10,Config!$A$3:$B$5,2,FALSE)))/100) -> ... | S10: =if(B10=0,"...",P10/M10-1) -> ... | T10: =if(B10=0,"...",P10-M10) -> ... | U10: =if(B10=0,"...",R10/O10-1) -> ... | V10: =if(B10=0,"...",R10-O10) -> ... | Y10: =if(X10=0,"...",VLOOKUP("*"&X10&"*",$AL$2:$AM1103,2,false)) -> ... | Z10: =if(X10=0,"...",sumifs($H$2:$H1103,$B$2:$B1103,X10,$D$2:$D1103,"ABIERTA")) -> ... | AA10: =if(X10=0,"",AC10/$AH$18) | AB10: =if(Z10=0,"...",if(X10=0,"...",sumifs($O$2:$O1103,$B$2:$B1103,X10,$D$2:$D1103,"ABIERTA")/Z10)) -> ... | AC10: =if(X10=0,"...",sumifs($R$2:$R1103,$B$2:$B1103,X10,$D$2:$D1103,"ABIERTA")) -> ... | AD10: =if(Z10=0,"...",if(X10=0,"...",AE10/(AC10-AE10))) -> ... | AE10: =if(Z10=0,"...",if(X10=0,"...",sumifs($V$2:$V1103,$B$2:$B1103,X10,$D$2:$D1103,"ABIERTA"))) -> ... | AL10: =IFERROR(__xludf.DUMMYFUNCTION("""COMPUTED_VALUE"""),"* ARC1D *") -> * ARC1D * | AM10: =IFERROR(__xludf.DUMMYFUNCTION("""COMPUTED_VALUE"""),106.9) -> 106.9
K11: =if(B11=0,"...",VLOOKUP(B11,$X$2:$Y1104,2,false)) -> ... | L11: =if(B11=0,"...",K11/IF(G11="DOLARES",1,Q11)) -> ... | P11: =if(B11=0,"...",$H11*(IF(D11="ABIERTA",K11,J11)*(1-VLOOKUP(A11,Config!$A$3:$B$5,2,FALSE)))/100) -> ... | S11: =if(B11=0,"...",P11/M11-1) -> ... | T11: =if(B11=0,"...",P11-M11) -> ... | U11: =if(B11=0,"...",R11/O11-1) -> ... | V11: =if(B11=0,"...",R11-O11) -> ... | Y11: =if(X11=0,"...",VLOOKUP("*"&X11&"*",$AL$2:$AM1104,2,false)) -> ... | Z11: =if(X11=0,"...",sumifs($H$2:$H1104,$B$2:$B1104,X11,$D$2:$D1104,"ABIERTA")) -> ... | AA11: =if(X11=0,"",AC11/$AH$18) | AB11: =if(Z11=0,"...",if(X11=0,"...",sumifs($O$2:$O1104,$B$2:$B1104,X11,$D$2:$D1104,"ABIERTA")/Z11)) -> ... | AC11: =if(X11=0,"...",sumifs($R$2:$R1104,$B$2:$B1104,X11,$D$2:$D1104,"ABIERTA")) -> ... | AD11: =if(Z11=0,"...",if(X11=0,"...",AE11/(AC11-AE11))) -> ... | AE11: =if(Z11=0,"...",if(X11=0,"...",sumifs($V$2:$V1104,$B$2:$B1104,X11,$D$2:$D1104,"ABIERTA"))) -> ... | AL11: =IFERROR(__xludf.DUMMYFUNCTION("""COMPUTED_VALUE"""),"* ARC1O *") -> * ARC1O * | AM11: =IFERROR(__xludf.DUMMYFUNCTION("""COMPUTED_VALUE"""),155840.0) -> 155840
K12: =if(B12=0,"...",VLOOKUP(B12,$X$2:$Y1105,2,false)) -> ... | L12: =if(B12=0,"...",K12/IF(G12="DOLARES",1,Q12)) -> ... | P12: =if(B12=0,"...",$H12*(IF(D12="ABIERTA",K12,J12)*(1-VLOOKUP(A12,Config!$A$3:$B$5,2,FALSE)))/100) -> ... | S12: =if(B12=0,"...",P12/M12-1) -> ... | T12: =if(B12=0,"...",P12-M12) -> ... | U12: =if(B12=0,"...",R12/O12-1) -> ... | V12: =if(B12=0,"...",R12-O12) -> ... | Y12: =if(X12=0,"...",VLOOKUP("*"&X12&"*",$AL$2:$AM1105,2,false)) -> ... | Z12: =if(X12=0,"...",sumifs($H$2:$H1105,$B$2:$B1105,X12,$D$2:$D1105,"ABIERTA")) -> ... | AA12: =if(X12=0,"",AC12/$AH$18) | AB12: =if(Z12=0,"...",if(X12=0,"...",sumifs($O$2:$O1105,$B$2:$B1105,X12,$D$2:$D1105,"ABIERTA")/Z12)) -> ... | AC12: =if(X12=0,"...",sumifs($R$2:$R1105,$B$2:$B1105,X12,$D$2:$D1105,"ABIERTA")) -> ... | AD12: =if(Z12=0,"...",if(X12=0,"...",AE12/(AC12-AE12))) -> ... | AE12: =if(Z12=0,"...",if(X12=0,"...",sumifs($V$2:$V1105,$B$2:$B1105,X12,$D$2:$D1105,"ABIERTA"))) -> ... | AL12: =IFERROR(__xludf.DUMMYFUNCTION("""COMPUTED_VALUE"""),"* BACAD *") -> * BACAD * | AM12: =IFERROR(__xludf.DUMMYFUNCTION("""COMPUTED_VALUE"""),101.4) -> 101.4
K13: =if(B13=0,"...",VLOOKUP(B13,$X$2:$Y1106,2,false)) -> ... | L13: =if(B13=0,"...",K13/IF(G13="DOLARES",1,Q13)) -> ... | P13: =if(B13=0,"...",$H13*(IF(D13="ABIERTA",K13,J13)*(1-VLOOKUP(A13,Config!$A$3:$B$5,2,FALSE)))/100) -> ... | S13: =if(B13=0,"...",P13/M13-1) -> ... | T13: =if(B13=0,"...",P13-M13) -> ... | U13: =if(B13=0,"...",R13/O13-1) -> ... | V13: =if(B13=0,"...",R13-O13) -> ... | Y13: =if(X13=0,"...",VLOOKUP("*"&X13&"*",$AL$2:$AM1106,2,false)) -> ... | Z13: =if(X13=0,"...",sumifs($H$2:$H1106,$B$2:$B1106,X13,$D$2:$D1106,"ABIERTA")) -> ... | AA13: =if(X13=0,"",AC13/$AH$18) | AB13: =if(Z13=0,"...",if(X13=0,"...",sumifs($O$2:$O1106,$B$2:$B1106,X13,$D$2:$D1106,"ABIERTA")/Z13)) -> ... | AC13: =if(X13=0,"...",sumifs($R$2:$R1106,$B$2:$B1106,X13,$D$2:$D1106,"ABIERTA")) -> ... | AD13: =if(Z13=0,"...",if(X13=0,"...",AE13/(AC13-AE13))) -> ... | AE13: =if(Z13=0,"...",if(X13=0,"...",sumifs($V$2:$V1106,$B$2:$B1106,X13,$D$2:$D1106,"ABIERTA"))) -> ... | AL13: =IFERROR(__xludf.DUMMYFUNCTION("""COMPUTED_VALUE"""),"* BACAO *") -> * BACAO * | AM13: =IFERROR(__xludf.DUMMYFUNCTION("""COMPUTED_VALUE"""),147630.0) -> 147630
K14: =if(B14=0,"...",VLOOKUP(B14,$X$2:$Y1107,2,false)) -> ... | L14: =if(B14=0,"...",K14/IF(G14="DOLARES",1,Q14)) -> ... | P14: =if(B14=0,"...",$H14*(IF(D14="ABIERTA",K14,J14)*(1-VLOOKUP(A14,Config!$A$3:$B$5,2,FALSE)))/100) -> ... | S14: =if(B14=0,"...",P14/M14-1) -> ... | T14: =if(B14=0,"...",P14-M14) -> ... | U14: =if(B14=0,"...",R14/O14-1) -> ... | V14: =if(B14=0,"...",R14-O14) -> ... | Y14: =if(X14=0,"...",VLOOKUP("*"&X14&"*",$AL$2:$AM1107,2,false)) -> ... | Z14: =if(X14=0,"...",sumifs($H$2:$H1107,$B$2:$B1107,X14,$D$2:$D1107,"ABIERTA")) -> ... | AA14: =if(X14=0,"",AC14/$AH$18) | AB14: =if(Z14=0,"...",if(X14=0,"...",sumifs($O$2:$O1107,$B$2:$B1107,X14,$D$2:$D1107,"ABIERTA")/Z14)) -> ... | AC14: =if(X14=0,"...",sumifs($R$2:$R1107,$B$2:$B1107,X14,$D$2:$D1107,"ABIERTA")) -> ... | AD14: =if(Z14=0,"...",if(X14=0,"...",AE14/(AC14-AE14))) -> ... | AE14: =if(Z14=0,"...",if(X14=0,"...",sumifs($V$2:$V1107,$B$2:$B1107,X14,$D$2:$D1107,"ABIERTA"))) -> ... | AL14: =IFERROR(__xludf.DUMMYFUNCTION("""COMPUTED_VALUE"""),"* BACGD *") -> * BACGD * | AM14: =IFERROR(__xludf.DUMMYFUNCTION("""COMPUTED_VALUE"""),106.6) -> 106.6
K15: =if(B15=0,"...",VLOOKUP(B15,$X$2:$Y1108,2,false)) -> ... | L15: =if(B15=0,"...",K15/IF(G15="DOLARES",1,Q15)) -> ... | P15: =if(B15=0,"...",$H15*(IF(D15="ABIERTA",K15,J15)*(1-VLOOKUP(A15,Config!$A$3:$B$5,2,FALSE)))/100) -> ... | S15: =if(B15=0,"...",P15/M15-1) -> ... | T15: =if(B15=0,"...",P15-M15) -> ... | U15: =if(B15=0,"...",R15/O15-1) -> ... | V15: =if(B15=0,"...",R15-O15) -> ... | Y15: =if(X15=0,"...",VLOOKUP("*"&X15&"*",$AL$2:$AM1108,2,false)) -> ... | Z15: =if(X15=0,"...",sumifs($H$2:$H1108,$B$2:$B1108,X15,$D$2:$D1108,"ABIERTA")) -> ... | AA15: =if(X15=0,"",AC15/$AH$18) | AB15: =if(Z15=0,"...",if(X15=0,"...",sumifs($O$2:$O1108,$B$2:$B1108,X15,$D$2:$D1108,"ABIERTA")/Z15)) -> ... | AC15: =if(X15=0,"...",sumifs($R$2:$R1108,$B$2:$B1108,X15,$D$2:$D1108,"ABIERTA")) -> ... | AD15: =if(Z15=0,"...",if(X15=0,"...",AE15/(AC15-AE15))) -> ... | AE15: =if(Z15=0,"...",if(X15=0,"...",sumifs($V$2:$V1108,$B$2:$B1108,X15,$D$2:$D1108,"ABIERTA"))) -> ... | AL15: =IFERROR(__xludf.DUMMYFUNCTION("""COMPUTED_VALUE"""),"* BACGO *") -> * BACGO * | AM15: =IFERROR(__xludf.DUMMYFUNCTION("""COMPUTED_VALUE"""),155560.0) -> 155560
K16: =if(B16=0,"...",VLOOKUP(B16,$X$2:$Y1109,2,false)) -> ... | L16: =if(B16=0,"...",K16/IF(G16="DOLARES",1,Q16)) -> ... | P16: =if(B16=0,"...",$H16*(IF(D16="ABIERTA",K16,J16)*(1-VLOOKUP(A16,Config!$A$3:$B$5,2,FALSE)))/100) -> ... | S16: =if(B16=0,"...",P16/M16-1) -> ... | T16: =if(B16=0,"...",P16-M16) -> ... | U16: =if(B16=0,"...",R16/O16-1) -> ... | V16: =if(B16=0,"...",R16-O16) -> ... | Y16: =if(X16=0,"...",VLOOKUP("*"&X16&"*",$AL$2:$AM1109,2,false)) -> ... | Z16: =if(X16=0,"...",sumifs($H$2:$H1109,$B$2:$B1109,X16,$D$2:$D1109,"ABIERTA")) -> ... | AA16: =if(X16=0,"",AC16/$AH$18) | AB16: =if(Z16=0,"...",if(X16=0,"...",sumifs($O$2:$O1109,$B$2:$B1109,X16,$D$2:$D1109,"ABIERTA")/Z16)) -> ... | AC16: =if(X16=0,"...",sumifs($R$2:$R1109,$B$2:$B1109,X16,$D$2:$D1109,"ABIERTA")) -> ... | AD16: =if(Z16=0,"...",if(X16=0,"...",AE16/(AC16-AE16))) -> ... | AE16: =if(Z16=0,"...",if(X16=0,"...",sumifs($V$2:$V1109,$B$2:$B1109,X16,$D$2:$D1109,"ABIERTA"))) -> ... | AL16: =IFERROR(__xludf.DUMMYFUNCTION("""COMPUTED_VALUE"""),"* BF35D *") -> * BF35D * | AM16: =IFERROR(__xludf.DUMMYFUNCTION("""COMPUTED_VALUE"""),98.95) -> 98.95
K17: =if(B17=0,"...",VLOOKUP(B17,$X$2:$Y1110,2,false)) -> ... | L17: =if(B17=0,"...",K17/IF(G17="DOLARES",1,Q17)) -> ... | P17: =if(B17=0,"...",$H17*(IF(D17="ABIERTA",K17,J17)*(1-VLOOKUP(A17,Config!$A$3:$B$5,2,FALSE)))/100) -> ... | S17: =if(B17=0,"...",P17/M17-1) -> ... | T17: =if(B17=0,"...",P17-M17) -> ... | U17: =if(B17=0,"...",R17/O17-1) -> ... | V17: =if(B17=0,"...",R17-O17) -> ... | Y17: =if(X17=0,"...",VLOOKUP("*"&X17&"*",$AL$2:$AM1110,2,false)) -> ... | Z17: =if(X17=0,"...",sumifs($H$2:$H1110,$B$2:$B1110,X17,$D$2:$D1110,"ABIERTA")) -> ... | AA17: =if(X17=0,"",AC17/$AH$18) | AB17: =if(Z17=0,"...",if(X17=0,"...",sumifs($O$2:$O1110,$B$2:$B1110,X17,$D$2:$D1110,"ABIERTA")/Z17)) -> ... | AC17: =if(X17=0,"...",sumifs($R$2:$R1110,$B$2:$B1110,X17,$D$2:$D1110,"ABIERTA")) -> ... | AD17: =if(Z17=0,"...",if(X17=0,"...",AE17/(AC17-AE17))) -> ... | AE17: =if(Z17=0,"...",if(X17=0,"...",sumifs($V$2:$V1110,$B$2:$B1110,X17,$D$2:$D1110,"ABIERTA"))) -> ... | AL17: =IFERROR(__xludf.DUMMYFUNCTION("""COMPUTED_VALUE"""),"* BF35O *") -> * BF35O * | AM17: =IFERROR(__xludf.DUMMYFUNCTION("""COMPUTED_VALUE"""),146000.0) -> 146000
K18: =if(B18=0,"...",VLOOKUP(B18,$X$2:$Y1111,2,false)) -> ... | L18: =if(B18=0,"...",K18/IF(G18="DOLARES",1,Q18)) -> ... | P18: =if(B18=0,"...",$H18*(IF(D18="ABIERTA",K18,J18)*(1-VLOOKUP(A18,Config!$A$3:$B$5,2,FALSE)))/100) -> ... | S18: =if(B18=0,"...",P18/M18-1) -> ... | T18: =if(B18=0,"...",P18-M18) -> ... | U18: =if(B18=0,"...",R18/O18-1) -> ... | V18: =if(B18=0,"...",R18-O18) -> ... | Y18: =if(X18=0,"...",VLOOKUP("*"&X18&"*",$AL$2:$AM1111,2,false)) -> ... | Z18: =if(X18=0,"...",sumifs($H$2:$H1111,$B$2:$B1111,X18,$D$2:$D1111,"ABIERTA")) -> ... | AA18: =if(X18=0,"",AC18/$AH$18) | AB18: =if(Z18=0,"...",if(X18=0,"...",sumifs($O$2:$O1111,$B$2:$B1111,X18,$D$2:$D1111,"ABIERTA")/Z18)) -> ... | AC18: =if(X18=0,"...",sumifs($R$2:$R1111,$B$2:$B1111,X18,$D$2:$D1111,"ABIERTA")) -> ... | AD18: =if(Z18=0,"...",if(X18=0,"...",AE18/(AC18-AE18))) -> ... | AE18: =if(Z18=0,"...",if(X18=0,"...",sumifs($V$2:$V1111,$B$2:$B1111,X18,$D$2:$D1111,"ABIERTA"))) -> ... | AG18: Total Abierto | AH18: =sumifs(R2:R1095,D2:D1095,"ABIERTA") -> 1533.8601 | AI18: Total Acumulado | AJ18: =sum(R2:R1095) -> 1533.8601 | AL18: =IFERROR(__xludf.DUMMYFUNCTION("""COMPUTED_VALUE"""),"* BF37C *") -> * BF37C * | AM18: =IFERROR(__xludf.DUMMYFUNCTION("""COMPUTED_VALUE"""),102.0) -> 102
K19: =if(B19=0,"...",VLOOKUP(B19,$X$2:$Y1112,2,false)) -> ... | L19: =if(B19=0,"...",K19/IF(G19="DOLARES",1,Q19)) -> ... | P19: =if(B19=0,"...",$H19*(IF(D19="ABIERTA",K19,J19)*(1-VLOOKUP(A19,Config!$A$3:$B$5,2,FALSE)))/100) -> ... | S19: =if(B19=0,"...",P19/M19-1) -> ... | T19: =if(B19=0,"...",P19-M19) -> ... | U19: =if(B19=0,"...",R19/O19-1) -> ... | V19: =if(B19=0,"...",R19-O19) -> ... | Y19: =if(X19=0,"...",VLOOKUP("*"&X19&"*",$AL$2:$AM1112,2,false)) -> ... | Z19: =if(X19=0,"...",sumifs($H$2:$H1112,$B$2:$B1112,X19,$D$2:$D1112,"ABIERTA")) -> ... | AA19: =if(X19=0,"",AC19/$AH$18) | AB19: =if(Z19=0,"...",if(X19=0,"...",sumifs($O$2:$O1112,$B$2:$B1112,X19,$D$2:$D1112,"ABIERTA")/Z19)) -> ... | AC19: =if(X19=0,"...",sumifs($R$2:$R1112,$B$2:$B1112,X19,$D$2:$D1112,"ABIERTA")) -> ... | AD19: =if(Z19=0,"...",if(X19=0,"...",AE19/(AC19-AE19))) -> ... | AE19: =if(Z19=0,"...",if(X19=0,"...",sumifs($V$2:$V1112,$B$2:$B1112,X19,$D$2:$D1112,"ABIERTA"))) -> ... | AL19: =IFERROR(__xludf.DUMMYFUNCTION("""COMPUTED_VALUE"""),"* BF37D *") -> * BF37D * | AM19: =IFERROR(__xludf.DUMMYFUNCTION("""COMPUTED_VALUE"""),100.45) -> 100.45
K20: =if(B20=0,"...",VLOOKUP(B20,$X$2:$Y1113,2,false)) -> ... | L20: =if(B20=0,"...",K20/IF(G20="DOLARES",1,Q20)) -> ... | P20: =if(B20=0,"...",$H20*(IF(D20="ABIERTA",K20,J20)*(1-VLOOKUP(A20,Config!$A$3:$B$5,2,FALSE)))/100) -> ... | S20: =if(B20=0,"...",P20/M20-1) -> ... | T20: =if(B20=0,"...",P20-M20) -> ... | U20: =if(B20=0,"...",R20/O20-1) -> ... | V20: =if(B20=0,"...",R20-O20) -> ... | Y20: =if(X20=0,"...",VLOOKUP("*"&X20&"*",$AL$2:$AM1113,2,false)) -> ... | Z20: =if(X20=0,"...",sumifs($H$2:$H1113,$B$2:$B1113,X20,$D$2:$D1113,"ABIERTA")) -> ... | AA20: =if(X20=0,"",AC20/$AH$18) | AB20: =if(Z20=0,"...",if(X20=0,"...",sumifs($O$2:$O1113,$B$2:$B1113,X20,$D$2:$D1113,"ABIERTA")/Z20)) -> ... | AC20: =if(X20=0,"...",sumifs($R$2:$R1113,$B$2:$B1113,X20,$D$2:$D1113,"ABIERTA")) -> ... | AD20: =if(Z20=0,"...",if(X20=0,"...",AE20/(AC20-AE20))) -> ... | AE20: =if(Z20=0,"...",if(X20=0,"...",sumifs($V$2:$V1113,$B$2:$B1113,X20,$D$2:$D1113,"ABIERTA"))) -> ... | AG20: Ganancia Abierto | AH20: =sumifs(V2:V1095,D2:D1095,"ABIERTA") -> 283.94694 | AI20: Ganancia Acumulada | AJ20: =sum(V2:V1095) -> 283.94694 | AL20: =IFERROR(__xludf.DUMMYFUNCTION("""COMPUTED_VALUE"""),"* BF37O *") -> * BF37O * | AM20: =IFERROR(__xludf.DUMMYFUNCTION("""COMPUTED_VALUE"""),147100.0) -> 147100
K21: =if(B21=0,"...",VLOOKUP(B21,$X$2:$Y1114,2,false)) -> ... | L21: =if(B21=0,"...",K21/IF(G21="DOLARES",1,Q21)) -> ... | P21: =if(B21=0,"...",$H21*(IF(D21="ABIERTA",K21,J21)*(1-VLOOKUP(A21,Config!$A$3:$B$5,2,FALSE)))/100) -> ... | S21: =if(B21=0,"...",P21/M21-1) -> ... | T21: =if(B21=0,"...",P21-M21) -> ... | U21: =if(B21=0,"...",R21/O21-1) -> ... | V21: =if(B21=0,"...",R21-O21) -> ... | Y21: =if(X21=0,"...",VLOOKUP("*"&X21&"*",$AL$2:$AM1114,2,false)) -> ... | Z21: =if(X21=0,"...",sumifs($H$2:$H1114,$B$2:$B1114,X21,$D$2:$D1114,"ABIERTA")) -> ... | AA21: =if(X21=0,"",AC21/$AH$18) | AB21: =if(Z21=0,"...",if(X21=0,"...",sumifs($O$2:$O1114,$B$2:$B1114,X21,$D$2:$D1114,"ABIERTA")/Z21)) -> ... | AC21: =if(X21=0,"...",sumifs($R$2:$R1114,$B$2:$B1114,X21,$D$2:$D1114,"ABIERTA")) -> ... | AD21: =if(Z21=0,"...",if(X21=0,"...",AE21/(AC21-AE21))) -> ... | AE21: =if(Z21=0,"...",if(X21=0,"...",sumifs($V$2:$V1114,$B$2:$B1114,X21,$D$2:$D1114,"ABIERTA"))) -> ... | AL21: =IFERROR(__xludf.DUMMYFUNCTION("""COMPUTED_VALUE"""),"* BF38O *") -> * BF38O * | AM21: =IFERROR(__xludf.DUMMYFUNCTION("""COMPUTED_VALUE"""),100.0) -> 100
K22: =if(B22=0,"...",VLOOKUP(B22,$X$2:$Y1115,2,false)) -> ... | L22: =if(B22=0,"...",K22/IF(G22="DOLARES",1,Q22)) -> ... | P22: =if(B22=0,"...",$H22*(IF(D22="ABIERTA",K22,J22)*(1-VLOOKUP(A22,Config!$A$3:$B$5,2,FALSE)))/100) -> ... | S22: =if(B22=0,"...",P22/M22-1) -> ... | T22: =if(B22=0,"...",P22-M22) -> ... | U22: =if(B22=0,"...",R22/O22-1) -> ... | V22: =if(B22=0,"...",R22-O22) -> ... | Y22: =if(X22=0,"...",VLOOKUP("*"&X22&"*",$AL$2:$AM1115,2,false)) -> ... | Z22: =if(X22=0,"...",sumifs($H$2:$H1115,$B$2:$B1115,X22,$D$2:$D1115,"ABIERTA")) -> ... | AA22: =if(X22=0,"",AC22/$AH$18) | AB22: =if(Z22=0,"...",if(X22=0,"...",sumifs($O$2:$O1115,$B$2:$B1115,X22,$D$2:$D1115,"ABIERTA")/Z22)) -> ... | AC22: =if(X22=0,"...",sumifs($R$2:$R1115,$B$2:$B1115,X22,$D$2:$D1115,"ABIERTA")) -> ... | AD22: =if(Z22=0,"...",if(X22=0,"...",AE22/(AC22-AE22))) -> ... | AE22: =if(Z22=0,"...",if(X22=0,"...",sumifs($V$2:$V1115,$B$2:$B1115,X22,$D$2:$D1115,"ABIERTA"))) -> ... | AG22: (%) | AH22: =AH20/(AH18-AH20) -> 0.22717334 | AI22: (%) | AJ22: =AJ20/(AJ18-AJ20) -> 0.22717334 | AL22: =IFERROR(__xludf.DUMMYFUNCTION("""COMPUTED_VALUE"""),"* BGC4D *") -> * BGC4D * | AM22: =IFERROR(__xludf.DUMMYFUNCTION("""COMPUTED_VALUE"""),100.5) -> 100.5
K23: =if(B23=0,"...",VLOOKUP(B23,$X$2:$Y1116,2,false)) -> ... | L23: =if(B23=0,"...",K23/IF(G23="DOLARES",1,Q23)) -> ... | P23: =if(B23=0,"...",$H23*(IF(D23="ABIERTA",K23,J23)*(1-VLOOKUP(A23,Config!$A$3:$B$5,2,FALSE)))/100) -> ... | S23: =if(B23=0,"...",P23/M23-1) -> ... | T23: =if(B23=0,"...",P23-M23) -> ... | U23: =if(B23=0,"...",R23/O23-1) -> ... | V23: =if(B23=0,"...",R23-O23) -> ... | Y23: =if(X23=0,"...",VLOOKUP("*"&X23&"*",$AL$2:$AM1116,2,false)) -> ... | Z23: =if(X23=0,"...",sumifs($H$2:$H1116,$B$2:$B1116,X23,$D$2:$D1116,"ABIERTA")) -> ... | AA23: =if(X23=0,"",AC23/$AH$18) | AB23: =if(Z23=0,"...",if(X23=0,"...",sumifs($O$2:$O1116,$B$2:$B1116,X23,$D$2:$D1116,"ABIERTA")/Z23)) -> ... | AC23: =if(X23=0,"...",sumifs($R$2:$R1116,$B$2:$B1116,X23,$D$2:$D1116,"ABIERTA")) -> ... | AD23: =if(Z23=0,"...",if(X23=0,"...",AE23/(AC23-AE23))) -> ... | AE23: =if(Z23=0,"...",if(X23=0,"...",sumifs($V$2:$V1116,$B$2:$B1116,X23,$D$2:$D1116,"ABIERTA"))) -> ... | AL23: =IFERROR(__xludf.DUMMYFUNCTION("""COMPUTED_VALUE"""),"* BGC4O *") -> * BGC4O * | AM23: =IFERROR(__xludf.DUMMYFUNCTION("""COMPUTED_VALUE"""),149300.0) -> 149300
K24: =if(B24=0,"...",VLOOKUP(B24,$X$2:$Y1117,2,false)) -> ... | L24: =if(B24=0,"...",K24/IF(G24="DOLARES",1,Q24)) -> ... | P24: =if(B24=0,"...",$H24*(IF(D24="ABIERTA",K24,J24)*(1-VLOOKUP(A24,Config!$A$3:$B$5,2,FALSE)))/100) -> ... | S24: =if(B24=0,"...",P24/M24-1) -> ... | T24: =if(B24=0,"...",P24-M24) -> ... | U24: =if(B24=0,"...",R24/O24-1) -> ... | V24: =if(B24=0,"...",R24-O24) -> ... | Y24: =if(X24=0,"...",VLOOKUP("*"&X24&"*",$AL$2:$AM1117,2,false)) -> ... | Z24: =if(X24=0,"...",sumifs($H$2:$H1117,$B$2:$B1117,X24,$D$2:$D1117,"ABIERTA")) -> ... | AA24: =if(X24=0,"",AC24/$AH$18) | AB24: =if(Z24=0,"...",if(X24=0,"...",sumifs($O$2:$O1117,$B$2:$B1117,X24,$D$2:$D1117,"ABIERTA")/Z24)) -> ... | AC24: =if(X24=0,"...",sumifs($R$2:$R1117,$B$2:$B1117,X24,$D$2:$D1117,"ABIERTA")) -> ... | AD24: =if(Z24=0,"...",if(X24=0,"...",AE24/(AC24-AE24))) -> ... | AE24: =if(Z24=0,"...",if(X24=0,"...",sumifs($V$2:$V1117,$B$2:$B1117,X24,$D$2:$D1117,"ABIERTA"))) -> ... | AL24: =IFERROR(__xludf.DUMMYFUNCTION("""COMPUTED_VALUE"""),"* BNCUO *") -> * BNCUO * | AM24: =IFERROR(__xludf.DUMMYFUNCTION("""COMPUTED_VALUE"""),108.0) -> 108
K25: =if(B25=0,"...",VLOOKUP(B25,$X$2:$Y1118,2,false)) -> ... | L25: =if(B25=0,"...",K25/IF(G25="DOLARES",1,Q25)) -> ... | P25: =if(B25=0,"...",$H25*(IF(D25="ABIERTA",K25,J25)*(1-VLOOKUP(A25,Config!$A$3:$B$5,2,FALSE)))/100) -> ... | S25: =if(B25=0,"...",P25/M25-1) -> ... | T25: =if(B25=0,"...",P25-M25) -> ... | U25: =if(B25=0,"...",R25/O25-1) -> ... | V25: =if(B25=0,"...",R25-O25) -> ... | Y25: =if(X25=0,"...",VLOOKUP("*"&X25&"*",$AL$2:$AM1118,2,false)) -> ... | Z25: =if(X25=0,"...",sumifs($H$2:$H1118,$B$2:$B1118,X25,$D$2:$D1118,"ABIERTA")) -> ... | AA25: =if(X25=0,"",AC25/$AH$18) | AB25: =if(Z25=0,"...",if(X25=0,"...",sumifs($O$2:$O1118,$B$2:$B1118,X25,$D$2:$D1118,"ABIERTA")/Z25)) -> ... | AC25: =if(X25=0,"...",sumifs($R$2:$R1118,$B$2:$B1118,X25,$D$2:$D1118,"ABIERTA")) -> ... | AD25: =if(Z25=0,"...",if(X25=0,"...",AE25/(AC25-AE25))) -> ... | AE25: =if(Z25=0,"...",if(X25=0,"...",sumifs($V$2:$V1118,$B$2:$B1118,X25,$D$2:$D1118,"ABIERTA"))) -> ... | AL25: =IFERROR(__xludf.DUMMYFUNCTION("""COMPUTED_VALUE"""),"* BOL1C *") -> * BOL1C * | AM25: =IFERROR(__xludf.DUMMYFUNCTION("""COMPUTED_VALUE"""),100.0) -> 100
K26: =if(B26=0,"...",VLOOKUP(B26,$X$2:$Y1119,2,false)) -> ... | L26: =if(B26=0,"...",K26/IF(G26="DOLARES",1,Q26)) -> ... | P26: =if(B26=0,"...",$H26*(IF(D26="ABIERTA",K26,J26)*(1-VLOOKUP(A26,Config!$A$3:$B$5,2,FALSE)))/100) -> ... | S26: =if(B26=0,"...",P26/M26-1) -> ... | T26: =if(B26=0,"...",P26-M26) -> ... | U26: =if(B26=0,"...",R26/O26-1) -> ... | V26: =if(B26=0,"...",R26-O26) -> ... | Y26: =if(X26=0,"...",VLOOKUP("*"&X26&"*",$AL$2:$AM1119,2,false)) -> ... | Z26: =if(X26=0,"...",sumifs($H$2:$H1119,$B$2:$B1119,X26,$D$2:$D1119,"ABIERTA")) -> ... | AA26: =if(X26=0,"",AC26/$AH$18) | AB26: =if(Z26=0,"...",if(X26=0,"...",sumifs($O$2:$O1119,$B$2:$B1119,X26,$D$2:$D1119,"ABIERTA")/Z26)) -> ... | AC26: =if(X26=0,"...",sumifs($R$2:$R1119,$B$2:$B1119,X26,$D$2:$D1119,"ABIERTA")) -> ... | AD26: =if(Z26=0,"...",if(X26=0,"...",AE26/(AC26-AE26))) -> ... | AE26: =if(Z26=0,"...",if(X26=0,"...",sumifs($V$2:$V1119,$B$2:$B1119,X26,$D$2:$D1119,"ABIERTA"))) -> ... | AG26: Config Gráficas | AH26: Tipo | AI26: column | AL26: =IFERROR(__xludf.DUMMYFUNCTION("""COMPUTED_VALUE"""),"* BOL1D *") -> * BOL1D * | AM26: =IFERROR(__xludf.DUMMYFUNCTION("""COMPUTED_VALUE"""),101.5) -> 101.5
K27: =if(B27=0,"...",VLOOKUP(B27,$X$2:$Y1120,2,false)) -> ... | L27: =if(B27=0,"...",K27/IF(G27="DOLARES",1,Q27)) -> ... | P27: =if(B27=0,"...",$H27*(IF(D27="ABIERTA",K27,J27)*(1-VLOOKUP(A27,Config!$A$3:$B$5,2,FALSE)))/100) -> ... | S27: =if(B27=0,"...",P27/M27-1) -> ... | T27: =if(B27=0,"...",P27-M27) -> ... | U27: =if(B27=0,"...",R27/O27-1) -> ... | V27: =if(B27=0,"...",R27-O27) -> ... | Y27: =if(X27=0,"...",VLOOKUP("*"&X27&"*",$AL$2:$AM1120,2,false)) -> ... | Z27: =if(X27=0,"...",sumifs($H$2:$H1120,$B$2:$B1120,X27,$D$2:$D1120,"ABIERTA")) -> ... | AA27: =if(X27=0,"",AC27/$AH$18) | AB27: =if(Z27=0,"...",if(X27=0,"...",sumifs($O$2:$O1120,$B$2:$B1120,X27,$D$2:$D1120,"ABIERTA")/Z27)) -> ... | AC27: =if(X27=0,"...",sumifs($R$2:$R1120,$B$2:$B1120,X27,$D$2:$D1120,"ABIERTA")) -> ... | AD27: =if(Z27=0,"...",if(X27=0,"...",AE27/(AC27-AE27))) -> ... | AE27: =if(Z27=0,"...",if(X27=0,"...",sumifs($V$2:$V1120,$B$2:$B1120,X27,$D$2:$D1120,"ABIERTA"))) -> ... | AH27: Días | AI27: 14 | AL27: =IFERROR(__xludf.DUMMYFUNCTION("""COMPUTED_VALUE"""),"* BOL1O *") -> * BOL1O * | AM27: =IFERROR(__xludf.DUMMYFUNCTION("""COMPUTED_VALUE"""),147500.0) -> 147500
K28: =if(B28=0,"...",VLOOKUP(B28,$X$2:$Y1121,2,false)) -> ... | L28: =if(B28=0,"...",K28/IF(G28="DOLARES",1,Q28)) -> ... | P28: =if(B28=0,"...",$H28*(IF(D28="ABIERTA",K28,J28)*(1-VLOOKUP(A28,Config!$A$3:$B$5,2,FALSE)))/100) -> ... | S28: =if(B28=0,"...",P28/M28-1) -> ... | T28: =if(B28=0,"...",P28-M28) -> ... | U28: =if(B28=0,"...",R28/O28-1) -> ... | V28: =if(B28=0,"...",R28-O28) -> ... | Y28: =if(X28=0,"...",VLOOKUP("*"&X28&"*",$AL$2:$AM1121,2,false)) -> ... | Z28: =if(X28=0,"...",sumifs($H$2:$H1121,$B$2:$B1121,X28,$D$2:$D1121,"ABIERTA")) -> ... | AA28: =if(X28=0,"",AC28/$AH$18) | AB28: =if(Z28=0,"...",if(X28=0,"...",sumifs($O$2:$O1121,$B$2:$B1121,X28,$D$2:$D1121,"ABIERTA")/Z28)) -> ... | AC28: =if(X28=0,"...",sumifs($R$2:$R1121,$B$2:$B1121,X28,$D$2:$D1121,"ABIERTA")) -> ... | AD28: =if(Z28=0,"...",if(X28=0,"...",AE28/(AC28-AE28))) -> ... | AE28: =if(Z28=0,"...",if(X28=0,"...",sumifs($V$2:$V1121,$B$2:$B1121,X28,$D$2:$D1121,"ABIERTA"))) -> ... | AL28: =IFERROR(__xludf.DUMMYFUNCTION("""COMPUTED_VALUE"""),"* BPCLO *") -> * BPCLO * | AM28: =IFERROR(__xludf.DUMMYFUNCTION("""COMPUTED_VALUE"""),100.0) -> 100
AL29: =IFERROR(__xludf.DUMMYFUNCTION("""COMPUTED_VALUE"""),"* BPCMO *") -> * BPCMO * | AM29: =IFERROR(__xludf.DUMMYFUNCTION("""COMPUTED_VALUE"""),109.3) -> 109.3
AL30: =IFERROR(__xludf.DUMMYFUNCTION("""COMPUTED_VALUE"""),"* BPCNO *") -> * BPCNO * | AM30: =IFERROR(__xludf.DUMMYFUNCTION("""COMPUTED_VALUE"""),111.2) -> 111.2
AL31: =IFERROR(__xludf.DUMMYFUNCTION("""COMPUTED_VALUE"""),"* BPCPD *") -> * BPCPD * | AM31: =IFERROR(__xludf.DUMMYFUNCTION("""COMPUTED_VALUE"""),102.25) -> 102.25
AL32: =IFERROR(__xludf.DUMMYFUNCTION("""COMPUTED_VALUE"""),"* BPCPO *") -> * BPCPO * | AM32: =IFERROR(__xludf.DUMMYFUNCTION("""COMPUTED_VALUE"""),160000.0) -> 160000
AL33: =IFERROR(__xludf.DUMMYFUNCTION("""COMPUTED_VALUE"""),"* BPCQD *") -> * BPCQD * | AM33: =IFERROR(__xludf.DUMMYFUNCTION("""COMPUTED_VALUE"""),100.0) -> 100
AL34: =IFERROR(__xludf.DUMMYFUNCTION("""COMPUTED_VALUE"""),"* BPCQO *") -> * BPCQO * | AM34: =IFERROR(__xludf.DUMMYFUNCTION("""COMPUTED_VALUE"""),156100.0) -> 156100
AL35: =IFERROR(__xludf.DUMMYFUNCTION("""COMPUTED_VALUE"""),"* BPCRO *") -> * BPCRO * | AM35: =IFERROR(__xludf.DUMMYFUNCTION("""COMPUTED_VALUE"""),100.0) -> 100
AL36: =IFERROR(__xludf.DUMMYFUNCTION("""COMPUTED_VALUE"""),"* BPCSO *") -> * BPCSO * | AM36: =IFERROR(__xludf.DUMMYFUNCTION("""COMPUTED_VALUE"""),148000.0) -> 148000
AL37: =IFERROR(__xludf.DUMMYFUNCTION("""COMPUTED_VALUE"""),"* BPCTD *") -> * BPCTD * | AM37: =IFERROR(__xludf.DUMMYFUNCTION("""COMPUTED_VALUE"""),104.0) -> 104
AL38: =IFERROR(__xludf.DUMMYFUNCTION("""COMPUTED_VALUE"""),"* BPCTO *") -> * BPCTO * | AM38: =IFERROR(__xludf.DUMMYFUNCTION("""COMPUTED_VALUE"""),150000.0) -> 150000
AL39: =IFERROR(__xludf.DUMMYFUNCTION("""COMPUTED_VALUE"""),"* BPCUC *") -> * BPCUC * | AM39: =IFERROR(__xludf.DUMMYFUNCTION("""COMPUTED_VALUE"""),100.0) -> 100
AL40: =IFERROR(__xludf.DUMMYFUNCTION("""COMPUTED_VALUE"""),"* BPCUD *") -> * BPCUD * | AM40: =IFERROR(__xludf.DUMMYFUNCTION("""COMPUTED_VALUE"""),100.0) -> 100
AL41: =IFERROR(__xludf.DUMMYFUNCTION("""COMPUTED_VALUE"""),"* BPCUO *") -> * BPCUO * | AM41: =IFERROR(__xludf.DUMMYFUNCTION("""COMPUTED_VALUE"""),147735.0) -> 147735
AL42: =IFERROR(__xludf.DUMMYFUNCTION("""COMPUTED_VALUE"""),"* BVCNO *") -> * BVCNO * | AM42: =IFERROR(__xludf.DUMMYFUNCTION("""COMPUTED_VALUE"""),100.0) -> 100
AL43: =IFERROR(__xludf.DUMMYFUNCTION("""COMPUTED_VALUE"""),"* BVCOD *") -> * BVCOD * | AM43: =IFERROR(__xludf.DUMMYFUNCTION("""COMPUTED_VALUE"""),99.25) -> 99.25
AL44: =IFERROR(__xludf.DUMMYFUNCTION("""COMPUTED_VALUE"""),"* BVCOO *") -> * BVCOO * | AM44: =IFERROR(__xludf.DUMMYFUNCTION("""COMPUTED_VALUE"""),146000.0) -> 146000
AL45: =IFERROR(__xludf.DUMMYFUNCTION("""COMPUTED_VALUE"""),"* BVCPC *") -> * BVCPC * | AM45: =IFERROR(__xludf.DUMMYFUNCTION("""COMPUTED_VALUE"""),100.0) -> 100
AL46: =IFERROR(__xludf.DUMMYFUNCTION("""COMPUTED_VALUE"""),"* BVCPD *") -> * BVCPD * | AM46: =IFERROR(__xludf.DUMMYFUNCTION("""COMPUTED_VALUE"""),100.0) -> 100
AL47: =IFERROR(__xludf.DUMMYFUNCTION("""COMPUTED_VALUE"""),"* BVCPO *") -> * BVCPO * | AM47: =IFERROR(__xludf.DUMMYFUNCTION("""COMPUTED_VALUE"""),148000.0) -> 148000
AL48: =IFERROR(__xludf.DUMMYFUNCTION("""COMPUTED_VALUE"""),"* BYC2O *") -> * BYC2O * | AM48: =IFERROR(__xludf.DUMMYFUNCTION("""COMPUTED_VALUE"""),136800.0) -> 136800
AL49: =IFERROR(__xludf.DUMMYFUNCTION("""COMPUTED_VALUE"""),"* BYC2P *") -> * BYC2P * | AM49: =IFERROR(__xludf.DUMMYFUNCTION("""COMPUTED_VALUE"""),104.0) -> 104
AL50: =IFERROR(__xludf.DUMMYFUNCTION("""COMPUTED_VALUE"""),"* BYCHD *") -> * BYCHD * | AM50: =IFERROR(__xludf.DUMMYFUNCTION("""COMPUTED_VALUE"""),105.5) -> 105.5
AL51: =IFERROR(__xludf.DUMMYFUNCTION("""COMPUTED_VALUE"""),"* BYCHO *") -> * BYCHO * | AM51: =IFERROR(__xludf.DUMMYFUNCTION("""COMPUTED_VALUE"""),154040.0) -> 154040
AL52: =IFERROR(__xludf.DUMMYFUNCTION("""COMPUTED_VALUE"""),"* BYCLO *") -> * BYCLO * | AM52: =IFERROR(__xludf.DUMMYFUNCTION("""COMPUTED_VALUE"""),103.9) -> 103.9
AL53: =IFERROR(__xludf.DUMMYFUNCTION("""COMPUTED_VALUE"""),"* BYCTD *") -> * BYCTD * | AM53: =IFERROR(__xludf.DUMMYFUNCTION("""COMPUTED_VALUE"""),102.5) -> 102.5
AL54: =IFERROR(__xludf.DUMMYFUNCTION("""COMPUTED_VALUE"""),"* BYCTO *") -> * BYCTO * | AM54: =IFERROR(__xludf.DUMMYFUNCTION("""COMPUTED_VALUE"""),157700.0) -> 157700
AL55: =IFERROR(__xludf.DUMMYFUNCTION("""COMPUTED_VALUE"""),"* BYCVC *") -> * BYCVC * | AM55: =IFERROR(__xludf.DUMMYFUNCTION("""COMPUTED_VALUE"""),99.3) -> 99.3
AL56: =IFERROR(__xludf.DUMMYFUNCTION("""COMPUTED_VALUE"""),"* BYCVD *") -> * BYCVD * | AM56: =IFERROR(__xludf.DUMMYFUNCTION("""COMPUTED_VALUE"""),102.05) -> 102.05
AL57: =IFERROR(__xludf.DUMMYFUNCTION("""COMPUTED_VALUE"""),"* BYCVO *") -> * BYCVO * | AM57: =IFERROR(__xludf.DUMMYFUNCTION("""COMPUTED_VALUE"""),152900.0) -> 152900
AL58: =IFERROR(__xludf.DUMMYFUNCTION("""COMPUTED_VALUE"""),"* CAC5C *") -> * CAC5C * | AM58: =IFERROR(__xludf.DUMMYFUNCTION("""COMPUTED_VALUE"""),74.25) -> 74.25
AL59: =IFERROR(__xludf.DUMMYFUNCTION("""COMPUTED_VALUE"""),"* CAC5D *") -> * CAC5D * | AM59: =IFERROR(__xludf.DUMMYFUNCTION("""COMPUTED_VALUE"""),81.0) -> 81
AL60: =IFERROR(__xludf.DUMMYFUNCTION("""COMPUTED_VALUE"""),"* CAC5O *") -> * CAC5O * | AM60: =IFERROR(__xludf.DUMMYFUNCTION("""COMPUTED_VALUE"""),120000.0) -> 120000
AL61: =IFERROR(__xludf.DUMMYFUNCTION("""COMPUTED_VALUE"""),"* CAC8D *") -> * CAC8D * | AM61: =IFERROR(__xludf.DUMMYFUNCTION("""COMPUTED_VALUE"""),99.1) -> 99.1
AL62: =IFERROR(__xludf.DUMMYFUNCTION("""COMPUTED_VALUE"""),"* CAC8O *") -> * CAC8O * | AM62: =IFERROR(__xludf.DUMMYFUNCTION("""COMPUTED_VALUE"""),145000.0) -> 145000
AL63: =IFERROR(__xludf.DUMMYFUNCTION("""COMPUTED_VALUE"""),"* CACBC *") -> * CACBC * | AM63: =IFERROR(__xludf.DUMMYFUNCTION("""COMPUTED_VALUE"""),100.0) -> 100
AL64: =IFERROR(__xludf.DUMMYFUNCTION("""COMPUTED_VALUE"""),"* CACBD *") -> * CACBD * | AM64: =IFERROR(__xludf.DUMMYFUNCTION("""COMPUTED_VALUE"""),100.0) -> 100
AL65: =IFERROR(__xludf.DUMMYFUNCTION("""COMPUTED_VALUE"""),"* CACBO *") -> * CACBO * | AM65: =IFERROR(__xludf.DUMMYFUNCTION("""COMPUTED_VALUE"""),146000.0) -> 146000
AL66: =IFERROR(__xludf.DUMMYFUNCTION("""COMPUTED_VALUE"""),"* CFS7D *") -> * CFS7D * | AM66: =IFERROR(__xludf.DUMMYFUNCTION("""COMPUTED_VALUE"""),100.0) -> 100
AL67: =IFERROR(__xludf.DUMMYFUNCTION("""COMPUTED_VALUE"""),"* CFS7O *") -> * CFS7O * | AM67: =IFERROR(__xludf.DUMMYFUNCTION("""COMPUTED_VALUE"""),41.6) -> 41.6
AL68: =IFERROR(__xludf.DUMMYFUNCTION("""COMPUTED_VALUE"""),"* CIC7O *") -> * CIC7O * | AM68: =IFERROR(__xludf.DUMMYFUNCTION("""COMPUTED_VALUE"""),147000.0) -> 147000
AL69: =IFERROR(__xludf.DUMMYFUNCTION("""COMPUTED_VALUE"""),"* CIC8D *") -> * CIC8D * | AM69: =IFERROR(__xludf.DUMMYFUNCTION("""COMPUTED_VALUE"""),94.0) -> 94
AL70: =IFERROR(__xludf.DUMMYFUNCTION("""COMPUTED_VALUE"""),"* CIC8O *") -> * CIC8O * | AM70: =IFERROR(__xludf.DUMMYFUNCTION("""COMPUTED_VALUE"""),123000.0) -> 123000
AL71: =IFERROR(__xludf.DUMMYFUNCTION("""COMPUTED_VALUE"""),"* CLI1D *") -> * CLI1D * | AM71: =IFERROR(__xludf.DUMMYFUNCTION("""COMPUTED_VALUE"""),32.0) -> 32
AL72: =IFERROR(__xludf.DUMMYFUNCTION("""COMPUTED_VALUE"""),"* CLI1O *") -> * CLI1O * | AM72: =IFERROR(__xludf.DUMMYFUNCTION("""COMPUTED_VALUE"""),48000.0) -> 48000
AL73: =IFERROR(__xludf.DUMMYFUNCTION("""COMPUTED_VALUE"""),"* CLSIC *") -> * CLSIC * | AM73: =IFERROR(__xludf.DUMMYFUNCTION("""COMPUTED_VALUE"""),31.0) -> 31
AL74: =IFERROR(__xludf.DUMMYFUNCTION("""COMPUTED_VALUE"""),"* CLSID *") -> * CLSID * | AM74: =IFERROR(__xludf.DUMMYFUNCTION("""COMPUTED_VALUE"""),33.3) -> 33.3
AL75: =IFERROR(__xludf.DUMMYFUNCTION("""COMPUTED_VALUE"""),"* CLSIO *") -> * CLSIO * | AM75: =IFERROR(__xludf.DUMMYFUNCTION("""COMPUTED_VALUE"""),49500.0) -> 49500
AL76: =IFERROR(__xludf.DUMMYFUNCTION("""COMPUTED_VALUE"""),"* COC1O *") -> * COC1O * | AM76: =IFERROR(__xludf.DUMMYFUNCTION("""COMPUTED_VALUE"""),103.0) -> 103
AL77: =IFERROR(__xludf.DUMMYFUNCTION("""COMPUTED_VALUE"""),"* COC2D *") -> * COC2D * | AM77: =IFERROR(__xludf.DUMMYFUNCTION("""COMPUTED_VALUE"""),99.5) -> 99.5
AL78: =IFERROR(__xludf.DUMMYFUNCTION("""COMPUTED_VALUE"""),"* COC2O *") -> * COC2O * | AM78: =IFERROR(__xludf.DUMMYFUNCTION("""COMPUTED_VALUE"""),145300.0) -> 145300
AL79: =IFERROR(__xludf.DUMMYFUNCTION("""COMPUTED_VALUE"""),"* CP29O *") -> * CP29O * | AM79: =IFERROR(__xludf.DUMMYFUNCTION("""COMPUTED_VALUE"""),20800.0) -> 20800
AL80: =IFERROR(__xludf.DUMMYFUNCTION("""COMPUTED_VALUE"""),"* CP32C *") -> * CP32C * | AM80: =IFERROR(__xludf.DUMMYFUNCTION("""COMPUTED_VALUE"""),99.75) -> 99.75
AL81: =IFERROR(__xludf.DUMMYFUNCTION("""COMPUTED_VALUE"""),"* CP32D *") -> * CP32D * | AM81: =IFERROR(__xludf.DUMMYFUNCTION("""COMPUTED_VALUE"""),103.15) -> 103.15
AL82: =IFERROR(__xludf.DUMMYFUNCTION("""COMPUTED_VALUE"""),"* CP32O *") -> * CP32O * | AM82: =IFERROR(__xludf.DUMMYFUNCTION("""COMPUTED_VALUE"""),149900.0) -> 149900
AL83: =IFERROR(__xludf.DUMMYFUNCTION("""COMPUTED_VALUE"""),"* CP34D *") -> * CP34D * | AM83: =IFERROR(__xludf.DUMMYFUNCTION("""COMPUTED_VALUE"""),100.15) -> 100.15
AL84: =IFERROR(__xludf.DUMMYFUNCTION("""COMPUTED_VALUE"""),"* CP34O *") -> * CP34O * | AM84: =IFERROR(__xludf.DUMMYFUNCTION("""COMPUTED_VALUE"""),143090.0) -> 143090
AL85: =IFERROR(__xludf.DUMMYFUNCTION("""COMPUTED_VALUE"""),"* CP35O *") -> * CP35O * | AM85: =IFERROR(__xludf.DUMMYFUNCTION("""COMPUTED_VALUE"""),137490.0) -> 137490
AL86: =IFERROR(__xludf.DUMMYFUNCTION("""COMPUTED_VALUE"""),"* CP36D *") -> * CP36D * | AM86: =IFERROR(__xludf.DUMMYFUNCTION("""COMPUTED_VALUE"""),86.0) -> 86
AL87: =IFERROR(__xludf.DUMMYFUNCTION("""COMPUTED_VALUE"""),"* CP36O *") -> * CP36O * | AM87: =IFERROR(__xludf.DUMMYFUNCTION("""COMPUTED_VALUE"""),126000.0) -> 126000
AL88: =IFERROR(__xludf.DUMMYFUNCTION("""COMPUTED_VALUE"""),"* CP37D *") -> * CP37D * | AM88: =IFERROR(__xludf.DUMMYFUNCTION("""COMPUTED_VALUE"""),89.0) -> 89
AL89: =IFERROR(__xludf.DUMMYFUNCTION("""COMPUTED_VALUE"""),"* CP37O *") -> * CP37O * | AM89: =IFERROR(__xludf.DUMMYFUNCTION("""COMPUTED_VALUE"""),124030.0) -> 124030
AL90: =IFERROR(__xludf.DUMMYFUNCTION("""COMPUTED_VALUE"""),"* CRCJD *") -> * CRCJD * | AM90: =IFERROR(__xludf.DUMMYFUNCTION("""COMPUTED_VALUE"""),17.25) -> 17.25
AL91: =IFERROR(__xludf.DUMMYFUNCTION("""COMPUTED_VALUE"""),"* CRCJO *") -> * CRCJO * | AM91: =IFERROR(__xludf.DUMMYFUNCTION("""COMPUTED_VALUE"""),12350.0) -> 12350
AL92: =IFERROR(__xludf.DUMMYFUNCTION("""COMPUTED_VALUE"""),"* CRCLD *") -> * CRCLD * | AM92: =IFERROR(__xludf.DUMMYFUNCTION("""COMPUTED_VALUE"""),52.0) -> 52
AL93: =IFERROR(__xludf.DUMMYFUNCTION("""COMPUTED_VALUE"""),"* CRCLO *") -> * CRCLO * | AM93: =IFERROR(__xludf.DUMMYFUNCTION("""COMPUTED_VALUE"""),31150.0) -> 31150
AL94: =IFERROR(__xludf.DUMMYFUNCTION("""COMPUTED_VALUE"""),"* CS38C *") -> * CS38C * | AM94: =IFERROR(__xludf.DUMMYFUNCTION("""COMPUTED_VALUE"""),102.45) -> 102.45
AL95: =IFERROR(__xludf.DUMMYFUNCTION("""COMPUTED_VALUE"""),"* CS38D *") -> * CS38D * | AM95: =IFERROR(__xludf.DUMMYFUNCTION("""COMPUTED_VALUE"""),104.0) -> 104
AL96: =IFERROR(__xludf.DUMMYFUNCTION("""COMPUTED_VALUE"""),"* CS38O *") -> * CS38O * | AM96: =IFERROR(__xludf.DUMMYFUNCTION("""COMPUTED_VALUE"""),151800.0) -> 151800
AL97: =IFERROR(__xludf.DUMMYFUNCTION("""COMPUTED_VALUE"""),"* CS40O *") -> * CS40O * | AM97: =IFERROR(__xludf.DUMMYFUNCTION("""COMPUTED_VALUE"""),103000.0) -> 103000
AL98: =IFERROR(__xludf.DUMMYFUNCTION("""COMPUTED_VALUE"""),"* CS44C *") -> * CS44C * | AM98: =IFERROR(__xludf.DUMMYFUNCTION("""COMPUTED_VALUE"""),99.5) -> 99.5
AL99: =IFERROR(__xludf.DUMMYFUNCTION("""COMPUTED_VALUE"""),"* CS44D *") -> * CS44D * | AM99: =IFERROR(__xludf.DUMMYFUNCTION("""COMPUTED_VALUE"""),101.9) -> 101.9
AL100: =IFERROR(__xludf.DUMMYFUNCTION("""COMPUTED_VALUE"""),"* CS44O *") -> * CS44O * | AM100: =IFERROR(__xludf.DUMMYFUNCTION("""COMPUTED_VALUE"""),151970.0) -> 151970
...

Sheet FCIs
B1: 10/30/23 | C1: Apertura | D1: Estado | E1: Cierre | F1: Dias | G1: Moneda | H1: Unidades | I1: Valor Compra | J1: Valor Venta | K1: Valor Actual | L1: Valor Actual USD | M1: Total Compra | N1: MEP Compra | O1: TC USD | P1: Total Venta | Q1: MEP Venta | R1: TV USD | S1: Ganancias (%) | T1: Ganancias Bruta | U1: GAN USD% | V1: GAN USD | X1: Ticker | Y1: Valor Actual | Z1: Unidades | AA1: % Cartera | AB1: PPC | AC1: Total (Abierto) | AD1: Ganancias (%) | AE1: Ganancias Tot | AL1: FCIs
A2: IOL | B2: CONIOLA | C2: 45324 | D2: CERRADA | E2: 45551 | F2: =if(B2=0,"...", IF(E2=0,today()-C2,E2-C2)) -> 227 | G2: PESOS | H2: 1455 | I2: 77.613 | J2: 107.65 | K2: =if(B2=0,"...",VLOOKUP(B2,$AL2:$AM29,2,false)) -> 187,01 | L2: =if(B2=0,"...",K2/IF(G2="DOLARES",1,Q2)) -> 0.15382654 | M2: =if(B2=0,"...",$H2*I2) -> 112926.91 | N2: 1237.43 | O2: =M2/IF(G2="DOLARES",1,N2) -> 91.259235 | P2: =if(B2=0,"...",$H2*(IF(D2="ABIERTA",K2,J2)*(1-VLOOKUP(A2,Config!$A$3:$B$5,2,FALSE)))) -> 156622.92 | Q2: 1215.72 | R2: =P2/IF(G2="DOLARES",1,Q2) -> 128.83141 | S2: =if(B2=0,"...",P2/M2-1) -> 0.38694056 | T2: =if(B2=0,"...",P2-M2) -> 43696.003 | U2: =if(B2=0,"...",R2/O2-1) -> 0.41170817 | V2: =if(B2=0,"...",R2-O2) -> 37.572172 | X2: {=Unique(B2:B29)} -> CONIOLA | Y2: =if(B2=0,"...",VLOOKUP(B2,$AL2:$AM29,2,false)) -> 187,01 | Z2: =if(X2=0,"...",sumifs($H$2:$H29,$B$2:$B29,X2,$D$2:$D29,"ABIERTA")) -> 0 | AA2: =if(X2=0,"",AC2/$AH$18) -> #DIV/0! | AB2: =if(Z2=0,"...",if(X2=0,"...",sumifs($O$2:$O29,$B$2:$B29,X2,$D$2:$D29,"ABIERTA")/Z2)) -> ... | AC2: =if(X2=0,"...",sumifs($R$2:$R29,$B$2:$B29,X2,$D$2:$D29,"ABIERTA")) -> 0 | AD2: =if(Z2=0,"...",if(X2=0,"...",AE2/(AC2-AE2))) -> ... | AE2: =if(Z2=0,"...",if(X2=0,"...",sumifs($V$2:$V29,$B$2:$B29,X2,$D$2:$D29,"ABIERTA"))) -> ... | AL2: Simbolo | AM2: Cierre | AN2: =IFERROR(__xludf.DUMMYFUNCTION("QUERY(IMPORTHTML(DataImports!B7,DataImports!D7,1),""select Col1, Col2, Col3, Col4"",1)"),"Símbolo") -> Símbolo | AO2: =IFERROR(__xludf.DUMMYFUNCTION("""COMPUTED_VALUE"""),"Tipo y moneda") -> Tipo y moneda | AP2: =IFERROR(__xludf.DUMMYFUNCTION("""COMPUTED_VALUE"""),"Horizonte de Inversión") -> Horizonte de Inversión | AQ2: =IFERROR(__xludf.DUMMYFUNCTION("""COMPUTED_VALUE"""),"Último") -> Último
Y3: =if(X3=0,"...",VLOOKUP("*"&X3&"*",$AN$2:$AO29,2,false)) -> ... | Z3: =if(X3=0,"...",sumifs($H$2:$H30,$B$2:$B30,X3,$D$2:$D30,"ABIERTA")) -> ... | AA3: =if(X3=0,"",AC3/$AH$18) | AB3: =if(Z3=0,"...",if(X3=0,"...",sumifs($O$2:$O30,$B$2:$B30,X3,$D$2:$D30,"ABIERTA")/Z3)) -> ... | AC3: =if(X3=0,"...",sumifs($R$2:$R30,$B$2:$B30,X3,$D$2:$D30,"ABIERTA")) -> ... | AD3: =if(Z3=0,"...",if(X3=0,"...",AE3/(AC3-AE3))) -> ... | AE3: =if(Z3=0,"...",if(X3=0,"...",sumifs($V$2:$V30,$B$2:$B30,X3,$D$2:$D30,"ABIERTA"))) -> ... | AL3: =IF($AN3="","...", Left(RIGHT($AN3,LEN($AN3)-FIND("*", $AN3)),FIND("*", RIGHT($AN3,LEN($AN3)-FIND("*", $AN3)))-1)) -> ADBAICA | AM3: =IF($AN3="","...", RIGHT($AQ3,LEN($AQ3)-FIND(" ", $AQ3))) -> 32,71 | AN3: =IFERROR(__xludf.DUMMYFUNCTION("""COMPUTED_VALUE"""),"*ADBAICA * Adcap Cobertura") -> *ADBAICA * Adcap Cobertura | AO3: =IFERROR(__xludf.DUMMYFUNCTION("""COMPUTED_VALUE"""),"Renta Fija Pesos") -> Renta Fija Pesos | AP3: =IFERROR(__xludf.DUMMYFUNCTION("""COMPUTED_VALUE"""),"Corto Plazo") -> Corto Plazo | AQ3: =IFERROR(__xludf.DUMMYFUNCTION("""COMPUTED_VALUE"""),"AR$ 32,71") -> AR$ 32,71
Y4: =if(X4=0,"...",VLOOKUP("*"&X4&"*",$AN$2:$AO30,2,false)) -> ... | Z4: =if(X4=0,"...",sumifs($H$2:$H31,$B$2:$B31,X4,$D$2:$D31,"ABIERTA")) -> ... | AA4: =if(X4=0,"",AC4/$AH$18) | AB4: =if(Z4=0,"...",if(X4=0,"...",sumifs($O$2:$O31,$B$2:$B31,X4,$D$2:$D31,"ABIERTA")/Z4)) -> ... | AC4: =if(X4=0,"...",sumifs($R$2:$R31,$B$2:$B31,X4,$D$2:$D31,"ABIERTA")) -> ... | AD4: =if(Z4=0,"...",if(X4=0,"...",AE4/(AC4-AE4))) -> ... | AE4: =if(Z4=0,"...",if(X4=0,"...",sumifs($V$2:$V31,$B$2:$B31,X4,$D$2:$D31,"ABIERTA"))) -> ... | AL4: =IF($AN4="","...", Left(RIGHT($AN4,LEN($AN4)-FIND("*", $AN4)),FIND("*", RIGHT($AN4,LEN($AN4)-FIND("*", $AN4)))-1)) -> ADBARFA | AM4: =IF($AN4="","...", RIGHT($AQ4,LEN($AQ4)-FIND(" ", $AQ4))) -> 5,00 | AN4: =IFERROR(__xludf.DUMMYFUNCTION("""COMPUTED_VALUE"""),"*ADBARFA * Adcap Balanceado XVI") -> *ADBARFA * Adcap Balanceado XVI | AO4: =IFERROR(__xludf.DUMMYFUNCTION("""COMPUTED_VALUE"""),"Renta Fija Pesos") -> Renta Fija Pesos | AP4: =IFERROR(__xludf.DUMMYFUNCTION("""COMPUTED_VALUE"""),"Mediano Plazo") -> Mediano Plazo | AQ4: =IFERROR(__xludf.DUMMYFUNCTION("""COMPUTED_VALUE"""),"AR$ 5,00") -> AR$ 5,00
Y5: =if(X5=0,"...",VLOOKUP("*"&X5&"*",$AN$2:$AO31,2,false)) -> ... | Z5: =if(X5=0,"...",sumifs($H$2:$H32,$B$2:$B32,X5,$D$2:$D32,"ABIERTA")) -> ... | AA5: =if(X5=0,"",AC5/$AH$18) | AB5: =if(Z5=0,"...",if(X5=0,"...",sumifs($O$2:$O32,$B$2:$B32,X5,$D$2:$D32,"ABIERTA")/Z5)) -> ... | AC5: =if(X5=0,"...",sumifs($R$2:$R32,$B$2:$B32,X5,$D$2:$D32,"ABIERTA")) -> ... | AD5: =if(Z5=0,"...",if(X5=0,"...",AE5/(AC5-AE5))) -> ... | AE5: =if(Z5=0,"...",if(X5=0,"...",sumifs($V$2:$V32,$B$2:$B32,X5,$D$2:$D32,"ABIERTA"))) -> ... | AL5: =IF($AN5="","...", Left(RIGHT($AN5,LEN($AN5)-FIND("*", $AN5)),FIND("*", RIGHT($AN5,LEN($AN5)-FIND("*", $AN5)))-1)) -> ADBWCPA | AM5: =IF($AN5="","...", RIGHT($AQ5,LEN($AQ5)-FIND(" ", $AQ5))) -> 9,89 | AN5: =IFERROR(__xludf.DUMMYFUNCTION("""COMPUTED_VALUE"""),"*ADBWCPA * Adcap Wise Capital Growth") -> *ADBWCPA * Adcap Wise Capital Growth | AO5: =IFERROR(__xludf.DUMMYFUNCTION("""COMPUTED_VALUE"""),"Renta Fija Pesos") -> Renta Fija Pesos | AP5: =IFERROR(__xludf.DUMMYFUNCTION("""COMPUTED_VALUE"""),"Mediano plazo") -> Mediano plazo | AQ5: =IFERROR(__xludf.DUMMYFUNCTION("""COMPUTED_VALUE"""),"AR$ 9,89") -> AR$ 9,89
Y6: =if(X6=0,"...",VLOOKUP("*"&X6&"*",$AN$2:$AO32,2,false)) -> ... | Z6: =if(X6=0,"...",sumifs($H$2:$H33,$B$2:$B33,X6,$D$2:$D33,"ABIERTA")) -> ... | AA6: =if(X6=0,"",AC6/$AH$18) | AB6: =if(Z6=0,"...",if(X6=0,"...",sumifs($O$2:$O33,$B$2:$B33,X6,$D$2:$D33,"ABIERTA")/Z6)) -> ... | AC6: =if(X6=0,"...",sumifs($R$2:$R33,$B$2:$B33,X6,$D$2:$D33,"ABIERTA")) -> ... | AD6: =if(Z6=0,"...",if(X6=0,"...",AE6/(AC6-AE6))) -> ... | AE6: =if(Z6=0,"...",if(X6=0,"...",sumifs($V$2:$V33,$B$2:$B33,X6,$D$2:$D33,"ABIERTA"))) -> ... | AL6: =IF($AN6="","...", Left(RIGHT($AN6,LEN($AN6)-FIND("*", $AN6)),FIND("*", RIGHT($AN6,LEN($AN6)-FIND("*", $AN6)))-1)) -> ADCGLOA | AM6: =IF($AN6="","...", RIGHT($AQ6,LEN($AQ6)-FIND(" ", $AQ6))) -> 1,28 | AN6: =IFERROR(__xludf.DUMMYFUNCTION("""COMPUTED_VALUE"""),"*ADCGLOA * Adcap Renta Dólar") -> *ADCGLOA * Adcap Renta Dólar | AO6: =IFERROR(__xludf.DUMMYFUNCTION("""COMPUTED_VALUE"""),"Renta Fija Dólares") -> Renta Fija Dólares | AP6: =IFERROR(__xludf.DUMMYFUNCTION("""COMPUTED_VALUE"""),"Corto Plazo") -> Corto Plazo | AQ6: =IFERROR(__xludf.DUMMYFUNCTION("""COMPUTED_VALUE"""),"US$ 1,28") -> US$ 1,28
Y7: =if(X7=0,"...",VLOOKUP("*"&X7&"*",$AN$2:$AO33,2,false)) -> ... | Z7: =if(X7=0,"...",sumifs($H$2:$H34,$B$2:$B34,X7,$D$2:$D34,"ABIERTA")) -> ... | AA7: =if(X7=0,"",AC7/$AH$18) | AB7: =if(Z7=0,"...",if(X7=0,"...",sumifs($O$2:$O34,$B$2:$B34,X7,$D$2:$D34,"ABIERTA")/Z7)) -> ... | AC7: =if(X7=0,"...",sumifs($R$2:$R34,$B$2:$B34,X7,$D$2:$D34,"ABIERTA")) -> ... | AD7: =if(Z7=0,"...",if(X7=0,"...",AE7/(AC7-AE7))) -> ... | AE7: =if(Z7=0,"...",if(X7=0,"...",sumifs($V$2:$V34,$B$2:$B34,X7,$D$2:$D34,"ABIERTA"))) -> ... | AL7: =IF($AN7="","...", Left(RIGHT($AN7,LEN($AN7)-FIND("*", $AN7)),FIND("*", RIGHT($AN7,LEN($AN7)-FIND("*", $AN7)))-1)) -> ADCUSAD | AM7: =IF($AN7="","...", RIGHT($AQ7,LEN($AQ7)-FIND(" ", $AQ7))) -> 1,03 | AN7: =IFERROR(__xludf.DUMMYFUNCTION("""COMPUTED_VALUE"""),"*ADCUSAD * Adcap Ahorro Dólares") -> *ADCUSAD * Adcap Ahorro Dólares | AO7: =IFERROR(__xludf.DUMMYFUNCTION("""COMPUTED_VALUE"""),"Plazos Fijos Dólares") -> Plazos Fijos Dólares | AP7: =IFERROR(__xludf.DUMMYFUNCTION("""COMPUTED_VALUE"""),"Corto Plazo") -> Corto Plazo | AQ7: =IFERROR(__xludf.DUMMYFUNCTION("""COMPUTED_VALUE"""),"US$ 1,03") -> US$ 1,03
Y8: =if(X8=0,"...",VLOOKUP("*"&X8&"*",$AN$2:$AO34,2,false)) -> ... | Z8: =if(X8=0,"...",sumifs($H$2:$H35,$B$2:$B35,X8,$D$2:$D35,"ABIERTA")) -> ... | AA8: =if(X8=0,"",AC8/$AH$18) | AB8: =if(Z8=0,"...",if(X8=0,"...",sumifs($O$2:$O35,$B$2:$B35,X8,$D$2:$D35,"ABIERTA")/Z8)) -> ... | AC8: =if(X8=0,"...",sumifs($R$2:$R35,$B$2:$B35,X8,$D$2:$D35,"ABIERTA")) -> ... | AD8: =if(Z8=0,"...",if(X8=0,"...",AE8/(AC8-AE8))) -> ... | AE8: =if(Z8=0,"...",if(X8=0,"...",sumifs($V$2:$V35,$B$2:$B35,X8,$D$2:$D35,"ABIERTA"))) -> ... | AL8: =IF($AN8="","...", Left(RIGHT($AN8,LEN($AN8)-FIND("*", $AN8)),FIND("*", RIGHT($AN8,LEN($AN8)-FIND("*", $AN8)))-1)) -> ADRDOLA | AM8: =IF($AN8="","...", RIGHT($AQ8,LEN($AQ8)-FIND(" ", $AQ8))) -> 16,07 | AN8: =IFERROR(__xludf.DUMMYFUNCTION("""COMPUTED_VALUE"""),"*ADRDOLA * Adcap Ahorro Pesos Fondo De Dinero") -> *ADRDOLA * Adcap Ahorro Pesos Fondo De Dinero | AO8: =IFERROR(__xludf.DUMMYFUNCTION("""COMPUTED_VALUE"""),"Plazos Fijos Pesos") -> Plazos Fijos Pesos | AP8: =IFERROR(__xludf.DUMMYFUNCTION("""COMPUTED_VALUE"""),"Corto Plazo") -> Corto Plazo | AQ8: =IFERROR(__xludf.DUMMYFUNCTION("""COMPUTED_VALUE"""),"AR$ 16,07") -> AR$ 16,07
K9: =if(B9=0,"...",VLOOKUP(B9,$X$2:$Y29,2,false)) -> ... | L9: =if(B9=0,"...",K9/IF(G9="DOLARES",1,Q9)) -> ... | P9: =if(B9=0,"...",$H9*(IF(D9="ABIERTA",K9,J9)*(1-VLOOKUP(A9,Config!$A$3:$B$5,2,FALSE)))/100) -> ... | S9: =if(B9=0,"...",P9/M9-1) -> ... | T9: =if(B9=0,"...",P9-M9) -> ... | U9: =if(B9=0,"...",R9/O9-1) -> ... | V9: =if(B9=0,"...",R9-O9) -> ... | Y9: =if(X9=0,"...",VLOOKUP("*"&X9&"*",$AN$2:$AO35,2,false)) -> ... | Z9: =if(X9=0,"...",sumifs($H$2:$H36,$B$2:$B36,X9,$D$2:$D36,"ABIERTA")) -> ... | AA9: =if(X9=0,"",AC9/$AH$18) | AB9: =if(Z9=0,"...",if(X9=0,"...",sumifs($O$2:$O36,$B$2:$B36,X9,$D$2:$D36,"ABIERTA")/Z9)) -> ... | AC9: =if(X9=0,"...",sumifs($R$2:$R36,$B$2:$B36,X9,$D$2:$D36,"ABIERTA")) -> ... | AD9: =if(Z9=0,"...",if(X9=0,"...",AE9/(AC9-AE9))) -> ... | AE9: =if(Z9=0,"...",if(X9=0,"...",sumifs($V$2:$V36,$B$2:$B36,X9,$D$2:$D36,"ABIERTA"))) -> ... | AL9: =IF($AN9="","...", Left(RIGHT($AN9,LEN($AN9)-FIND("*", $AN9)),FIND("*", RIGHT($AN9,LEN($AN9)-FIND("*", $AN9)))-1)) -> ADREMIA | AM9: =IF($AN9="","...", RIGHT($AQ9,LEN($AQ9)-FIND(" ", $AQ9))) -> 93,67 | AN9: =IFERROR(__xludf.DUMMYFUNCTION("""COMPUTED_VALUE"""),"*ADREMIA * Adcap Balanceado Vi") -> *ADREMIA * Adcap Balanceado Vi | AO9: =IFERROR(__xludf.DUMMYFUNCTION("""COMPUTED_VALUE"""),"Renta Fija Pesos") -> Renta Fija Pesos | AP9: =IFERROR(__xludf.DUMMYFUNCTION("""COMPUTED_VALUE"""),"Mediano Plazo") -> Mediano Plazo | AQ9: =IFERROR(__xludf.DUMMYFUNCTION("""COMPUTED_VALUE"""),"AR$ 93,67") -> AR$ 93,67
K10: =if(B10=0,"...",VLOOKUP(B10,$X$2:$Y30,2,false)) -> ... | L10: =if(B10=0,"...",K10/IF(G10="DOLARES",1,Q10)) -> ... | P10: =if(B10=0,"...",$H10*(IF(D10="ABIERTA",K10,J10)*(1-VLOOKUP(A10,Config!$A$3:$B$5,2,FALSE)))/100) -> ... | S10: =if(B10=0,"...",P10/M10-1) -> ... | T10: =if(B10=0,"...",P10-M10) -> ... | U10: =if(B10=0,"...",R10/O10-1) -> ... | V10: =if(B10=0,"...",R10-O10) -> ... | Y10: =if(X10=0,"...",VLOOKUP("*"&X10&"*",$AN$2:$AO36,2,false)) -> ... | Z10: =if(X10=0,"...",sumifs($H$2:$H37,$B$2:$B37,X10,$D$2:$D37,"ABIERTA")) -> ... | AA10: =if(X10=0,"",AC10/$AH$18) | AB10: =if(Z10=0,"...",if(X10=0,"...",sumifs($O$2:$O37,$B$2:$B37,X10,$D$2:$D37,"ABIERTA")/Z10)) -> ... | AC10: =if(X10=0,"...",sumifs($R$2:$R37,$B$2:$B37,X10,$D$2:$D37,"ABIERTA")) -> ... | AD10: =if(Z10=0,"...",if(X10=0,"...",AE10/(AC10-AE10))) -> ... | AE10: =if(Z10=0,"...",if(X10=0,"...",sumifs($V$2:$V37,$B$2:$B37,X10,$D$2:$D37,"ABIERTA"))) -> ... | AL10: =IF($AN10="","...", Left(RIGHT($AN10,LEN($AN10)-FIND("*", $AN10)),FIND("*", RIGHT($AN10,LEN($AN10)-FIND("*", $AN10)))-1)) -> CNXPOPA | AM10: =IF($AN10="","...", RIGHT($AQ10,LEN($AQ10)-FIND(" ", $AQ10))) -> 113,02 | AN10: =IFERROR(__xludf.DUMMYFUNCTION("""COMPUTED_VALUE"""),"*CNXPOPA * Adcap Pesos Plus") -> *CNXPOPA * Adcap Pesos Plus | AO10: =IFERROR(__xludf.DUMMYFUNCTION("""COMPUTED_VALUE"""),"Renta Fija Pesos") -> Renta Fija Pesos | AP10: =IFERROR(__xludf.DUMMYFUNCTION("""COMPUTED_VALUE"""),"Corto Plazo") -> Corto Plazo | AQ10: =IFERROR(__xludf.DUMMYFUNCTION("""COMPUTED_VALUE"""),"AR$ 113,02") -> AR$ 113,02
K11: =if(B11=0,"...",VLOOKUP(B11,$X$2:$Y31,2,false)) -> ... | L11: =if(B11=0,"...",K11/IF(G11="DOLARES",1,Q11)) -> ... | P11: =if(B11=0,"...",$H11*(IF(D11="ABIERTA",K11,J11)*(1-VLOOKUP(A11,Config!$A$3:$B$5,2,FALSE)))/100) -> ... | S11: =if(B11=0,"...",P11/M11-1) -> ... | T11: =if(B11=0,"...",P11-M11) -> ... | U11: =if(B11=0,"...",R11/O11-1) -> ... | V11: =if(B11=0,"...",R11-O11) -> ... | Y11: =if(X11=0,"...",VLOOKUP("*"&X11&"*",$AN$2:$AO37,2,false)) -> ... | Z11: =if(X11=0,"...",sumifs($H$2:$H38,$B$2:$B38,X11,$D$2:$D38,"ABIERTA")) -> ... | AA11: =if(X11=0,"",AC11/$AH$18) | AB11: =if(Z11=0,"...",if(X11=0,"...",sumifs($O$2:$O38,$B$2:$B38,X11,$D$2:$D38,"ABIERTA")/Z11)) -> ... | AC11: =if(X11=0,"...",sumifs($R$2:$R38,$B$2:$B38,X11,$D$2:$D38,"ABIERTA")) -> ... | AD11: =if(Z11=0,"...",if(X11=0,"...",AE11/(AC11-AE11))) -> ... | AE11: =if(Z11=0,"...",if(X11=0,"...",sumifs($V$2:$V38,$B$2:$B38,X11,$D$2:$D38,"ABIERTA"))) -> ... | AL11: =IF($AN11="","...", Left(RIGHT($AN11,LEN($AN11)-FIND("*", $AN11)),FIND("*", RIGHT($AN11,LEN($AN11)-FIND("*", $AN11)))-1)) -> CONBAA | AM11: =IF($AN11="","...", RIGHT($AQ11,LEN($AQ11)-FIND(" ", $AQ11))) -> 125,20 | AN11: =IFERROR(__xludf.DUMMYFUNCTION("""COMPUTED_VALUE"""),"*CONBAA * Adcap Balanceado") -> *CONBAA * Adcap Balanceado | AO11: =IFERROR(__xludf.DUMMYFUNCTION("""COMPUTED_VALUE"""),"Renta Mixta Pesos") -> Renta Mixta Pesos | AP11: =IFERROR(__xludf.DUMMYFUNCTION("""COMPUTED_VALUE"""),"Largo Plazo") -> Largo Plazo | AQ11: =IFERROR(__xludf.DUMMYFUNCTION("""COMPUTED_VALUE"""),"AR$ 125,20") -> AR$ 125,20
K12: =if(B12=0,"...",VLOOKUP(B12,$X$2:$Y32,2,false)) -> ... | L12: =if(B12=0,"...",K12/IF(G12="DOLARES",1,Q12)) -> ... | P12: =if(B12=0,"...",$H12*(IF(D12="ABIERTA",K12,J12)*(1-VLOOKUP(A12,Config!$A$3:$B$5,2,FALSE)))/100) -> ... | S12: =if(B12=0,"...",P12/M12-1) -> ... | T12: =if(B12=0,"...",P12-M12) -> ... | U12: =if(B12=0,"...",R12/O12-1) -> ... | V12: =if(B12=0,"...",R12-O12) -> ... | Y12: =if(X12=0,"...",VLOOKUP("*"&X12&"*",$AN$2:$AO38,2,false)) -> ... | Z12: =if(X12=0,"...",sumifs($H$2:$H39,$B$2:$B39,X12,$D$2:$D39,"ABIERTA")) -> ... | AA12: =if(X12=0,"",AC12/$AH$18) | AB12: =if(Z12=0,"...",if(X12=0,"...",sumifs($O$2:$O39,$B$2:$B39,X12,$D$2:$D39,"ABIERTA")/Z12)) -> ... | AC12: =if(X12=0,"...",sumifs($R$2:$R39,$B$2:$B39,X12,$D$2:$D39,"ABIERTA")) -> ... | AD12: =if(Z12=0,"...",if(X12=0,"...",AE12/(AC12-AE12))) -> ... | AE12: =if(Z12=0,"...",if(X12=0,"...",sumifs($V$2:$V39,$B$2:$B39,X12,$D$2:$D39,"ABIERTA"))) -> ... | AL12: =IF($AN12="","...", Left(RIGHT($AN12,LEN($AN12)-FIND("*", $AN12)),FIND("*", RIGHT($AN12,LEN($AN12)-FIND("*", $AN12)))-1)) -> CONIOLA | AM12: =IF($AN12="","...", RIGHT($AQ12,LEN($AQ12)-FIND(" ", $AQ12))) -> 187,01 | AN12: =IFERROR(__xludf.DUMMYFUNCTION("""COMPUTED_VALUE"""),"*CONIOLA * Adcap Acciones") -> *CONIOLA * Adcap Acciones | AO12: =IFERROR(__xludf.DUMMYFUNCTION("""COMPUTED_VALUE"""),"Renta Variable Pesos") -> Renta Variable Pesos | AP12: =IFERROR(__xludf.DUMMYFUNCTION("""COMPUTED_VALUE"""),"Largo Plazo") -> Largo Plazo | AQ12: =IFERROR(__xludf.DUMMYFUNCTION("""COMPUTED_VALUE"""),"AR$ 187,01") -> AR$ 187,01
K13: =if(B13=0,"...",VLOOKUP(B13,$X$2:$Y33,2,false)) -> ... | L13: =if(B13=0,"...",K13/IF(G13="DOLARES",1,Q13)) -> ... | P13: =if(B13=0,"...",$H13*(IF(D13="ABIERTA",K13,J13)*(1-VLOOKUP(A13,Config!$A$3:$B$5,2,FALSE)))/100) -> ... | S13: =if(B13=0,"...",P13/M13-1) -> ... | T13: =if(B13=0,"...",P13-M13) -> ... | U13: =if(B13=0,"...",R13/O13-1) -> ... | V13: =if(B13=0,"...",R13-O13) -> ... | Y13: =if(X13=0,"...",VLOOKUP("*"&X13&"*",$AN$2:$AO39,2,false)) -> ... | Z13: =if(X13=0,"...",sumifs($H$2:$H40,$B$2:$B40,X13,$D$2:$D40,"ABIERTA")) -> ... | AA13: =if(X13=0,"",AC13/$AH$18) | AB13: =if(Z13=0,"...",if(X13=0,"...",sumifs($O$2:$O40,$B$2:$B40,X13,$D$2:$D40,"ABIERTA")/Z13)) -> ... | AC13: =if(X13=0,"...",sumifs($R$2:$R40,$B$2:$B40,X13,$D$2:$D40,"ABIERTA")) -> ... | AD13: =if(Z13=0,"...",if(X13=0,"...",AE13/(AC13-AE13))) -> ... | AE13: =if(Z13=0,"...",if(X13=0,"...",sumifs($V$2:$V40,$B$2:$B40,X13,$D$2:$D40,"ABIERTA"))) -> ... | AL13: =IF($AN13="","...", Left(RIGHT($AN13,LEN($AN13)-FIND("*", $AN13)),FIND("*", RIGHT($AN13,LEN($AN13)-FIND("*", $AN13)))-1)) -> CONRETO | AM13: =IF($AN13="","...", RIGHT($AQ13,LEN($AQ13)-FIND(" ", $AQ13))) -> 28,85 | AN13: =IFERROR(__xludf.DUMMYFUNCTION("""COMPUTED_VALUE"""),"*CONRETO * Adcap Moneda") -> *CONRETO * Adcap Moneda | AO13: =IFERROR(__xludf.DUMMYFUNCTION("""COMPUTED_VALUE"""),"Renta Variable Pesos") -> Renta Variable Pesos | AP13: =IFERROR(__xludf.DUMMYFUNCTION("""COMPUTED_VALUE"""),"Mediano Plazo") -> Mediano Plazo | AQ13: =IFERROR(__xludf.DUMMYFUNCTION("""COMPUTED_VALUE"""),"AR$ 28,85") -> AR$ 28,85
K14: =if(B14=0,"...",VLOOKUP(B14,$X$2:$Y34,2,false)) -> ... | L14: =if(B14=0,"...",K14/IF(G14="DOLARES",1,Q14)) -> ... | P14: =if(B14=0,"...",$H14*(IF(D14="ABIERTA",K14,J14)*(1-VLOOKUP(A14,Config!$A$3:$B$5,2,FALSE)))/100) -> ... | S14: =if(B14=0,"...",P14/M14-1) -> ... | T14: =if(B14=0,"...",P14-M14) -> ... | U14: =if(B14=0,"...",R14/O14-1) -> ... | V14: =if(B14=0,"...",R14-O14) -> ... | Y14: =if(X14=0,"...",VLOOKUP("*"&X14&"*",$AN$2:$AO40,2,false)) -> ... | Z14: =if(X14=0,"...",sumifs($H$2:$H41,$B$2:$B41,X14,$D$2:$D41,"ABIERTA")) -> ... | AA14: =if(X14=0,"",AC14/$AH$18) | AB14: =if(Z14=0,"...",if(X14=0,"...",sumifs($O$2:$O41,$B$2:$B41,X14,$D$2:$D41,"ABIERTA")/Z14)) -> ... | AC14: =if(X14=0,"...",sumifs($R$2:$R41,$B$2:$B41,X14,$D$2:$D41,"ABIERTA")) -> ... | AD14: =if(Z14=0,"...",if(X14=0,"...",AE14/(AC14-AE14))) -> ... | AE14: =if(Z14=0,"...",if(X14=0,"...",sumifs($V$2:$V41,$B$2:$B41,X14,$D$2:$D41,"ABIERTA"))) -> ... | AL14: =IF($AN14="","...", Left(RIGHT($AN14,LEN($AN14)-FIND("*", $AN14)),FIND("*", RIGHT($AN14,LEN($AN14)-FIND("*", $AN14)))-1)) -> CRTAFAA | AM14: =IF($AN14="","...", RIGHT($AQ14,LEN($AQ14)-FIND(" ", $AQ14))) -> 160,94 | AN14: =IFERROR(__xludf.DUMMYFUNCTION("""COMPUTED_VALUE"""),"*CRTAFAA * Adcap Renta Fija") -> *CRTAFAA * Adcap Renta Fija | AO14: =IFERROR(__xludf.DUMMYFUNCTION("""COMPUTED_VALUE"""),"Renta Fija Pesos") -> Renta Fija Pesos | AP14: =IFERROR(__xludf.DUMMYFUNCTION("""COMPUTED_VALUE"""),"Mediano Plazo") -> Mediano Plazo | AQ14: =IFERROR(__xludf.DUMMYFUNCTION("""COMPUTED_VALUE"""),"AR$ 160,94") -> AR$ 160,94
K15: =if(B15=0,"...",VLOOKUP(B15,$X$2:$Y35,2,false)) -> ... | L15: =if(B15=0,"...",K15/IF(G15="DOLARES",1,Q15)) -> ... | P15: =if(B15=0,"...",$H15*(IF(D15="ABIERTA",K15,J15)*(1-VLOOKUP(A15,Config!$A$3:$B$5,2,FALSE)))/100) -> ... | S15: =if(B15=0,"...",P15/M15-1) -> ... | T15: =if(B15=0,"...",P15-M15) -> ... | U15: =if(B15=0,"...",R15/O15-1) -> ... | V15: =if(B15=0,"...",R15-O15) -> ... | Y15: =if(X15=0,"...",VLOOKUP("*"&X15&"*",$AN$2:$AO41,2,false)) -> ... | Z15: =if(X15=0,"...",sumifs($H$2:$H42,$B$2:$B42,X15,$D$2:$D42,"ABIERTA")) -> ... | AA15: =if(X15=0,"",AC15/$AH$18) | AB15: =if(Z15=0,"...",if(X15=0,"...",sumifs($O$2:$O42,$B$2:$B42,X15,$D$2:$D42,"ABIERTA")/Z15)) -> ... | AC15: =if(X15=0,"...",sumifs($R$2:$R42,$B$2:$B42,X15,$D$2:$D42,"ABIERTA")) -> ... | AD15: =if(Z15=0,"...",if(X15=0,"...",AE15/(AC15-AE15))) -> ... | AE15: =if(Z15=0,"...",if(X15=0,"...",sumifs($V$2:$V42,$B$2:$B42,X15,$D$2:$D42,"ABIERTA"))) -> ... | AL15: =IF($AN15="","...", Left(RIGHT($AN15,LEN($AN15)-FIND("*", $AN15)),FIND("*", RIGHT($AN15,LEN($AN15)-FIND("*", $AN15)))-1)) -> IOLDOLD | AM15: =IF($AN15="","...", RIGHT($AQ15,LEN($AQ15)-FIND(" ", $AQ15))) -> 1,04 | AN15: =IFERROR(__xludf.DUMMYFUNCTION("""COMPUTED_VALUE"""),"*IOLDOLD * IOL Dólar Ahorro Plus") -> *IOLDOLD * IOL Dólar Ahorro Plus | AO15: =IFERROR(__xludf.DUMMYFUNCTION("""COMPUTED_VALUE"""),"Renta Fija Dólares") -> Renta Fija Dólares | AP15: =IFERROR(__xludf.DUMMYFUNCTION("""COMPUTED_VALUE"""),"Corto Plazo") -> Corto Plazo | AQ15: =IFERROR(__xludf.DUMMYFUNCTION("""COMPUTED_VALUE"""),"US$ 1,04") -> US$ 1,04
K16: =if(B16=0,"...",VLOOKUP(B16,$X$2:$Y36,2,false)) -> ... | L16: =if(B16=0,"...",K16/IF(G16="DOLARES",1,Q16)) -> ... | P16: =if(B16=0,"...",$H16*(IF(D16="ABIERTA",K16,J16)*(1-VLOOKUP(A16,Config!$A$3:$B$5,2,FALSE)))/100) -> ... | S16: =if(B16=0,"...",P16/M16-1) -> ... | T16: =if(B16=0,"...",P16-M16) -> ... | U16: =if(B16=0,"...",R16/O16-1) -> ... | V16: =if(B16=0,"...",R16-O16) -> ... | Y16: =if(X16=0,"...",VLOOKUP("*"&X16&"*",$AN$2:$AO42,2,false)) -> ... | Z16: =if(X16=0,"...",sumifs($H$2:$H43,$B$2:$B43,X16,$D$2:$D43,"ABIERTA")) -> ... | AA16: =if(X16=0,"",AC16/$AH$18) | AB16: =if(Z16=0,"...",if(X16=0,"...",sumifs($O$2:$O43,$B$2:$B43,X16,$D$2:$D43,"ABIERTA")/Z16)) -> ... | AC16: =if(X16=0,"...",sumifs($R$2:$R43,$B$2:$B43,X16,$D$2:$D43,"ABIERTA")) -> ... | AD16: =if(Z16=0,"...",if(X16=0,"...",AE16/(AC16-AE16))) -> ... | AE16: =if(Z16=0,"...",if(X16=0,"...",sumifs($V$2:$V43,$B$2:$B43,X16,$D$2:$D43,"ABIERTA"))) -> ... | AL16: =IF($AN16="","...", Left(RIGHT($AN16,LEN($AN16)-FIND("*", $AN16)),FIND("*", RIGHT($AN16,LEN($AN16)-FIND("*", $AN16)))-1)) -> IOLPORA | AM16: =IF($AN16="","...", RIGHT($AQ16,LEN($AQ16)-FIND(" ", $AQ16))) -> 1,32 | AN16: =IFERROR(__xludf.DUMMYFUNCTION("""COMPUTED_VALUE"""),"*IOLPORA * IOL Portafolio Potenciado") -> *IOLPORA * IOL Portafolio Potenciado | AO16: =IFERROR(__xludf.DUMMYFUNCTION("""COMPUTED_VALUE"""),"Renta Mixta Pesos") -> Renta Mixta Pesos | AP16: =IFERROR(__xludf.DUMMYFUNCTION("""COMPUTED_VALUE"""),"Mediano Plazo") -> Mediano Plazo | AQ16: =IFERROR(__xludf.DUMMYFUNCTION("""COMPUTED_VALUE"""),"AR$ 1,32") -> AR$ 1,32
K17: =if(B17=0,"...",VLOOKUP(B17,$X$2:$Y37,2,false)) -> ... | L17: =if(B17=0,"...",K17/IF(G17="DOLARES",1,Q17)) -> ... | P17: =if(B17=0,"...",$H17*(IF(D17="ABIERTA",K17,J17)*(1-VLOOKUP(A17,Config!$A$3:$B$5,2,FALSE)))/100) -> ... | S17: =if(B17=0,"...",P17/M17-1) -> ... | T17: =if(B17=0,"...",P17-M17) -> ... | U17: =if(B17=0,"...",R17/O17-1) -> ... | V17: =if(B17=0,"...",R17-O17) -> ... | Y17: =if(X17=0,"...",VLOOKUP("*"&X17&"*",$AN$2:$AO43,2,false)) -> ... | Z17: =if(X17=0,"...",sumifs($H$2:$H44,$B$2:$B44,X17,$D$2:$D44,"ABIERTA")) -> ... | AA17: =if(X17=0,"",AC17/$AH$18) | AB17: =if(Z17=0,"...",if(X17=0,"...",sumifs($O$2:$O44,$B$2:$B44,X17,$D$2:$D44,"ABIERTA")/Z17)) -> ... | AC17: =if(X17=0,"...",sumifs($R$2:$R44,$B$2:$B44,X17,$D$2:$D44,"ABIERTA")) -> ... | AD17: =if(Z17=0,"...",if(X17=0,"...",AE17/(AC17-AE17))) -> ... | AE17: =if(Z17=0,"...",if(X17=0,"...",sumifs($V$2:$V44,$B$2:$B44,X17,$D$2:$D44,"ABIERTA"))) -> ... | AL17: =IF($AN17="","...", Left(RIGHT($AN17,LEN($AN17)-FIND("*", $AN17)),FIND("*", RIGHT($AN17,LEN($AN17)-FIND("*", $AN17)))-1)) -> PCOMAGB | AM17: =IF($AN17="","...", RIGHT($AQ17,LEN($AQ17)-FIND(" ", $AQ17))) -> 357,07 | AN17: =IFERROR(__xludf.DUMMYFUNCTION("""COMPUTED_VALUE"""),"*PCOMAGB * Premier Commodities") -> *PCOMAGB * Premier Commodities | AO17: =IFERROR(__xludf.DUMMYFUNCTION("""COMPUTED_VALUE"""),"Renta Variable Pesos") -> Renta Variable Pesos | AP17: =IFERROR(__xludf.DUMMYFUNCTION("""COMPUTED_VALUE"""),"Largo Plazo") -> Largo Plazo | AQ17: =IFERROR(__xludf.DUMMYFUNCTION("""COMPUTED_VALUE"""),"AR$ 357,07") -> AR$ 357,07
K18: =if(B18=0,"...",VLOOKUP(B18,$X$2:$Y38,2,false)) -> ... | L18: =if(B18=0,"...",K18/IF(G18="DOLARES",1,Q18)) -> ... | P18: =if(B18=0,"...",$H18*(IF(D18="ABIERTA",K18,J18)*(1-VLOOKUP(A18,Config!$A$3:$B$5,2,FALSE)))/100) -> ... | S18: =if(B18=0,"...",P18/M18-1) -> ... | T18: =if(B18=0,"...",P18-M18) -> ... | U18: =if(B18=0,"...",R18/O18-1) -> ... | V18: =if(B18=0,"...",R18-O18) -> ... | Y18: =if(X18=0,"...",VLOOKUP("*"&X18&"*",$AN$2:$AO44,2,false)) -> ... | Z18: =if(X18=0,"...",sumifs($H$2:$H45,$B$2:$B45,X18,$D$2:$D45,"ABIERTA")) -> ... | AA18: =if(X18=0,"",AC18/$AH$18) | AB18: =if(Z18=0,"...",if(X18=0,"...",sumifs($O$2:$O45,$B$2:$B45,X18,$D$2:$D45,"ABIERTA")/Z18)) -> ... | AC18: =if(X18=0,"...",sumifs($R$2:$R45,$B$2:$B45,X18,$D$2:$D45,"ABIERTA")) -> ... | AD18: =if(Z18=0,"...",if(X18=0,"...",AE18/(AC18-AE18))) -> ... | AE18: =if(Z18=0,"...",if(X18=0,"...",sumifs($V$2:$V45,$B$2:$B45,X18,$D$2:$D45,"ABIERTA"))) -> ... | AG18: Total Abierto | AH18: =sumifs(R2:R29,D2:D29,"ABIERTA") -> 0 | AI18: Total Acumulado | AJ18: =sum(R2:R29) -> 128.83141 | AL18: =IF($AN18="","...", Left(RIGHT($AN18,LEN($AN18)-FIND("*", $AN18)),FIND("*", RIGHT($AN18,LEN($AN18)-FIND("*", $AN18)))-1)) -> PRCPPEB | AM18: =IF($AN18="","...", RIGHT($AQ18,LEN($AQ18)-FIND(" ", $AQ18))) -> 144,66 | AN18: =IFERROR(__xludf.DUMMYFUNCTION("""COMPUTED_VALUE"""),"*PRCPPEB * Premier Renta Corto Plazo En Pesos") -> *PRCPPEB * Premier Renta Corto Plazo En Pesos | AO18: =IFERROR(__xludf.DUMMYFUNCTION("""COMPUTED_VALUE"""),"Plazos Fijos Pesos") -> Plazos Fijos Pesos | AP18: =IFERROR(__xludf.DUMMYFUNCTION("""COMPUTED_VALUE"""),"Corto Plazo") -> Corto Plazo | AQ18: =IFERROR(__xludf.DUMMYFUNCTION("""COMPUTED_VALUE"""),"AR$ 144,66") -> AR$ 144,66
K19: =if(B19=0,"...",VLOOKUP(B19,$X$2:$Y39,2,false)) -> ... | L19: =if(B19=0,"...",K19/IF(G19="DOLARES",1,Q19)) -> ... | P19: =if(B19=0,"...",$H19*(IF(D19="ABIERTA",K19,J19)*(1-VLOOKUP(A19,Config!$A$3:$B$5,2,FALSE)))/100) -> ... | S19: =if(B19=0,"...",P19/M19-1) -> ... | T19: =if(B19=0,"...",P19-M19) -> ... | U19: =if(B19=0,"...",R19/O19-1) -> ... | V19: =if(B19=0,"...",R19-O19) -> ... | Y19: =if(X19=0,"...",VLOOKUP("*"&X19&"*",$AN$2:$AO45,2,false)) -> ... | Z19: =if(X19=0,"...",sumifs($H$2:$H46,$B$2:$B46,X19,$D$2:$D46,"ABIERTA")) -> ... | AA19: =if(X19=0,"",AC19/$AH$18) | AB19: =if(Z19=0,"...",if(X19=0,"...",sumifs($O$2:$O46,$B$2:$B46,X19,$D$2:$D46,"ABIERTA")/Z19)) -> ... | AC19: =if(X19=0,"...",sumifs($R$2:$R46,$B$2:$B46,X19,$D$2:$D46,"ABIERTA")) -> ... | AD19: =if(Z19=0,"...",if(X19=0,"...",AE19/(AC19-AE19))) -> ... | AE19: =if(Z19=0,"...",if(X19=0,"...",sumifs($V$2:$V46,$B$2:$B46,X19,$D$2:$D46,"ABIERTA"))) -> ... | AL19: =IF($AN19="","...", Left(RIGHT($AN19,LEN($AN19)-FIND("*", $AN19)),FIND("*", RIGHT($AN19,LEN($AN19)-FIND("*", $AN19)))-1)) -> PRERMDB | AM19: =IF($AN19="","...", RIGHT($AQ19,LEN($AQ19)-FIND(" ", $AQ19))) -> 0,99 | AN19: =IFERROR(__xludf.DUMMYFUNCTION("""COMPUTED_VALUE"""),"*PRERMDB * Premier Renta Mixta En Dolares") -> *PRERMDB * Premier Renta Mixta En Dolares | AO19: =IFERROR(__xludf.DUMMYFUNCTION("""COMPUTED_VALUE"""),"Renta Mixta Dólares") -> Renta Mixta Dólares | AP19: =IFERROR(__xludf.DUMMYFUNCTION("""COMPUTED_VALUE"""),"Largo Plazo") -> Largo Plazo | AQ19: =IFERROR(__xludf.DUMMYFUNCTION("""COMPUTED_VALUE"""),"US$ 0,99") -> US$ 0,99
K20: =if(B20=0,"...",VLOOKUP(B20,$X$2:$Y40,2,false)) -> ... | L20: =if(B20=0,"...",K20/IF(G20="DOLARES",1,Q20)) -> ... | P20: =if(B20=0,"...",$H20*(IF(D20="ABIERTA",K20,J20)*(1-VLOOKUP(A20,Config!$A$3:$B$5,2,FALSE)))/100) -> ... | S20: =if(B20=0,"...",P20/M20-1) -> ... | T20: =if(B20=0,"...",P20-M20) -> ... | U20: =if(B20=0,"...",R20/O20-1) -> ... | V20: =if(B20=0,"...",R20-O20) -> ... | Y20: =if(X20=0,"...",VLOOKUP("*"&X20&"*",$AN$2:$AO46,2,false)) -> ... | Z20: =if(X20=0,"...",sumifs($H$2:$H47,$B$2:$B47,X20,$D$2:$D47,"ABIERTA")) -> ... | AA20: =if(X20=0,"",AC20/$AH$18) | AB20: =if(Z20=0,"...",if(X20=0,"...",sumifs($O$2:$O47,$B$2:$B47,X20,$D$2:$D47,"ABIERTA")/Z20)) -> ... | AC20: =if(X20=0,"...",sumifs($R$2:$R47,$B$2:$B47,X20,$D$2:$D47,"ABIERTA")) -> ... | AD20: =if(Z20=0,"...",if(X20=0,"...",AE20/(AC20-AE20))) -> ... | AE20: =if(Z20=0,"...",if(X20=0,"...",sumifs($V$2:$V47,$B$2:$B47,X20,$D$2:$D47,"ABIERTA"))) -> ... | AG20: Ganancia Abierto | AH20: =sumifs(V2:V29,D2:D29,"ABIERTA") -> 0 | AI20: Ganancia Acumulada | AJ20: =sum(V2:V29) -> 37.572172 | AL20: =IF($AN20="","...", Left(RIGHT($AN20,LEN($AN20)-FIND("*", $AN20)),FIND("*", RIGHT($AN20,LEN($AN20)-FIND("*", $AN20)))-1)) -> PRFAHOB | AM20: =IF($AN20="","...", RIGHT($AQ20,LEN($AQ20)-FIND(" ", $AQ20))) -> 700,56 | AN20: =IFERROR(__xludf.DUMMYFUNCTION("""COMPUTED_VALUE"""),"*PRFAHOB * Premier Renta Fija Ahorro") -> *PRFAHOB * Premier Renta Fija Ahorro | AO20: =IFERROR(__xludf.DUMMYFUNCTION("""COMPUTED_VALUE"""),"Renta Fija Pesos") -> Renta Fija Pesos | AP20: =IFERROR(__xludf.DUMMYFUNCTION("""COMPUTED_VALUE"""),"Corto Plazo") -> Corto Plazo | AQ20: =IFERROR(__xludf.DUMMYFUNCTION("""COMPUTED_VALUE"""),"AR$ 700,56") -> AR$ 700,56
K21: =if(B21=0,"...",VLOOKUP(B21,$X$2:$Y41,2,false)) -> ... | L21: =if(B21=0,"...",K21/IF(G21="DOLARES",1,Q21)) -> ... | P21: =if(B21=0,"...",$H21*(IF(D21="ABIERTA",K21,J21)*(1-VLOOKUP(A21,Config!$A$3:$B$5,2,FALSE)))/100) -> ... | S21: =if(B21=0,"...",P21/M21-1) -> ... | T21: =if(B21=0,"...",P21-M21) -> ... | U21: =if(B21=0,"...",R21/O21-1) -> ... | V21: =if(B21=0,"...",R21-O21) -> ... | Y21: =if(X21=0,"...",VLOOKUP("*"&X21&"*",$AN$2:$AO47,2,false)) -> ... | Z21: =if(X21=0,"...",sumifs($H$2:$H48,$B$2:$B48,X21,$D$2:$D48,"ABIERTA")) -> ... | AA21: =if(X21=0,"",AC21/$AH$18) | AB21: =if(Z21=0,"...",if(X21=0,"...",sumifs($O$2:$O48,$B$2:$B48,X21,$D$2:$D48,"ABIERTA")/Z21)) -> ... | AC21: =if(X21=0,"...",sumifs($R$2:$R48,$B$2:$B48,X21,$D$2:$D48,"ABIERTA")) -> ... | AD21: =if(Z21=0,"...",if(X21=0,"...",AE21/(AC21-AE21))) -> ... | AE21: =if(Z21=0,"...",if(X21=0,"...",sumifs($V$2:$V48,$B$2:$B48,X21,$D$2:$D48,"ABIERTA"))) -> ... | AL21: =IF($AN21="","...", Left(RIGHT($AN21,LEN($AN21)-FIND("*", $AN21)),FIND("*", RIGHT($AN21,LEN($AN21)-FIND("*", $AN21)))-1)) -> PRGLBDB | AM21: =IF($AN21="","...", RIGHT($AQ21,LEN($AQ21)-FIND(" ", $AQ21))) -> 0,86 | AN21: =IFERROR(__xludf.DUMMYFUNCTION("""COMPUTED_VALUE"""),"*PRGLBDB * Premier Global Dolares") -> *PRGLBDB * Premier Global Dolares | AO21: =IFERROR(__xludf.DUMMYFUNCTION("""COMPUTED_VALUE"""),"Renta Fija Dólares") -> Renta Fija Dólares | AP21: =IFERROR(__xludf.DUMMYFUNCTION("""COMPUTED_VALUE"""),"Mediano Plazo") -> Mediano Plazo | AQ21: =IFERROR(__xludf.DUMMYFUNCTION("""COMPUTED_VALUE"""),"US$ 0,86") -> US$ 0,86
K22: =if(B22=0,"...",VLOOKUP(B22,$X$2:$Y42,2,false)) -> ... | L22: =if(B22=0,"...",K22/IF(G22="DOLARES",1,Q22)) -> ... | P22: =if(B22=0,"...",$H22*(IF(D22="ABIERTA",K22,J22)*(1-VLOOKUP(A22,Config!$A$3:$B$5,2,FALSE)))/100) -> ... | S22: =if(B22=0,"...",P22/M22-1) -> ... | T22: =if(B22=0,"...",P22-M22) -> ... | U22: =if(B22=0,"...",R22/O22-1) -> ... | V22: =if(B22=0,"...",R22-O22) -> ... | Y22: =if(X22=0,"...",VLOOKUP("*"&X22&"*",$AN$2:$AO48,2,false)) -> ... | Z22: =if(X22=0,"...",sumifs($H$2:$H49,$B$2:$B49,X22,$D$2:$D49,"ABIERTA")) -> ... | AA22: =if(X22=0,"",AC22/$AH$18) | AB22: =if(Z22=0,"...",if(X22=0,"...",sumifs($O$2:$O49,$B$2:$B49,X22,$D$2:$D49,"ABIERTA")/Z22)) -> ... | AC22: =if(X22=0,"...",sumifs($R$2:$R49,$B$2:$B49,X22,$D$2:$D49,"ABIERTA")) -> ... | AD22: =if(Z22=0,"...",if(X22=0,"...",AE22/(AC22-AE22))) -> ... | AE22: =if(Z22=0,"...",if(X22=0,"...",sumifs($V$2:$V49,$B$2:$B49,X22,$D$2:$D49,"ABIERTA"))) -> ... | AG22: (%) | AH22: =AH20/(AH18-AH20) -> #DIV/0! | AI22: (%) | AJ22: =AJ20/(AJ18-AJ20) -> 0.41170817 | AL22: =IF($AN22="","...", Left(RIGHT($AN22,LEN($AN22)-FIND("*", $AN22)),FIND("*", RIGHT($AN22,LEN($AN22)-FIND("*", $AN22)))-1)) -> PRMCAPB | AM22: =IF($AN22="","...", RIGHT($AQ22,LEN($AQ22)-FIND(" ", $AQ22))) -> 142,69 | AN22: =IFERROR(__xludf.DUMMYFUNCTION("""COMPUTED_VALUE"""),"*PRMCAPB * Premier Capital") -> *PRMCAPB * Premier Capital | AO22: =IFERROR(__xludf.DUMMYFUNCTION("""COMPUTED_VALUE"""),"Renta Fija Pesos") -> Renta Fija Pesos | AP22: =IFERROR(__xludf.DUMMYFUNCTION("""COMPUTED_VALUE"""),"Mediano Plazo") -> Mediano Plazo | AQ22: =IFERROR(__xludf.DUMMYFUNCTION("""COMPUTED_VALUE"""),"AR$ 142,69") -> AR$ 142,69
K23: =if(B23=0,"...",VLOOKUP(B23,$X$2:$Y43,2,false)) -> ... | L23: =if(B23=0,"...",K23/IF(G23="DOLARES",1,Q23)) -> ... | P23: =if(B23=0,"...",$H23*(IF(D23="ABIERTA",K23,J23)*(1-VLOOKUP(A23,Config!$A$3:$B$5,2,FALSE)))/100) -> ... | S23: =if(B23=0,"...",P23/M23-1) -> ... | T23: =if(B23=0,"...",P23-M23) -> ... | U23: =if(B23=0,"...",R23/O23-1) -> ... | V23: =if(B23=0,"...",R23-O23) -> ... | Y23: =if(X23=0,"...",VLOOKUP("*"&X23&"*",$AN$2:$AO49,2,false)) -> ... | Z23: =if(X23=0,"...",sumifs($H$2:$H50,$B$2:$B50,X23,$D$2:$D50,"ABIERTA")) -> ... | AA23: =if(X23=0,"",AC23/$AH$18) | AB23: =if(Z23=0,"...",if(X23=0,"...",sumifs($O$2:$O50,$B$2:$B50,X23,$D$2:$D50,"ABIERTA")/Z23)) -> ... | AC23: =if(X23=0,"...",sumifs($R$2:$R50,$B$2:$B50,X23,$D$2:$D50,"ABIERTA")) -> ... | AD23: =if(Z23=0,"...",if(X23=0,"...",AE23/(AC23-AE23))) -> ... | AE23: =if(Z23=0,"...",if(X23=0,"...",sumifs($V$2:$V50,$B$2:$B50,X23,$D$2:$D50,"ABIERTA"))) -> ... | AL23: =IF($AN23="","...", Left(RIGHT($AN23,LEN($AN23)-FIND("*", $AN23)),FIND("*", RIGHT($AN23,LEN($AN23)-FIND("*", $AN23)))-1)) -> PRPEDOB | AM23: =IF($AN23="","...", RIGHT($AQ23,LEN($AQ23)-FIND(" ", $AQ23))) -> 1,65 | AN23: =IFERROR(__xludf.DUMMYFUNCTION("""COMPUTED_VALUE"""),"*PRPEDOB * Premier Performance Dolares") -> *PRPEDOB * Premier Performance Dolares | AO23: =IFERROR(__xludf.DUMMYFUNCTION("""COMPUTED_VALUE"""),"Renta Fija Dólares") -> Renta Fija Dólares | AP23: =IFERROR(__xludf.DUMMYFUNCTION("""COMPUTED_VALUE"""),"Corto Plazo") -> Corto Plazo | AQ23: =IFERROR(__xludf.DUMMYFUNCTION("""COMPUTED_VALUE"""),"US$ 1,65") -> US$ 1,65
K24: =if(B24=0,"...",VLOOKUP(B24,$X$2:$Y44,2,false)) -> ... | L24: =if(B24=0,"...",K24/IF(G24="DOLARES",1,Q24)) -> ... | P24: =if(B24=0,"...",$H24*(IF(D24="ABIERTA",K24,J24)*(1-VLOOKUP(A24,Config!$A$3:$B$5,2,FALSE)))/100) -> ... | S24: =if(B24=0,"...",P24/M24-1) -> ... | T24: =if(B24=0,"...",P24-M24) -> ... | U24: =if(B24=0,"...",R24/O24-1) -> ... | V24: =if(B24=0,"...",R24-O24) -> ... | Y24: =if(X24=0,"...",VLOOKUP("*"&X24&"*",$AN$2:$AO50,2,false)) -> ... | Z24: =if(X24=0,"...",sumifs($H$2:$H51,$B$2:$B51,X24,$D$2:$D51,"ABIERTA")) -> ... | AA24: =if(X24=0,"",AC24/$AH$18) | AB24: =if(Z24=0,"...",if(X24=0,"...",sumifs($O$2:$O51,$B$2:$B51,X24,$D$2:$D51,"ABIERTA")/Z24)) -> ... | AC24: =if(X24=0,"...",sumifs($R$2:$R51,$B$2:$B51,X24,$D$2:$D51,"ABIERTA")) -> ... | AD24: =if(Z24=0,"...",if(X24=0,"...",AE24/(AC24-AE24))) -> ... | AE24: =if(Z24=0,"...",if(X24=0,"...",sumifs($V$2:$V51,$B$2:$B51,X24,$D$2:$D51,"ABIERTA"))) -> ... | AL24: =IF($AN24="","...", Left(RIGHT($AN24,LEN($AN24)-FIND("*", $AN24)),FIND("*", RIGHT($AN24,LEN($AN24)-FIND("*", $AN24)))-1)) -> PRPLPEB | AM24: =IF($AN24="","...", RIGHT($AQ24,LEN($AQ24)-FIND(" ", $AQ24))) -> 151,11 | AN24: =IFERROR(__xludf.DUMMYFUNCTION("""COMPUTED_VALUE"""),"*PRPLPEB * Premier Renta Plus En Pesos") -> *PRPLPEB * Premier Renta Plus En Pesos | AO24: =IFERROR(__xludf.DUMMYFUNCTION("""COMPUTED_VALUE"""),"Renta Fija Pesos") -> Renta Fija Pesos | AP24: =IFERROR(__xludf.DUMMYFUNCTION("""COMPUTED_VALUE"""),"Corto Plazo") -> Corto Plazo | AQ24: =IFERROR(__xludf.DUMMYFUNCTION("""COMPUTED_VALUE"""),"AR$ 151,11") -> AR$ 151,11
K25: =if(B25=0,"...",VLOOKUP(B25,$X$2:$Y45,2,false)) -> ... | L25: =if(B25=0,"...",K25/IF(G25="DOLARES",1,Q25)) -> ... | P25: =if(B25=0,"...",$H25*(IF(D25="ABIERTA",K25,J25)*(1-VLOOKUP(A25,Config!$A$3:$B$5,2,FALSE)))/100) -> ... | S25: =if(B25=0,"...",P25/M25-1) -> ... | T25: =if(B25=0,"...",P25-M25) -> ... | U25: =if(B25=0,"...",R25/O25-1) -> ... | V25: =if(B25=0,"...",R25-O25) -> ... | Y25: =if(X25=0,"...",VLOOKUP("*"&X25&"*",$AN$2:$AO51,2,false)) -> ... | Z25: =if(X25=0,"...",sumifs($H$2:$H52,$B$2:$B52,X25,$D$2:$D52,"ABIERTA")) -> ... | AA25: =if(X25=0,"",AC25/$AH$18) | AB25: =if(Z25=0,"...",if(X25=0,"...",sumifs($O$2:$O52,$B$2:$B52,X25,$D$2:$D52,"ABIERTA")/Z25)) -> ... | AC25: =if(X25=0,"...",sumifs($R$2:$R52,$B$2:$B52,X25,$D$2:$D52,"ABIERTA")) -> ... | AD25: =if(Z25=0,"...",if(X25=0,"...",AE25/(AC25-AE25))) -> ... | AE25: =if(Z25=0,"...",if(X25=0,"...",sumifs($V$2:$V52,$B$2:$B52,X25,$D$2:$D52,"ABIERTA"))) -> ... | AL25: =IF($AN25="","...", Left(RIGHT($AN25,LEN($AN25)-FIND("*", $AN25)),FIND("*", RIGHT($AN25,LEN($AN25)-FIND("*", $AN25)))-1)) -> PRREMIB | AM25: =IF($AN25="","...", RIGHT($AQ25,LEN($AQ25)-FIND(" ", $AQ25))) -> 49,04 | AN25: =IFERROR(__xludf.DUMMYFUNCTION("""COMPUTED_VALUE"""),"*PRREMIB * Premier Renta Mixta") -> *PRREMIB * Premier Renta Mixta | AO25: =IFERROR(__xludf.DUMMYFUNCTION("""COMPUTED_VALUE"""),"Renta Mixta Pesos") -> Renta Mixta Pesos | AP25: =IFERROR(__xludf.DUMMYFUNCTION("""COMPUTED_VALUE"""),"Largo Plazo") -> Largo Plazo | AQ25: =IFERROR(__xludf.DUMMYFUNCTION("""COMPUTED_VALUE"""),"AR$ 49,04") -> AR$ 49,04
K26: =if(B26=0,"...",VLOOKUP(B26,$X$2:$Y46,2,false)) -> ... | L26: =if(B26=0,"...",K26/IF(G26="DOLARES",1,Q26)) -> ... | P26: =if(B26=0,"...",$H26*(IF(D26="ABIERTA",K26,J26)*(1-VLOOKUP(A26,Config!$A$3:$B$5,2,FALSE)))/100) -> ... | S26: =if(B26=0,"...",P26/M26-1) -> ... | T26: =if(B26=0,"...",P26-M26) -> ... | U26: =if(B26=0,"...",R26/O26-1) -> ... | V26: =if(B26=0,"...",R26-O26) -> ... | Y26: =if(X26=0,"...",VLOOKUP("*"&X26&"*",$AN$2:$AO52,2,false)) -> ... | Z26: =if(X26=0,"...",sumifs($H$2:$H53,$B$2:$B53,X26,$D$2:$D53,"ABIERTA")) -> ... | AA26: =if(X26=0,"",AC26/$AH$18) | AB26: =if(Z26=0,"...",if(X26=0,"...",sumifs($O$2:$O53,$B$2:$B53,X26,$D$2:$D53,"ABIERTA")/Z26)) -> ... | AC26: =if(X26=0,"...",sumifs($R$2:$R53,$B$2:$B53,X26,$D$2:$D53,"ABIERTA")) -> ... | AD26: =if(Z26=0,"...",if(X26=0,"...",AE26/(AC26-AE26))) -> ... | AE26: =if(Z26=0,"...",if(X26=0,"...",sumifs($V$2:$V53,$B$2:$B53,X26,$D$2:$D53,"ABIERTA"))) -> ... | AG26: Config Gráficas | AH26: Tipo | AI26: column | AL26: =IF($AN26="","...", Left(RIGHT($AN26,LEN($AN26)-FIND("*", $AN26)),FIND("*", RIGHT($AN26,LEN($AN26)-FIND("*", $AN26)))-1)) -> PRTAVAB | AM26: =IF($AN26="","...", RIGHT($AQ26,LEN($AQ26)-FIND(" ", $AQ26))) -> 1.322,50 | AN26: =IFERROR(__xludf.DUMMYFUNCTION("""COMPUTED_VALUE"""),"*PRTAVAB * Premier Renta Variable") -> *PRTAVAB * Premier Renta Variable | AO26: =IFERROR(__xludf.DUMMYFUNCTION("""COMPUTED_VALUE"""),"Renta Variable Pesos") -> Renta Variable Pesos | AP26: =IFERROR(__xludf.DUMMYFUNCTION("""COMPUTED_VALUE"""),"Largo Plazo") -> Largo Plazo | AQ26: =IFERROR(__xludf.DUMMYFUNCTION("""COMPUTED_VALUE"""),"AR$ 1.322,50") -> AR$ 1.322,50
K27: =if(B27=0,"...",VLOOKUP(B27,$X$2:$Y47,2,false)) -> ... | L27: =if(B27=0,"...",K27/IF(G27="DOLARES",1,Q27)) -> ... | P27: =if(B27=0,"...",$H27*(IF(D27="ABIERTA",K27,J27)*(1-VLOOKUP(A27,Config!$A$3:$B$5,2,FALSE)))/100) -> ... | S27: =if(B27=0,"...",P27/M27-1) -> ... | T27: =if(B27=0,"...",P27-M27) -> ... | U27: =if(B27=0,"...",R27/O27-1) -> ... | V27: =if(B27=0,"...",R27-O27) -> ... | Y27: =if(X27=0,"...",VLOOKUP("*"&X27&"*",$AN$2:$AO53,2,false)) -> ... | Z27: =if(X27=0,"...",sumifs($H$2:$H54,$B$2:$B54,X27,$D$2:$D54,"ABIERTA")) -> ... | AA27: =if(X27=0,"",AC27/$AH$18) | AB27: =if(Z27=0,"...",if(X27=0,"...",sumifs($O$2:$O54,$B$2:$B54,X27,$D$2:$D54,"ABIERTA")/Z27)) -> ... | AC27: =if(X27=0,"...",sumifs($R$2:$R54,$B$2:$B54,X27,$D$2:$D54,"ABIERTA")) -> ... | AD27: =if(Z27=0,"...",if(X27=0,"...",AE27/(AC27-AE27))) -> ... | AE27: =if(Z27=0,"...",if(X27=0,"...",sumifs($V$2:$V54,$B$2:$B54,X27,$D$2:$D54,"ABIERTA"))) -> ... | AH27: Días | AI27: 14 | AL27: =IF($AN27="","...", Left(RIGHT($AN27,LEN($AN27)-FIND("*", $AN27)),FIND("*", RIGHT($AN27,LEN($AN27)-FIND("*", $AN27)))-1)) -> ... | AM27: =IF($AN27="","...", RIGHT($AQ27,LEN($AQ27)-FIND(" ", $AQ27))) -> ...
K28: =if(B28=0,"...",VLOOKUP(B28,$X$2:$Y48,2,false)) -> ... | L28: =if(B28=0,"...",K28/IF(G28="DOLARES",1,Q28)) -> ... | P28: =if(B28=0,"...",$H28*(IF(D28="ABIERTA",K28,J28)*(1-VLOOKUP(A28,Config!$A$3:$B$5,2,FALSE)))/100) -> ... | S28: =if(B28=0,"...",P28/M28-1) -> ... | T28: =if(B28=0,"...",P28-M28) -> ... | U28: =if(B28=0,"...",R28/O28-1) -> ... | V28: =if(B28=0,"...",R28-O28) -> ... | Y28: =if(X28=0,"...",VLOOKUP("*"&X28&"*",$AN$2:$AO54,2,false)) -> ... | Z28: =if(X28=0,"...",sumifs($H$2:$H55,$B$2:$B55,X28,$D$2:$D55,"ABIERTA")) -> ... | AA28: =if(X28=0,"",AC28/$AH$18) | AB28: =if(Z28=0,"...",if(X28=0,"...",sumifs($O$2:$O55,$B$2:$B55,X28,$D$2:$D55,"ABIERTA")/Z28)) -> ... | AC28: =if(X28=0,"...",sumifs($R$2:$R55,$B$2:$B55,X28,$D$2:$D55,"ABIERTA")) -> ... | AD28: =if(Z28=0,"...",if(X28=0,"...",AE28/(AC28-AE28))) -> ... | AE28: =if(Z28=0,"...",if(X28=0,"...",sumifs($V$2:$V55,$B$2:$B55,X28,$D$2:$D55,"ABIERTA"))) -> ... | AL28: =IF($AN28="","...", Left(RIGHT($AN28,LEN($AN28)-FIND("*", $AN28)),FIND("*", RIGHT($AN28,LEN($AN28)-FIND("*", $AN28)))-1)) -> ... | AM28: =IF($AN28="","...", RIGHT($AQ28,LEN($AQ28)-FIND(" ", $AQ28))) -> ...
AL29: =IF($AN29="","...", Left(RIGHT($AN29,LEN($AN29)-FIND("*", $AN29)),FIND("*", RIGHT($AN29,LEN($AN29)-FIND("*", $AN29)))-1)) -> ... | AM29: =IF($AN29="","...", RIGHT($AQ29,LEN($AQ29)-FIND(" ", $AQ29))) -> ...

Sheet Bonds
B1: 10/30/23 | C1: Apertura | D1: Estado | E1: Cierre | F1: Dias | G1: Moneda | H1: Unidades | I1: Valor Compra | J1: Valor Venta | K1: Valor Actual | L1: Valor Actual $ | M1: Total Compra | N1: CCL Compra | O1: Total Compra $ | P1: Total Venta | Q1: CCL Venta | R1: Total Venta $ | S1: Ganancias (%) | T1: Ganancias Bruta | U1: Gan. $% | V1: Ganancia $ | X1: Ticker | Z1: Unidades | AA1: % Cartera | AB1: PPC USD | AC1: PPC | AD1: T. Ab USD | AE1: T. Ab | AF1: Gan. USD (%) | AG1: Gan. Pesos % | AH1: Gan. Tot. USD | AI1: Gan. Tot. Pesos | AR1: BONOS USD
A2: IOL | B2: AL30D | C2: 45057 | D2: ABIERTA | F2: =if(B2=0,"...", IF(E2=0,today()-C2,E2-C2)) -> 939 | G2: PESOS | H2: 1076 | I2: 9109 | K2: =if(B2=0,"...",IF($G2="PESOS",Q2,1)*SUBSTITUTE(VLOOKUP(B2,$X$2:$Y646,2,false),".",",")) -> 83550.96 | L2: =if(B2=0,"...",SUBSTITUTE(VLOOKUP(B2,$X$2:$Y646,2,false),".",",")) -> 65,84 | M2: =if(B2=0,"...",$H2*I2/IF(G2="DOLARES",1,100)) -> 98012.84 | N2: =VLOOKUP($C2,CCLHistory!$A$6:$B646,2,FALSE) -> 453,96 | O2: =M2/IF(G2="DOLARES",1,N2) -> 215.90634 | P2: =if(B2=0,"...",$H2*(IF(D2="ABIERTA",L2,J2)*IF(G2="DOLARES",1,Q2)*(1-VLOOKUP(A2,Config!$A$3:$B$5,2,FALSE)))/IF(G2="DOLARES",1,100)) -> 898963.38 | Q2: =IF(D2="ABIERTA",Config!$D$4,VLOOKUP(E2,CCLHistory!$A$6:$B646,2,FALSE)) -> 1269 | R2: =if(B2=0,"...",$H2*(IF(D2="ABIERTA",L2,J2)*(1-VLOOKUP(A2,Config!$A$3:$B$5,2,FALSE)))/100) -> 708.40298 | S2: =if(B2=0,"...",P2/M2-1) -> 8.171894 | T2: =if(B2=0,"...",P2-M2) -> 800950.54 | U2: =if(B2=0,"...",R2/O2-1) -> 2.2810662 | V2: =if(B2=0,"...",R2-O2) -> 492.49664 | X2: {=Unique(B2:B646)} -> AL30D | Y2: =if(X2=0,"...",VLOOKUP("*"&X2&"*",$AR$2:$AS646,2,false)) -> 65.84 | Z2: =if(X2=0,"...",sumifs($H$2:$H646,$B$2:$B646,X2,$D$2:$D646,"ABIERTA")) -> 2036 | AA2: =if(X2=0,"",AD2/$AL$18) -> 1 | AB2: =if(Z2=0,"...",if(X2=0,"...",sumifs($O$2:$O646,$B$2:$B646,X2,$D$2:$D646,"ABIERTA")/Z2)) -> 0.23426244 | AC2: =if(Z2=0,"...",if(X2=0,"...",sumifs($M$2:$M646,$B$2:$B646,X2,$D$2:$D646,"ABIERTA")/Z2)) -> 120.69676 | AD2: =if(X2=0,"...",sumifs($R$2:$R646,$B$2:$B646,X2,$D$2:$D646,"ABIERTA")) -> 1340.4354 | AE2: =if(X2=0,"...",sumifs($P$2:$P646,$B$2:$B646,X2,$D$2:$D646,"ABIERTA")) -> 1701012.5 | AF2: =if(Z2=0,"...",if(X2=0,"...",AH2/(AD2-AH2))) -> 1.8103826 | AG2: =if(X2=0,"...",if(X2=0,"...",AI2/(AE2-AI2))) -> 5.9220403 | AH2: =if(Z2=0,"...",if(X2=0,"...",sumifs($V$2:$V646,$B$2:$B646,X2,$D$2:$D646,"ABIERTA"))) -> 863.47705 | AI2: =if(X2=0,"...",if(Z2=0,"...",sumifs($T$2:$T646,$B$2:$B646,X2,$D$2:$D646,"ABIERTA"))) -> 1455273.9 | AR2: =IFERROR(__xludf.DUMMYFUNCTION("QUERY(IMPORTHTML(DataImports!B5,DataImports!D5,1),""select Col1, Col2"",1)"),"Símbolo") -> Símbolo | AS2: =IFERROR(__xludf.DUMMYFUNCTION("""COMPUTED_VALUE"""),"Último Operado") -> Último Operado
A3: IOL | B3: AL30D | C3: 45100 | D3: ABIERTA | F3: =if(B3=0,"...", IF(E3=0,today()-C3,E3-C3)) -> 896 | G3: PESOS | H3: 384 | I3: 12759.5 | K3: =if(B3=0,"...",IF($G3="PESOS",Q3,1)*SUBSTITUTE(VLOOKUP(B3,$X$2:$Y647,2,false),".",",")) -> 83550.96 | L3: =if(B3=0,"...",SUBSTITUTE(VLOOKUP(B3,$X$2:$Y647,2,false),".",",")) -> 65,84 | M3: =if(B3=0,"...",$H3*I3/IF(G3="DOLARES",1,100)) -> 48996.48 | N3: =VLOOKUP($C3,CCLHistory!$A$6:$B646,2,FALSE) -> 520,02 | O3: =M3/IF(G3="DOLARES",1,N3) -> 94.220376 | P3: =if(B3=0,"...",$H3*(IF(D3="ABIERTA",L3,J3)*IF(G3="DOLARES",1,Q3)*(1-VLOOKUP(A3,Config!$A$3:$B$5,2,FALSE)))/IF(G3="DOLARES",1,100)) -> 320819.64 | Q3: =IF(D3="ABIERTA",Config!$D$4,VLOOKUP(E3,CCLHistory!$A$6:$B646,2,FALSE)) -> 1269 | R3: =if(B3=0,"...",$H3*(IF(D3="ABIERTA",L3,J3)*(1-VLOOKUP(A3,Config!$A$3:$B$5,2,FALSE)))/100) -> 252.81296 | S3: =if(B3=0,"...",P3/M3-1) -> 5.5478101 | T3: =if(B3=0,"...",P3-M3) -> 271823.16 | U3: =if(B3=0,"...",R3/O3-1) -> 1.683209 | V3: =if(B3=0,"...",R3-O3) -> 158.59258 | Y3: =if(X3=0,"...",VLOOKUP("*"&X3&"*",$AR$2:$AS647,2,false)) -> ... | Z3: =if(X3=0,"...",sumifs($H$2:$H647,$B$2:$B647,X3,$D$2:$D647,"ABIERTA")) -> ... | AA3: =if(X3=0,"",AD3/$AL$18) | AB3: =if(Z3=0,"...",if(X3=0,"...",sumifs($O$2:$O647,$B$2:$B647,X3,$D$2:$D647,"ABIERTA")/Z3)) -> ... | AD3: =if(X3=0,"...",sumifs($R$2:$R647,$B$2:$B647,X3,$D$2:$D647,"ABIERTA")) -> ... | AF3: =if(Z3=0,"...",if(X3=0,"...",AH3/(AD3-AH3))) -> ... | AH3: =if(Z3=0,"...",if(X3=0,"...",sumifs($V$2:$V647,$B$2:$B647,X3,$D$2:$D647,"ABIERTA"))) -> ... | AI3: =if(X3=0,"...",if(Z3=0,"...",sumifs($T$2:$T647,$B$2:$B647,X3,$D$2:$D647,"ABIERTA"))) -> ... | AR3: =IFERROR(__xludf.DUMMYFUNCTION("""COMPUTED_VALUE"""),"* AE38 *") -> * AE38 * | AS3: =IFERROR(__xludf.DUMMYFUNCTION("""COMPUTED_VALUE"""),114600.0) -> 114600
A4: IOL | B4: AL30D | C4: 45147 | D4: ABIERTA | F4: =if(B4=0,"...", IF(E4=0,today()-C4,E4-C4)) -> 849 | G4: PESOS | H4: 576 | I4: 17140.5 | K4: =if(B4=0,"...",IF($G4="PESOS",Q4,1)*SUBSTITUTE(VLOOKUP(B4,$X$2:$Y648,2,false),".",",")) -> 83550.96 | L4: =if(B4=0,"...",SUBSTITUTE(VLOOKUP(B4,$X$2:$Y648,2,false),".",",")) -> 65,84 | M4: =if(B4=0,"...",$H4*I4/IF(G4="DOLARES",1,100)) -> 98729.28 | N4: =VLOOKUP($C4,CCLHistory!$A$6:$B646,2,FALSE) -> 591,79 | O4: =M4/IF(G4="DOLARES",1,N4) -> 166.83161 | P4: =if(B4=0,"...",$H4*(IF(D4="ABIERTA",L4,J4)*IF(G4="DOLARES",1,Q4)*(1-VLOOKUP(A4,Config!$A$3:$B$5,2,FALSE)))/IF(G4="DOLARES",1,100)) -> 481229.47 | Q4: =IF(D4="ABIERTA",Config!$D$4,VLOOKUP(E4,CCLHistory!$A$6:$B646,2,FALSE)) -> 1269 | R4: =if(B4=0,"...",$H4*(IF(D4="ABIERTA",L4,J4)*(1-VLOOKUP(A4,Config!$A$3:$B$5,2,FALSE)))/100) -> 379.21944 | S4: =if(B4=0,"...",P4/M4-1) -> 3.8742325 | T4: =if(B4=0,"...",P4-M4) -> 382500.19 | U4: =if(B4=0,"...",R4/O4-1) -> 1.273067 | V4: =if(B4=0,"...",R4-O4) -> 212.38783 | Y4: =if(X4=0,"...",VLOOKUP("*"&X4&"*",$AR$2:$AS648,2,false)) -> ... | Z4: =if(X4=0,"...",sumifs($H$2:$H648,$B$2:$B648,X4,$D$2:$D648,"ABIERTA")) -> ... | AA4: =if(X4=0,"",AD4/$AL$18) | AB4: =if(Z4=0,"...",if(X4=0,"...",sumifs($O$2:$O648,$B$2:$B648,X4,$D$2:$D648,"ABIERTA")/Z4)) -> ... | AD4: =if(X4=0,"...",sumifs($R$2:$R648,$B$2:$B648,X4,$D$2:$D648,"ABIERTA")) -> ... | AF4: =if(Z4=0,"...",if(X4=0,"...",AH4/(AD4-AH4))) -> ... | AH4: =if(Z4=0,"...",if(X4=0,"...",sumifs($V$2:$V648,$B$2:$B648,X4,$D$2:$D648,"ABIERTA"))) -> ... | AI4: =if(X4=0,"...",if(Z4=0,"...",sumifs($T$2:$T648,$B$2:$B648,X4,$D$2:$D648,"ABIERTA"))) -> ... | AR4: =IFERROR(__xludf.DUMMYFUNCTION("""COMPUTED_VALUE"""),"* AE38C *") -> * AE38C * | AS4: =IFERROR(__xludf.DUMMYFUNCTION("""COMPUTED_VALUE"""),76.0) -> 76
K5: =if(B5=0,"...",IF($G5="PESOS",Q5,1)*SUBSTITUTE(VLOOKUP(B5,$X$2:$Y649,2,false),".",",")) -> ... | L5: =if(B5=0,"...",SUBSTITUTE(VLOOKUP(B5,$X$2:$Y649,2,false),".",",")) -> ... | N5: {=if($B5=0,"...",INDEX(IMPORTFROMWEB(CONCAT(DataImports!$B$3,TEXT($C5,DataImports!$C$3)),DataImports!$D$3),1))} -> ... | P5: =if(B5=0,"...",$H5*(IF(D5="ABIERTA",L5,J5)*IF(G5="DOLARES",1,Q5)*(1-VLOOKUP(A5,Config!$A$3:$B$5,2,FALSE)))/IF(G5="DOLARES",1,100)) -> ... | Q5: {=if(B5=0,"...",IF($D5="ABIERTA",Config!$D$4,INDEX(IMPORTFROMWEB(CONCAT(DataImports!$B$3,TEXT($E5,DataImports!$C$3)),DataImports!$D$3),1)))} -> ... | R5: =if(B5=0,"...",$H5*(IF(D5="ABIERTA",L5,J5)*(1-VLOOKUP(A5,Config!$A$3:$B$5,2,FALSE)))/100) -> ... | Y5: =if(X5=0,"...",VLOOKUP("*"&X5&"*",$AR$2:$AS649,2,false)) -> ... | Z5: =if(X5=0,"...",sumifs($H$2:$H649,$B$2:$B649,X5,$D$2:$D649,"ABIERTA")) -> ... | AA5: =if(X5=0,"",AD5/$AL$18) | AB5: =if(Z5=0,"...",if(X5=0,"...",sumifs($O$2:$O649,$B$2:$B649,X5,$D$2:$D649,"ABIERTA")/Z5)) -> ... | AD5: =if(X5=0,"...",sumifs($R$2:$R649,$B$2:$B649,X5,$D$2:$D649,"ABIERTA")) -> ... | AF5: =if(Z5=0,"...",if(X5=0,"...",AH5/(AD5-AH5))) -> ... | AH5: =if(Z5=0,"...",if(X5=0,"...",sumifs($V$2:$V649,$B$2:$B649,X5,$D$2:$D649,"ABIERTA"))) -> ... | AI5: =if(X5=0,"...",if(Z5=0,"...",sumifs($T$2:$T649,$B$2:$B649,X5,$D$2:$D649,"ABIERTA"))) -> ... | AR5: =IFERROR(__xludf.DUMMYFUNCTION("""COMPUTED_VALUE"""),"* AE38D *") -> * AE38D * | AS5: =IFERROR(__xludf.DUMMYFUNCTION("""COMPUTED_VALUE"""),78.2) -> 78.2
K6: =if(B6=0,"...",IF($G6="PESOS",Q6,1)*SUBSTITUTE(VLOOKUP(B6,$X$2:$Y650,2,false),".",",")) -> ... | L6: =if(B6=0,"...",SUBSTITUTE(VLOOKUP(B6,$X$2:$Y650,2,false),".",",")) -> ... | N6: {=if($B6=0,"...",INDEX(IMPORTFROMWEB(CONCAT(DataImports!$B$3,TEXT($C6,DataImports!$C$3)),DataImports!$D$3),1))} -> ... | P6: =if(B6=0,"...",$H6*(IF(D6="ABIERTA",L6,J6)*IF(G6="DOLARES",1,Q6)*(1-VLOOKUP(A6,Config!$A$3:$B$5,2,FALSE)))/IF(G6="DOLARES",1,100)) -> ... | Q6: {=if(B6=0,"...",IF($D6="ABIERTA",Config!$D$4,INDEX(IMPORTFROMWEB(CONCAT(DataImports!$B$3,TEXT($E6,DataImports!$C$3)),DataImports!$D$3),1)))} -> ... | R6: =if(B6=0,"...",$H6*(IF(D6="ABIERTA",L6,J6)*(1-VLOOKUP(A6,Config!$A$3:$B$5,2,FALSE)))/100) -> ... | Y6: =if(X6=0,"...",VLOOKUP("*"&X6&"*",$AR$2:$AS650,2,false)) -> ... | Z6: =if(X6=0,"...",sumifs($H$2:$H650,$B$2:$B650,X6,$D$2:$D650,"ABIERTA")) -> ... | AA6: =if(X6=0,"",AD6/$AL$18) | AB6: =if(Z6=0,"...",if(X6=0,"...",sumifs($O$2:$O650,$B$2:$B650,X6,$D$2:$D650,"ABIERTA")/Z6)) -> ... | AD6: =if(X6=0,"...",sumifs($R$2:$R650,$B$2:$B650,X6,$D$2:$D650,"ABIERTA")) -> ... | AF6: =if(Z6=0,"...",if(X6=0,"...",AH6/(AD6-AH6))) -> ... | AH6: =if(Z6=0,"...",if(X6=0,"...",sumifs($V$2:$V650,$B$2:$B650,X6,$D$2:$D650,"ABIERTA"))) -> ... | AI6: =if(X6=0,"...",if(Z6=0,"...",sumifs($T$2:$T650,$B$2:$B650,X6,$D$2:$D650,"ABIERTA"))) -> ... | AR6: =IFERROR(__xludf.DUMMYFUNCTION("""COMPUTED_VALUE"""),"* AL29 *") -> * AL29 * | AS6: =IFERROR(__xludf.DUMMYFUNCTION("""COMPUTED_VALUE"""),101770.0) -> 101770
K7: =if(B7=0,"...",IF($G7="PESOS",Q7,1)*SUBSTITUTE(VLOOKUP(B7,$X$2:$Y651,2,false),".",",")) -> ... | L7: =if(B7=0,"...",SUBSTITUTE(VLOOKUP(B7,$X$2:$Y651,2,false),".",",")) -> ... | N7: {=if($B7=0,"...",INDEX(IMPORTFROMWEB(CONCAT(DataImports!$B$3,TEXT($C7,DataImports!$C$3)),DataImports!$D$3),1))} -> ... | P7: =if(B7=0,"...",$H7*(IF(D7="ABIERTA",L7,J7)*IF(G7="DOLARES",1,Q7)*(1-VLOOKUP(A7,Config!$A$3:$B$5,2,FALSE)))/IF(G7="DOLARES",1,100)) -> ... | Q7: {=if(B7=0,"...",IF($D7="ABIERTA",Config!$D$4,INDEX(IMPORTFROMWEB(CONCAT(DataImports!$B$3,TEXT($E7,DataImports!$C$3)),DataImports!$D$3),1)))} -> ... | R7: =if(B7=0,"...",$H7*(IF(D7="ABIERTA",L7,J7)*(1-VLOOKUP(A7,Config!$A$3:$B$5,2,FALSE)))/100) -> ... | S7: =if(B7=0,"...",P7/M7-1) -> ... | T7: =if(B7=0,"...",P7-M7) -> ... | U7: =if(B7=0,"...",R7/O7-1) -> ... | V7: =if(B7=0,"...",R7-O7) -> ... | Y7: =if(X7=0,"...",VLOOKUP("*"&X7&"*",$AR$2:$AS651,2,false)) -> ... | Z7: =if(X7=0,"...",sumifs($H$2:$H651,$B$2:$B651,X7,$D$2:$D651,"ABIERTA")) -> ... | AA7: =if(X7=0,"",AD7/$AL$18) | AB7: =if(Z7=0,"...",if(X7=0,"...",sumifs($O$2:$O651,$B$2:$B651,X7,$D$2:$D651,"ABIERTA")/Z7)) -> ... | AD7: =if(X7=0,"...",sumifs($R$2:$R651,$B$2:$B651,X7,$D$2:$D651,"ABIERTA")) -> ... | AF7: =if(Z7=0,"...",if(X7=0,"...",AH7/(AD7-AH7))) -> ... | AH7: =if(Z7=0,"...",if(X7=0,"...",sumifs($V$2:$V651,$B$2:$B651,X7,$D$2:$D651,"ABIERTA"))) -> ... | AI7: =if(X7=0,"...",if(Z7=0,"...",sumifs($T$2:$T651,$B$2:$B651,X7,$D$2:$D651,"ABIERTA"))) -> ... | AR7: =IFERROR(__xludf.DUMMYFUNCTION("""COMPUTED_VALUE"""),"* AL29C *") -> * AL29C * | AS7: =IFERROR(__xludf.DUMMYFUNCTION("""COMPUTED_VALUE"""),68.16) -> 68.16
K8: =if(B8=0,"...",IF($G8="PESOS",Q8,1)*SUBSTITUTE(VLOOKUP(B8,$X$2:$Y652,2,false),".",",")) -> ... | L8: =if(B8=0,"...",SUBSTITUTE(VLOOKUP(B8,$X$2:$Y652,2,false),".",",")) -> ... | N8: {=if($B8=0,"...",INDEX(IMPORTFROMWEB(CONCAT(DataImports!$B$3,TEXT($C8,DataImports!$C$3)),DataImports!$D$3),1))} -> ... | P8: =if(B8=0,"...",$H8*(IF(D8="ABIERTA",L8,J8)*IF(G8="DOLARES",1,Q8)*(1-VLOOKUP(A8,Config!$A$3:$B$5,2,FALSE)))/IF(G8="DOLARES",1,100)) -> ... | Q8: {=if(B8=0,"...",IF($D8="ABIERTA",Config!$D$4,INDEX(IMPORTFROMWEB(CONCAT(DataImports!$B$3,TEXT($E8,DataImports!$C$3)),DataImports!$D$3),1)))} -> ... | R8: =if(B8=0,"...",$H8*(IF(D8="ABIERTA",L8,J8)*(1-VLOOKUP(A8,Config!$A$3:$B$5,2,FALSE)))/100) -> ... | S8: =if(B8=0,"...",P8/M8-1) -> ... | T8: =if(B8=0,"...",P8-M8) -> ... | U8: =if(B8=0,"...",R8/O8-1) -> ... | V8: =if(B8=0,"...",R8-O8) -> ... | Y8: =if(X8=0,"...",VLOOKUP("*"&X8&"*",$AR$2:$AS652,2,false)) -> ... | Z8: =if(X8=0,"...",sumifs($H$2:$H652,$B$2:$B652,X8,$D$2:$D652,"ABIERTA")) -> ... | AA8: =if(X8=0,"",AD8/$AL$18) | AB8: =if(Z8=0,"...",if(X8=0,"...",sumifs($O$2:$O652,$B$2:$B652,X8,$D$2:$D652,"ABIERTA")/Z8)) -> ... | AD8: =if(X8=0,"...",sumifs($R$2:$R652,$B$2:$B652,X8,$D$2:$D652,"ABIERTA")) -> ... | AF8: =if(Z8=0,"...",if(X8=0,"...",AH8/(AD8-AH8))) -> ... | AH8: =if(Z8=0,"...",if(X8=0,"...",sumifs($V$2:$V652,$B$2:$B652,X8,$D$2:$D652,"ABIERTA"))) -> ... | AI8: =if(X8=0,"...",if(Z8=0,"...",sumifs($T$2:$T652,$B$2:$B652,X8,$D$2:$D652,"ABIERTA"))) -> ... | AR8: =IFERROR(__xludf.DUMMYFUNCTION("""COMPUTED_VALUE"""),"* AL29D *") -> * AL29D * | AS8: =IFERROR(__xludf.DUMMYFUNCTION("""COMPUTED_VALUE"""),69.48) -> 69.48
K9: =if(B9=0,"...",IF($G9="PESOS",Q9,1)*SUBSTITUTE(VLOOKUP(B9,$X$2:$Y653,2,false),".",",")) -> ... | L9: =if(B9=0,"...",SUBSTITUTE(VLOOKUP(B9,$X$2:$Y653,2,false),".",",")) -> ... | N9: {=if($B9=0,"...",INDEX(IMPORTFROMWEB(CONCAT(DataImports!$B$3,TEXT($C9,DataImports!$C$3)),DataImports!$D$3),1))} -> ... | P9: =if(B9=0,"...",$H9*(IF(D9="ABIERTA",L9,J9)*IF(G9="DOLARES",1,Q9)*(1-VLOOKUP(A9,Config!$A$3:$B$5,2,FALSE)))/IF(G9="DOLARES",1,100)) -> ... | Q9: {=if(B9=0,"...",IF($D9="ABIERTA",Config!$D$4,INDEX(IMPORTFROMWEB(CONCAT(DataImports!$B$3,TEXT($E9,DataImports!$C$3)),DataImports!$D$3),1)))} -> ... | R9: =if(B9=0,"...",$H9*(IF(D9="ABIERTA",L9,J9)*(1-VLOOKUP(A9,Config!$A$3:$B$5,2,FALSE)))/100) -> ... | S9: =if(B9=0,"...",P9/M9-1) -> ... | T9: =if(B9=0,"...",P9-M9) -> ... | U9: =if(B9=0,"...",R9/O9-1) -> ... | V9: =if(B9=0,"...",R9-O9) -> ... | Y9: =if(X9=0,"...",VLOOKUP("*"&X9&"*",$AR$2:$AS653,2,false)) -> ... | Z9: =if(X9=0,"...",sumifs($H$2:$H653,$B$2:$B653,X9,$D$2:$D653,"ABIERTA")) -> ... | AA9: =if(X9=0,"",AD9/$AL$18) | AB9: =if(Z9=0,"...",if(X9=0,"...",sumifs($O$2:$O653,$B$2:$B653,X9,$D$2:$D653,"ABIERTA")/Z9)) -> ... | AD9: =if(X9=0,"...",sumifs($R$2:$R653,$B$2:$B653,X9,$D$2:$D653,"ABIERTA")) -> ... | AF9: =if(Z9=0,"...",if(X9=0,"...",AH9/(AD9-AH9))) -> ... | AH9: =if(Z9=0,"...",if(X9=0,"...",sumifs($V$2:$V653,$B$2:$B653,X9,$D$2:$D653,"ABIERTA"))) -> ... | AI9: =if(X9=0,"...",if(Z9=0,"...",sumifs($T$2:$T653,$B$2:$B653,X9,$D$2:$D653,"ABIERTA"))) -> ... | AR9: =IFERROR(__xludf.DUMMYFUNCTION("""COMPUTED_VALUE"""),"* AL30 *") -> * AL30 * | AS9: =IFERROR(__xludf.DUMMYFUNCTION("""COMPUTED_VALUE"""),96460.0) -> 96460
K10: =if(B10=0,"...",IF($G10="PESOS",Q10,1)*SUBSTITUTE(VLOOKUP(B10,$X$2:$Y654,2,false),".",",")) -> ... | L10: =if(B10=0,"...",SUBSTITUTE(VLOOKUP(B10,$X$2:$Y654,2,false),".",",")) -> ... | N10: {=if($B10=0,"...",INDEX(IMPORTFROMWEB(CONCAT(DataImports!$B$3,TEXT($C10,DataImports!$C$3)),DataImports!$D$3),1))} -> ... | P10: =if(B10=0,"...",$H10*(IF(D10="ABIERTA",L10,J10)*IF(G10="DOLARES",1,Q10)*(1-VLOOKUP(A10,Config!$A$3:$B$5,2,FALSE)))/IF(G10="DOLARES",1,100)) -> ... | Q10: {=if(B10=0,"...",IF($D10="ABIERTA",Config!$D$4,INDEX(IMPORTFROMWEB(CONCAT(DataImports!$B$3,TEXT($E10,DataImports!$C$3)),DataImports!$D$3),1)))} -> ... | R10: =if(B10=0,"...",$H10*(IF(D10="ABIERTA",L10,J10)*(1-VLOOKUP(A10,Config!$A$3:$B$5,2,FALSE)))/100) -> ... | S10: =if(B10=0,"...",P10/M10-1) -> ... | T10: =if(B10=0,"...",P10-M10) -> ... | U10: =if(B10=0,"...",R10/O10-1) -> ... | V10: =if(B10=0,"...",R10-O10) -> ... | Y10: =if(X10=0,"...",VLOOKUP("*"&X10&"*",$AR$2:$AS654,2,false)) -> ... | Z10: =if(X10=0,"...",sumifs($H$2:$H654,$B$2:$B654,X10,$D$2:$D654,"ABIERTA")) -> ... | AA10: =if(X10=0,"",AD10/$AL$18) | AB10: =if(Z10=0,"...",if(X10=0,"...",sumifs($O$2:$O654,$B$2:$B654,X10,$D$2:$D654,"ABIERTA")/Z10)) -> ... | AD10: =if(X10=0,"...",sumifs($R$2:$R654,$B$2:$B654,X10,$D$2:$D654,"ABIERTA")) -> ... | AF10: =if(Z10=0,"...",if(X10=0,"...",AH10/(AD10-AH10))) -> ... | AH10: =if(Z10=0,"...",if(X10=0,"...",sumifs($V$2:$V654,$B$2:$B654,X10,$D$2:$D654,"ABIERTA"))) -> ... | AI10: =if(X10=0,"...",if(Z10=0,"...",sumifs($T$2:$T654,$B$2:$B654,X10,$D$2:$D654,"ABIERTA"))) -> ... | AR10: =IFERROR(__xludf.DUMMYFUNCTION("""COMPUTED_VALUE"""),"* AL30C *") -> * AL30C * | AS10: =IFERROR(__xludf.DUMMYFUNCTION("""COMPUTED_VALUE"""),64.23) -> 64.23
K11: =if(B11=0,"...",IF($G11="PESOS",Q11,1)*SUBSTITUTE(VLOOKUP(B11,$X$2:$Y655,2,false),".",",")) -> ... | L11: =if(B11=0,"...",SUBSTITUTE(VLOOKUP(B11,$X$2:$Y655,2,false),".",",")) -> ... | N11: {=if($B11=0,"...",INDEX(IMPORTFROMWEB(CONCAT(DataImports!$B$3,TEXT($C11,DataImports!$C$3)),DataImports!$D$3),1))} -> ... | P11: =if(B11=0,"...",$H11*(IF(D11="ABIERTA",L11,J11)*IF(G11="DOLARES",1,Q11)*(1-VLOOKUP(A11,Config!$A$3:$B$5,2,FALSE)))/IF(G11="DOLARES",1,100)) -> ... | Q11: {=if(B11=0,"...",IF($D11="ABIERTA",Config!$D$4,INDEX(IMPORTFROMWEB(CONCAT(DataImports!$B$3,TEXT($E11,DataImports!$C$3)),DataImports!$D$3),1)))} -> ... | R11: =if(B11=0,"...",$H11*(IF(D11="ABIERTA",L11,J11)*(1-VLOOKUP(A11,Config!$A$3:$B$5,2,FALSE)))/100) -> ... | S11: =if(B11=0,"...",P11/M11-1) -> ... | T11: =if(B11=0,"...",P11-M11) -> ... | U11: =if(B11=0,"...",R11/O11-1) -> ... | V11: =if(B11=0,"...",R11-O11) -> ... | Y11: =if(X11=0,"...",VLOOKUP("*"&X11&"*",$AR$2:$AS655,2,false)) -> ... | Z11: =if(X11=0,"...",sumifs($H$2:$H655,$B$2:$B655,X11,$D$2:$D655,"ABIERTA")) -> ... | AA11: =if(X11=0,"",AD11/$AL$18) | AB11: =if(Z11=0,"...",if(X11=0,"...",sumifs($O$2:$O655,$B$2:$B655,X11,$D$2:$D655,"ABIERTA")/Z11)) -> ... | AD11: =if(X11=0,"...",sumifs($R$2:$R655,$B$2:$B655,X11,$D$2:$D655,"ABIERTA")) -> ... | AF11: =if(Z11=0,"...",if(X11=0,"...",AH11/(AD11-AH11))) -> ... | AH11: =if(Z11=0,"...",if(X11=0,"...",sumifs($V$2:$V655,$B$2:$B655,X11,$D$2:$D655,"ABIERTA"))) -> ... | AI11: =if(X11=0,"...",if(Z11=0,"...",sumifs($T$2:$T655,$B$2:$B655,X11,$D$2:$D655,"ABIERTA"))) -> ... | AR11: =IFERROR(__xludf.DUMMYFUNCTION("""COMPUTED_VALUE"""),"* AL30D *") -> * AL30D * | AS11: =IFERROR(__xludf.DUMMYFUNCTION("""COMPUTED_VALUE"""),65.84) -> 65.84
K12: =if(B12=0,"...",IF($G12="PESOS",Q12,1)*SUBSTITUTE(VLOOKUP(B12,$X$2:$Y656,2,false),".",",")) -> ... | L12: =if(B12=0,"...",SUBSTITUTE(VLOOKUP(B12,$X$2:$Y656,2,false),".",",")) -> ... | N12: {=if($B12=0,"...",INDEX(IMPORTFROMWEB(CONCAT(DataImports!$B$3,TEXT($C12,DataImports!$C$3)),DataImports!$D$3),1))} -> ... | P12: =if(B12=0,"...",$H12*(IF(D12="ABIERTA",L12,J12)*IF(G12="DOLARES",1,Q12)*(1-VLOOKUP(A12,Config!$A$3:$B$5,2,FALSE)))/IF(G12="DOLARES",1,100)) -> ... | Q12: {=if(B12=0,"...",IF($D12="ABIERTA",Config!$D$4,INDEX(IMPORTFROMWEB(CONCAT(DataImports!$B$3,TEXT($E12,DataImports!$C$3)),DataImports!$D$3),1)))} -> ... | R12: =if(B12=0,"...",$H12*(IF(D12="ABIERTA",L12,J12)*(1-VLOOKUP(A12,Config!$A$3:$B$5,2,FALSE)))/100) -> ... | S12: =if(B12=0,"...",P12/M12-1) -> ... | T12: =if(B12=0,"...",P12-M12) -> ... | U12: =if(B12=0,"...",R12/O12-1) -> ... | V12: =if(B12=0,"...",R12-O12) -> ... | Y12: =if(X12=0,"...",VLOOKUP("*"&X12&"*",$AR$2:$AS656,2,false)) -> ... | Z12: =if(X12=0,"...",sumifs($H$2:$H656,$B$2:$B656,X12,$D$2:$D656,"ABIERTA")) -> ... | AA12: =if(X12=0,"",AD12/$AL$18) | AB12: =if(Z12=0,"...",if(X12=0,"...",sumifs($O$2:$O656,$B$2:$B656,X12,$D$2:$D656,"ABIERTA")/Z12)) -> ... | AD12: =if(X12=0,"...",sumifs($R$2:$R656,$B$2:$B656,X12,$D$2:$D656,"ABIERTA")) -> ... | AF12: =if(Z12=0,"...",if(X12=0,"...",AH12/(AD12-AH12))) -> ... | AH12: =if(Z12=0,"...",if(X12=0,"...",sumifs($V$2:$V656,$B$2:$B656,X12,$D$2:$D656,"ABIERTA"))) -> ... | AI12: =if(X12=0,"...",if(Z12=0,"...",sumifs($T$2:$T656,$B$2:$B656,X12,$D$2:$D656,"ABIERTA"))) -> ... | AR12: =IFERROR(__xludf.DUMMYFUNCTION("""COMPUTED_VALUE"""),"* AL35 *") -> * AL35 * | AS12: =IFERROR(__xludf.DUMMYFUNCTION("""COMPUTED_VALUE"""),109690.0) -> 109690
